Workbook

Sheet SUMMARY 
A2: DAILY TRANSACTIONS GROUP B
B3: NAME OF COMPANY | C3: AED | D3: USD | E3: EURO | F3: REMARKS | G3: AED CREDIT | H3: AED DEBIT | I3: USD CREDIT | J3: USD DEBIT | K3: EUR CREDIT | L3: EUR DEBIT
C4: ='HEDGES MSQ AED '!E100 -> 0 | D4: ='HEDGES MSQ USD'!E100 -> 0 | E4: ='HEDGES MSQ EURO'!E100 -> 0 | F4: CLOSED
A5: 1A | B5: HEDGES GOODS FAB | C5: ='HEDGES FAB AED '!E100 -> 317.31 | D5: ='HEDGES FAB USD'!E100 -> 124.89
F6: CLOSED
A7: 2A | B7: RHINE MSQ | C7: 0 | F7: NA
A8: 2B | B8: RHINE ENBD | C8: 2705.9 | D8: 0 | F8: KYC ISSUE
A9: 2C | B9: RHINE | C9: -4.31 | D9: 17.86 | E9: 0
A10: 2D | B10: RHINE SIB | C10: 142.71 | D10: 0 | F10: KYC ISSUE
A11: 2E | B11: RHINE AJMAN | C11: -4538 | D11: 85.91 | F11: NA
A12: 2F | B12: RHINE ADIB | C12: 895.61 | D12: 0
A14: 1A | B14: RHINE MULTY NBF | C14: ='RHINE MULTY NBF AED'!E100 -> 1091.95
A16: 3A | B16: CARNIFY ENBD | C16: ='CARNIFY ENBD AED'!E326 -> 616.13 | D16: ='CARNIFY ENBD USD '!E100 -> 1.84
A17: 3B | B17: CARNIFY ADIB | C17: ='CARNIFY ADIB AED '!E325 -> 1311.97 | D17: ='CARNIFY ADIB USD'!E100 -> 787.62 | F17: KYC ISSUE
A18: 3C | B18: CARNIFY EIB | C18: ='CARNIFY EIB AED'!E326 -> 128.21
A20: 4A | B20: RED STONE WIO | C20: ='RED STONE WIO AED '!E397 -> -400.002 | D20: ='RED STONE WIO USD'!E143 -> 0.27 | E20: ='RED STONE WIO EUR'!E110 -> 0.42 | M20: CAN'T TRF
A21: 4B | B21: RED STONE ADIB | C21: ='RED STONE ADIB AED '!E100 -> 111.63 | D21: ='RED STONE ADIB USD'!E110 -> 0 | E21: ='RED STONE ADIB EUR'!E110 -> 0 | M21: ACTIVE BUT TL EXPIRED
A23: 5A | B23: IDEA GROVE ADIB | C23: ='IDEA GROVE ADIB AED'!E100 -> 322 | D23: ='IDEA GROVE ADIB USD'!E100 -> 2 | E23: ='IDEA GROVE ADIB EURO'!E100 -> 5
A24: 5B | B24: IDEA GROVE EIB | C24: ='IDEA GROVE EIB AED'!E352 -> 83.82 | D24: =500+100-514.56-54.82-25.73-2.74+89850-11.23-224.62-100-60000-28000-1360+9840-54.82-2.74-9938 -> 0.74 | M24: ISSUE
A25: 5C | B25: IDEA GROVE RAK | C25: ='IDEA GROVE RAK AED'!E100 -> 9250.35 | M25: CHQ
A26: 5D | B26: IDEA GROVE SIB | C26: ='IDEA GROVE SIB AED'!E100 -> 187.98
A28: 6A | B28: AGNIRA WIO | C28: ='AGINRA WIO AED'!E203 -> 1758.71 | D28: ='AGNIRA WIO USD'!E100 -> 0.75 | F28: ASHISH JI
A29: 6B | B29: AGNIRA EIB | C29: ='AGINRA EIB AED '!E131 -> 733.15 | F29: ASHISH JI
A31: 7A | B31: SILVER STONE WIO A/C | C31: ='SILVER STONE WIO AED'!E345 -> 1815.435 | D31: ='SILVER STONE WIO USD'!E99 -> 0 | E31: ='SILVER STONE WIO EUR'!E63 -> 0
A32: 7B | B32: SILVER STONE ADIB A/C | C32: ='SILVER STONE ADIB AED'!E63 -> 108.53 | D32: ='SILVER STONE ADIB USD'!E63 -> 0.35 | E32: ='SILVER STONE ADIB EUR'!E63 -> 0
A33: 7C | B33: SILVER STONE MSQ A/C | C33: ='SILVER STONE MSQ AED '!E100 -> 0
A34: 7D | B34: SILVER STONE ENBD A/C | C34: ='SILVER STONE ENBD AED '!E100 -> 524299.95
A36: 8A | B36: M J S STAR NBF | C36: ='M J S STAR NBF AED '!E100 -> 0.02 | D36: ='M J S STAR NBF USD'!E100 -> 0.01
A37: 8B | B37: M J S STAR RAK | C37: ='M J S STAR RAK AED '!E100 -> 1798.2 | D37: ='M J S STAR RAK USD'!E100 -> 1000 | F37: ONLINE NOT ACTIVATED
A38: 8C | B38: M J S STAR EIB | C38: ='MJS STAR EIB AED'!E237 -> 775.95 | F38: NA
A39: 8D | B39: M J S STAR SIB | C39: ='MJS STAR SIB AED'!E100 -> 1093.16 | D39: ='MJS STAR SIB USD'!E100 -> 286.99
A40: 8E | B40: M J S STAR UBL | C40: 0 | D40: 0
A42: 9A | B42: CAPSLOCK FAB | C42: ='CAPS LOCK FAB AED '!E363 -> 232.64 | D42: ='CAPS LOCK FAB USD'!E100 -> 1.6
A43: 9B | B43: CAPSLOCK SIB | C43: ='CAPSLOCK SIB AED'!E140 -> 113.95 | D43: ='CAPSLOCK SIB USD'!E100 -> -8.58
A44: 9C | B44: CAPSLOCK WIO | C44: ='CAPS LOCK WIO AED '!E100 -> 1455
A46: 10A | B46: FUTURE BRIDGE GT MSQ | C46: ='FUTURE BRIDGE MSQ AED'!E100 -> 1640.95 | D46: 0
A48: 11A | B48: GOLDENOVA GENEAL TRAD. RAK | C48: ='GOLDENOVA RAK AED'!E100 -> 5.6843419e-13
A50: 12A | B50: SHRIJI INTERNATIONAL EIB | C50: ='SHRIJI INT EIB AED'!E244 -> 1191.9 | D50: 0
A52: 13A | B52: ORBIT PLUS SIB | C52: ='ORBIT PLUS SIB'!E209 -> 95.08
A53: 13B | B53: ORBIT PLUS MSQ | C53: 0
A54: 13C | B54: ORBIT PLUS WIO | C54: ='ORBIT PLUS WIO AED'!E209 -> 563.62 | D54: ='ORBIT PLUS WIO USD'!E100 -> 81.83
A55: 13C | B55: ORBIT PLUS ADIB | C55: ='ORBIT PLUS ADIB AED'!E100 -> 57.62 | D55: ='ORBIT PLUS ADIB USD'!E100 -> 1517.38
A56: 13E | B56: ORBIT PLUS UBL | C56: ='ORBIT PLUS UBL AED'!E100 -> 1876.45
A58: 14A | B58: UNNATI ADIB | C58: =6000-472.5-741.9-472.5-4200+2332-2000 -> 445.1 | D58: =200+1132.23+539.16 -> 1871.39
A59: 14B | B59: UNNATI SIB | C59: 200
A60: 14C | B60: UNNATI WIO
B62: TOTAL | C62: =SUM(C4:C61) -> 552478.67 | D62: =SUM(D1:D61) -> 5772.85
A63: DAILY TRANSACTIONS 2 B
A65: 10A | B65: BLACK PEPPER EVENTS WIO | C65: ='BLACK PEPPER WIO AED'!E100 -> 590.61 | D65: ='BLACK PEPPER WIO USD'!E100 -> 0 | F65: NA | M65: NAME CHANGED STARTOSPHERE EVENT
A66: 10B | B66: BLACK PEPPER B.MISR | C66: ='BLACK PEPPER B.MISR AED '!E100 -> 0 | D66: ='BLACK PEPPER B.MISR USD'!E100 -> 0 | F66: ONLINE ISSUE | M66: TL EXPIRED
A67: 10C | B67: BLACK PEPPER EVENTS AJMAN | C67: ='BLACK PEPPER AJMAN AED '!E100 -> -2081 | D67: ='BLACK PEPPER AJMAN USD'!E100 -> 0
A68: 10D | B68: BLACK PEPPER EIB | C68: ='BLACK PEPPER EIB AED '!E100 -> 0 | D68: ='BLACK PEPPER EIB USD'!E100 -> -175
A69: 10E | B69: BLACK PEPPER EVENTS ADIB | C69: ='BLACK PEPPER ADIB AED'!E100 -> 1081.2 | D69: ='BLACK PEPPER ADIB USD'!E100 -> 1.65
A72: 11A | B72: RED FIRE ENBD | C72: ='RED FIRE ENBD AED '!E100 -> -67.42 | D72: ='RED FIRE ENBD USD'!E100 -> 27.89
A73: 11E | B73: RED FIRE WIO | C73: ='RED FIRE WIO AED'!E100 -> -655.21 | D73: ='RED FIRE WIO USD'!E100 -> 0
A74: 11C | B74: RED FIRE NBF | C74: ='RED FIRE NBF AED '!E100 -> 0.01 | D74: ='RED FIRE NBF USD'!E100 -> 25.21
A75: 11D | B75: RED FIRE ADIB | C75: ='RED FIRE ADIB AED'!E100 -> 100.48 | D75: ='RED FIRE ADIB USD'!E100 -> 0 | F75: kyc issue
A76: 11E | B76: RED FIRE AL MASRAF | C76: ='RED FIRE AL MASRAF AED'!E100 -> -191.05 | D76: ='RED FIRE AL MASRAF USD'!E100 -> -912.01 | F76: DISABLED
A78: 12A | B78: PINNACLE COMP. ADIB | C78: ='PINNACLE COMP ADIB AED '!E100 -> 396.75 | D78: ='PINNACLE COMP ADIB USD'!E100 -> 82.31
A79: 12B | B79: PINNACLE COMP. WIO | C79: ='PINNACLE COMP WIO AED'!E100 -> 412.09 | D79: ='PINNACLE COMP WIO USD'!E100 -> 0
A81: 13A | B81: HEDGES TOURISM WIO | C81: ='HEDGES TOURISM WIO AED'!E100 -> 11.09 | D81: ='HEDGES TOURISM WIO USD'!E100 -> 0 | F81: KYC ISSUE
A82: 13B | B82: HEDGES TOURISM NBF | C82: ='HEDGES TOURISM NBF AED'!E100 -> 190.14 | D82: ='HEDGES TOURISM NBF USD'!E100 -> 0 | F82: KYC ISSUE
A83: 13C | B83: HEDGES TOURISM NEO | C83: ='HEDGES TOURISM NEO BIZ AED'!E100 -> 423.44 | D83: ='HEDGES TOURISM NEO BIZ USD'!E100 -> 0 | F83: ONLINE ISSUE
A85: 14A | B85: RHINE BULLIONS RAK | C85: ='RHINE BULLIONS RAK AED'!E290 -> 1219.34 | D85: ='RHINE BULLIONS RAK USD'!E100 -> 77.01 | F85: NOT WORKING
A87: 14B | B87: HEDGES REAL EST NEO | C87: ='HEDGES REAL ESTATE NEO BIZ AED'!E100 -> 0 | D87: ='HEDGES REAL ESTATE NEO BIZ USD '!E100 -> 0 | F87: NOT WORKING
A89: 15A | B89: NET FLOW WIO A/C | C89: ='NET FLOW WIO '!E260 -> 246.42 | D89: ='NET FLOW WIO USD'!E100 -> 0.05 | M89: CLOSING DATE 01.4.26
A90: 15B | B90: NETFLOW EIB | C90: ='NET FLOW EIB AED '!E100 -> 428.21 | M90: CHQ
A91: 15C | B91: NETFLOW RAK | C91: ='NET FLOW RAK AED'!E100 -> 3640.5 | F91: NOT ACTIVE
A92: 15D | B92: NET FLOW ADIB A/C | C92: ='NET FLOW ADIB AED '!E100 -> 76 | D92: 0
A94: 16A | B94: MORPHIS GOODS RAK | C94: ='MORPHIS GOODS RAK AED '!E100 -> 1131.28
A96: 17A | B96: GLUCKRICH EIB | C96: ='GLUCKRICH EIB AED'!E100 -> 0 | F96: CLOSED
A97: 17B | B97: GLUCKRICH INDUSIND | D97: 12054.68
A98: 17C | B98: GLUCKRICH MISR | C98: ='GLUCKRICH MISR AED'!E100 -> 4711.76
A99: 17D | B99: GLUCKRICH NBF | C99: ='GLUCKRICH NBF AED'!E100 -> 1079.62 | D99: ='GLUCKRICH NBF USD'!E100 -> 1.92
A100: 17E | B100: GLUCKRICH HOLDING UBL | C100: =2013-105 -> 1908 | D100: 0
A102: 18A | B102: WEST END ADIB | C102: ='WEST END ADIB AED'!E100 -> 3.75 | D102: 0
A103: 18B | B103: WEST END FAB | C103: ='WEST END FAB AED'!E100 -> 235.53
A104: 18C | B104: WEST END EIB | C104: ='WEST END EIB AED'!E100 -> -1998.35
A105: 18D | B105: WEST END WIO | C105: ='WEST END WIO AED'!E100 -> 1559.88 | D105: 0
A107: 19A | B107: MAPLESKY WIO | C107: ='MAPLE SKY WIO AED '!E100 -> -2.3572966e-10 | D107: ='MAPLE SKY WIO USD '!E100 -> 128 | F107: CLOSED
A108: 19B | B108: MAPLESKY EVENTS MSQ | C108: ='MAPLE SKY MASHREQ AED '!E100 -> 1938.46 | D108: =100+145205+28195-169595+204153+10350-109125-109125+286445-286563.46-27.3+449950-27.3-500-100000-349434 -> 0.94 | E108: 0
A109: 19C | B109: MAPLESKY EVENTS NBF | M109: ACTIVATED
A111: 20A | B111: BLACK PEPPER REAL EST ADIB | C111: ='B P R E ADIB AED '!E100 -> 74.1 | D111: 0 | M111: DIGI PASS ISSUE
A113: 21A | B113: CARGOLIC ADCB | C113: ='CARGOLIC ADCB AED'!E100 -> 0
A114: 21B | B114: CARGOLIC EIB | C114: ='CARGOLIC EIB AED '!E100 -> -4364.05
A115: 21C | B115: CARGOLIC ADIB | C115: ='CARGOLIC ADIB AED '!E100 -> 367.5 | F115: KYC ISSUE
A117: 22A | B117: ALPHA SENTRY ADIB | C117: ='alpha sentry adib aed '!E100 -> 24.5 | D117: ='ALPHA SENTRY ADIB USD'!E100 -> 1078.31 | E117: ='ALPHA SENTRY ADIB EUR'!E100 -> 98.24 | M117: TL EXPIRED | O117: p
A118: 22B | B118: ALPHA SENTRY UBL | C118: ='Alpha sentry UBL AED '!E100 -> 219.45 | M118: TL EXPIRED
A120: 23A | B120: QUANTUM ADIB | C120: 5412 | D120: 1248 | E120: 751 | F120: N/A
A121: 23B | B121: QUANTUM RAK | C121: 0
A123: 24A | B123: PARADE WAVE ADIB | C123: =387.1-131.25+4362-131.25 -> 4486.6 | D123: =1200-1200 -> 0 | F123: N/A | M123: TL EXPIRED
A125: 25A | B125: OPTICORE ADIB | C125: ='OPTICORE ADIB AED'!E100 -> 587.5 | D125: ='OPTICORE ADIB USD'!E100 -> 1188.56 | E125: 0
A126: 25B | B126: OPTICORE ENBD | C126: -2283.75 | D126: 0 | E126: 0
A127: 25C | B127: OPTICORE WIO | C127: ='OPTICORE WIO AED'!E70 -> 300.62 | M127: CLOSED
A128: 25D | B128: OPTICORE SIB | C128: ='OPTICORE SIB'!E100 -> 808.3 | N128: =5000-210-430.5-270.15-420-1.05+200000-202860+250000 -> 250808.3
A130: 26A | B130: AGNICO MSQ | C130: ='AGINCO MSQ AED'!E100 -> 1321.94 | D130: ='AGINCO MSQ USD'!E100 -> 3.02
A132: 27A | B132: SWIFT BRIDGE SIB | C132: ='SWIFT BRIDGE SIB AED'!E210 -> 37.041387 | D132: ='SWIFT BRIDGE SIB USD'!E160 -> 438.88 | M132: PENDING
A133: 27B | B133: SWIFT BRIDGE MSQ | C133: ='SWIFT BRIDGE MSQ AED'!E100 -> 1303.5
A134: 27C | B134: SWIFT BRIDGE ENBD | C134: ='SWIFT BRIDGE ENBD AED'!E100 -> 4738.55 | D134: 0
A135: 27D | B135: SWIFT BRIDGE WIO | C135: ='SWIFT BRIDGE WIO AED'!E135 -> 562 | D135: 0
...

Sheet MJS STAR EIB AED
A1: M J S STAR
A2: EIB AED
A3: DATE | B3: PARTICULAR | C3: DEPOSIT | D3: WITHDRAWAL | E3: BALANCE
B4: OPENING BALANCE | E4: -131.25
A5: 29-08-2025 | B5: FUND RECD FROM ROYAL EN EM ENBD AED | C5: 410257 | E5: =E4+C5-D5 -> 410125.75
A6: 29-08-2025 | B6: TT TRF TO Meteor Balanced Portfolio USD 108325@3.692 | D6: 399935.9 | E6: =E5+C6-D6 -> 10189.85
A7: 02.09.2025 | B7: BANK CHARGES | D7: 125 | E7: =E6+C7-D7 -> 10064.85
A8: 02.09.2025 | B8: BANK CHARGES | D8: 6.25 | E8: =E7+C8-D8 -> 10058.6
A9: 18.09.2025 | B9: CHEQUE DEPOSIT Y A X A TRADING LLC | C9: 915750 | E9: =E8+C9-D9 -> 925808.6
A10: 18.09.2025 | B10: TT TRF TO BLACK PEPPER ADIB AED | D10: 496857 | E10: =E9+C10-D10 -> 428951.6
A11: 18.09.2025 | B11: BANK CHARGES | D11: 21 | E11: =E10+C11-D11 -> 428930.6
A12: 18.09.2025 | B12: TT TRF TO BLACK PEPPER ADIB AED | D12: 426851 | E12: =E11+C12-D12 -> 2079.6
A13: 18.09.2025 | B13: BANK CHARGES | D13: 21 | E13: =E12+C13-D13 -> 2058.6
A14: 19.09.2025 | B14: CHEQUE DEPOSIT (ROHIT MEHTA) | C14: 2307 | E14: =E13+C14-D14 -> 4365.6
A15: 20.09.2025 | B15: FUND RECD FROM ALTARIQ ALMETHALI HEAVY EQUIPMENT | C15: 850000 | E15: =E14+C15-D15 -> 854365.6
A16: 20.09.2025 | B16: TT TRF FROM M J STAR TO BLACK PEPPER ADIB | D16: 598671 | E16: =E15+C16-D16 -> 255694.6
A17: 20.09.2025 | B17: BANK CHARGES | D17: 21 | E17: =E16+C17-D17 -> 255673.6
A18: 20.09.2025 | B18: TT TRF FROM M J STAR TO COMIDA UBL | D18: 253104 | E18: =E17+C18-D18 -> 2569.6
A19: 20.09.2025 | B19: BANK CHARGES | D19: 21 | E19: =E18+C19-D19 -> 2548.6
A20: 20.09.2025 | B20: BANK CHARGES | D20: 4.2 | E20: =E19+C20-D20 -> 2544.4
A21: 22.09.2025 | B21: FUND RECD FROM SILVER CROSS EQUIPMENT | C21: 579640 | E21: =E20+C21-D21 -> 582184.4
A22: 22.09.2025 | B22: TT TRF FROM MJS STAR EIB TO CAPS LOCK FAB | D22: 580213 | E22: =E21+C22-D22 -> 1971.4
A23: 22.09.2025 | B23: BANK CHARGES | D23: 21 | E23: =E22+C23-D23 -> 1950.4
A24: 25.09.2025 | B24: CASH DEPOSIT | C24: 224000 | E24: =E23+C24-D24 -> 225950.4
A25: 25.09.2025 | B25: TT TRF TO CAPS LOCK FAB AED | D25: 8201 | E25: =E24+C25-D25 -> 217749.4
A26: 25.09.2025 | B26: BANK CHARGES | D26: 21 | E26: =E25+C26-D26 -> 217728.4
A27: 25.09.2025 | B27: TT TRF TO BLACK PEPPER ADIB AED | D27: 215410 | E27: =E26+C27-D27 -> 2318.4
A28: 25.09.2025 | B28: BANK CHARGES | D28: 21 | E28: =E27+C28-D28 -> 2297.4
A29: 29.09.2025 | B29: CASH DEPOSIT | C29: 101000 | E29: =E28+C29-D29 -> 103297.4
A30: 29.09.2025 | B30: CASH DEPOSIT | C30: 117000 | E30: =E29+C30-D30 -> 220297.4
A31: 29.09.2025 | B31: CASH DEPOSIT | C31: 100000 | E31: =E30+C31-D31 -> 320297.4
A32: 29.09.2025 | B32: TT TRF TO BLACK PEPPER ADIB AED | D32: 319230 | E32: =E31+C32-D32 -> 1067.4
A33: 29.09.2025 | B33: BANK CHARGES | D33: 25.2 | E33: =E32+C33-D33 -> 1042.2
A34: 02.10.2025 | B34: BANK CHARGES | D34: 300 | E34: =E33+C34-D34 -> 742.2
A35: 02.10.2025 | B35: BANK CHARGES | D35: 125 | E35: =E34+C35-D35 -> 617.2
A36: 02.10.2025 | B36: BANK CHARGES | D36: 15 | E36: =E35+C36-D36 -> 602.2
A37: 02.10.2025 | B37: BANK CHARGES | D37: 6.25 | E37: =E36+C37-D37 -> 595.95
A38: 09.10.2025 | B38: CHEQUE RECD FROM AFFORDABLES FASHION LLC | C38: 100000 | E38: =E37+C38-D38 -> 100595.95
A39: 09.10.2025 | B39: TT TRF TO BLACK PEPPER NBF AED | D39: 99687 | E39: =E38+C39-D39 -> 908.95
A40: 09.10.2025 | B40: BANK CHARGES | D40: 22.05 | E40: =E39+C40-D40 -> 886.9
A41: 14.10.2025 | B41: CASH DEPOSIT | C41: 141000 | E41: =E40+C41-D41 -> 141886.9
A42: 14.10.2025 | B42: CASH DEPOSIT | C42: 71000 | E42: =E41+C42-D42 -> 212886.9
A43: 14.10.2025 | B43: TT TRF TO BLACK PEPPER GT NBF AED | D43: 210350 | E43: =E42+C43-D43 -> 2536.9
A44: 14.10.2025 | B44: BANK CHARGES | D44: 21 | E44: =E43+C44-D44 -> 2515.9
A45: 17.10.2025 | B45: CASH DEPOSIT | C45: 220000 | E45: =E44+C45-D45 -> 222515.9
A46: 17.10.2025 | B46: TT TRF TO BLACK PEPPER GT NBF AED | D46: 220597 | E46: =E45+C46-D46 -> 1918.9
A47: 17.10.2025 | B47: BANK CHARGES | D47: 21 | E47: =E46+C47-D47 -> 1897.9
A48: 17.10.2025 | B48: BANK CHARGES | D48: 2.1 | E48: =E47+C48-D48 -> 1895.8
A49: 21.10.2025 | B49: FUND RECD FROM EXOTIC WHEELS CAR RENTAL | C49: 100000 | E49: =E48+C49-D49 -> 101895.8
A50: 21.10.2025 | B50: TT TRF TO BLACK PEPPER GT NBF AED | D50: 99638 | E50: =E49+C50-D50 -> 2257.8
A51: 21.10.2025 | B51: BANK CHARGES | D51: 21 | E51: =E50+C51-D51 -> 2236.8
A52: 21.10.2025 | B52: BANK CHARGES | D52: 1 | E52: =E51+C52-D52 -> 2235.8
A53: 23.10.2025 | B53: FUND RECD FROM ALTARIQ ALMETHALI HEAVY EQUIPMENT | C53: 1054890 | E53: =E52+C53-D53 -> 1057125.8
A54: 23.10.2025 | B54: FUND RECD FROM AZE TRADE INTERNATIONAL | C54: 62000 | E54: =E53+C54-D54 -> 1119125.8
A55: 23.10.2025 | B55: TT TRF TO BLACK PEPPER GT NBF AED | D55: 550361 | E55: =E54+C55-D55 -> 568764.8
A56: 23.10.2025 | B56: TT TRF TO BLACK PEPPER GT NBF AED | D56: 566824 | E56: =E55+C56-D56 -> 1940.8
A57: 23.10.2025 | B57: BANK CHARGES | D57: 21.05 | E57: =E56+C57-D57 -> 1919.75
A58: 23.10.2025 | B58: BANK CHARGES | D58: 21.05 | E58: =E57+C58-D58 -> 1898.7
A59: 23.10.2025 | B59: BANK CHARGES | D59: 2.05 | E59: =E58+C59-D59 -> 1896.65
A60: 27.10.2025 | B60: FUND RECD FROM ROYAL EN EM ENBD AED | C60: 99284 | E60: =E59+C60-D60 -> 101180.65
A61: 27.10.2025 | B61: TT TRF TO EXOTIC CAR WHEELS MSQ (RETURNED) | D61: 100000 | E61: =E60+C61-D61 -> 1180.65
A62: 28.10.2025 | B62: FUND RECD FROM AZE TRADE INTERNATIONAL | C62: 105362 | E62: =E61+C62-D62 -> 106542.65
A63: 29.10.2025 | B63: TT TRF TO BLACK PEPPER GT NBF AED | D63: 105326 | E63: =E62+C63-D63 -> 1216.65
A64: 29.10.2025 | B64: BANK CHARGES | D64: 21 | E64: =E63+C64-D64 -> 1195.65
A65: 31.10.2025 | B65: CASH DEPOSIT | C65: 101500 | E65: =E64+C65-D65 -> 102695.65
A66: 31.10.2025 | B66: TT TRF TO BLACK PEPPER GT NBF AED | D66: 101328 | E66: =E65+C66-D66 -> 1367.65
A67: 02.11.2025 | B67: BANK CHARGES | D67: 125 | E67: =E66+C67-D67 -> 1242.65
A68: 02.11.2025 | B68: BANK CHARGES | D68: 6.25 | E68: =E67+C68-D68 -> 1236.4
A69: 02.11.2025 | B69: BANK CHARGES | D69: 300 | E69: =E68+C69-D69 -> 936.4
A70: 02.11.2025 | B70: BANK CHARGES | D70: 15 | E70: =E69+C70-D70 -> 921.4
A71: 02.11.2025 | B71: BANK CHARGES | D71: 21 | E71: =E70+C71-D71 -> 900.4
A72: 02.11.2025 | B72: BANK CHARGES | D72: 2.1 | E72: =E71+C72-D72 -> 898.3
A73: 10.11.2025 | B73: FUND RECD FROM SILVER CROSS EQUIPMENT | C73: 892870 | E73: =E72+C73-D73 -> 893768.3
A74: 11.11.2025 | B74: TT TRF TO CAPS LOCK FAB AED | D74: 891968 | E74: =E73+C74-D74 -> 1800.3
A75: 11.11.2025 | B75: BANK CHARGES | D75: 21 | E75: =E74+C75-D75 -> 1779.3
A76: 11.11.2025 | B76: BANK CHARGES | D76: 1.05 | E76: =E75+C76-D76 -> 1778.25
A77: 15.11.2025 | B77: FUND RECD FROM GREEN METAL SCRAP TRADING LLC | C77: 100000 | E77: =E76+C77-D77 -> 101778.25
A78: 15.11.2025 | B78: TT TRF TO BLACK PEPPER GT NBF AED | D78: 100549 | E78: =E77+C78-D78 -> 1229.25
A79: 15.11.2025 | B79: BANK CHARGES | D79: 1.05 | E79: =E78+C79-D79 -> 1228.2
A80: 15.11.2025 | B80: BANK CHARGES | D80: 21 | E80: =E79+C80-D80 -> 1207.2
A81: 20.11.2025 | B81: FUND RECD FROM ROYAL EN EM ENBD AED | C81: 380531 | E81: =E80+C81-D81 -> 381738.2
A82: 20.11.2025 | B82: CASH DEPOSIT | C82: 125000 | E82: =E81+C82-D82 -> 506738.2
A83: 20.11.2025 | B83: CASH DEPOSIT | C83: 95000 | E83: =E82+C83-D83 -> 601738.2
A84: 20.11.2025 | B84: TT TRF TO Meteor Balanced Portfolio USD 162600 | D84: 600319.2 | E84: =E83+C84-D84 -> 1419
A85: 22.11.2025 | B85: FUND RECD FROM RASHIDA JUZAR ALI | C85: 50000 | E85: =E84+C85-D85 -> 51419
A86: 27.11.2025 | B86: FUND RECD FROM ROYAL EN EM ENBD AED | C86: 541002 | E86: =E85+C86-D86 -> 592421
A87: 27.11.2025 | B87: TT TRF TO Meteor Balanced Portfolio (USD 160013) | D87: 590768 | E87: =E86+C87-D87 -> 1653
A88: 01.12.2025 | B88: BANK CHARGES | D88: =125+6.25+300+15 -> 446.25 | E88: =E87+C88-D88 -> 1206.75
A89: 05.12.2025 | B89: FUND RECD FROM ROYAL ENBD | C89: 28013 | E89: =E88+C89-D89 -> 29219.75
A90: 05.12.2025 | B90: TT TRF TO OLYMPIC COMPANIES FEDERAL (USD 7500) | D90: 27690 | E90: =E89+C90-D90 -> 1529.75
A91: 06.12.2025 | B91: CASH DEPOSIT | C91: 200000 | E91: =E90+C91-D91 -> 201529.75
A92: 06.12.2025 | B92: TT TRF TO BLACK PEPPER GT NBF AED | D92: 200013 | E92: =E91+C92-D92 -> 1516.75
A93: 13.12.2025 | B93: FUND RECD FROM ROYAL ENBD | C93: 49963 | E93: =E92+C93-D93 -> 51479.75
A94: 13.12.2025 | B94: REVERSE TT TRF TO RASHIDA JUZAR ALI ENBD | D94: 50000 | E94: =E93+C94-D94 -> 1479.75
A95: 19.12.2025 | B95: BANK CHARGES | D95: 22.05 | E95: =E94+C95-D95 -> 1457.7
A96: 19.12.2025 | B96: CASH DEPOSIT | C96: =224000+25000 -> 249000 | E96: =E95+C96-D96 -> 250457.7
A97: 19.12.2025 | B97: FUND RECD FROM AMINEX SIB | C97: 304005 | E97: =E96+C97-D97 -> 554462.7
A98: 19.12.2025 | B98: TT TRF TO Meteor Balanced Portfolio (USD 150K) | D98: 553800 | E98: =E97+C98-D98 -> 662.7
A99: 22.12.2025 | B99: FUND RECD FROM GREEN METAL SCRAP TRADING LLC | C99: 100000 | E99: =E98+C99-D99 -> 100662.7
A100: 22.12.2025 | B100: TT TRF TO BLACK PEPPER GT NBF AED | D100: 99986 | E100: =E99+C100-D100 -> 676.7
...

Sheet RHINE MULTY NBF AED
A1: M J S STAR
A2: EIB AED
A3: DATE | B3: PARTICULAR | C3: DEPOSIT | D3: WITHDRAWAL | E3: BALANCE
E4: 0
A5: 28.04.2026 | B5: FUND RECD FROM | C5: 105323 | E5: =E4+C5-D5 -> 105323
A6: 28.04.2026 | B6: TT TRF TO PINNACLE GR NBF AED | D6: 104230 | E6: =E5+C6-D6 -> 1093
A7: 28.04.2026 | B7: BANK CHARGES | D7: 1.05 | E7: =E6+C7-D7 -> 1091.95
E8: =E7+C8-D8 -> 1091.95
E9: =E8+C9-D9 -> 1091.95
E10: =E9+C10-D10 -> 1091.95
E11: =E10+C11-D11 -> 1091.95
E12: =E11+C12-D12 -> 1091.95
E13: =E12+C13-D13 -> 1091.95
E14: =E13+C14-D14 -> 1091.95
E15: =E14+C15-D15 -> 1091.95
E16: =E15+C16-D16 -> 1091.95
E17: =E16+C17-D17 -> 1091.95
E18: =E17+C18-D18 -> 1091.95
E19: =E18+C19-D19 -> 1091.95
... E100: =E99+C100-D100 -> 1091.95

Sheet MJS STAR SIB AED
A1: M J S STAR
A2: SIB AED
A3: DATE | B3: PARTICULAR | C3: DEPOSIT | D3: WITHDRAWAL | E3: BALANCE
B4: OPENING BALANCE | E4: 1948.5
A5: 25.02.2026 | B5: FUND RECD FROM CAPS LOCK FAB AED | C5: 11252 | E5: =E4+C5-D5 -> 13200.5
A6: 25.02.2026 | B6: TT TRF TO CRIF GULF DWC | D6: 11200 | E6: =E5+C6-D6 -> 2000.5
A7: 25.02.2026 | B7: BANK CHARGES | D7: 0.5 | E7: =E6+C7-D7 -> 2000
A8: 02.03.2026 | B8: BANK CHARGES | D8: 425.25 | E8: =E7+C8-D8 -> 1574.75
A9: 02.03.2026 | B9: AED TO USD | D9: 369.14 | E9: =E8+C9-D9 -> 1205.61
A10: 11.03.2026 | B10: FUND RECD FROM PINNACLE GR NBF AED | C10: 612582 | E10: =E9+C10-D10 -> 613787.61
A11: 11.03.2026 | B11: FUND RECD FROM PINNACLE GR NBF AED | C11: 490231 | E11: =E10+C11-D11 -> 1104018.6
A12: 11.03.2026 | B12: FUND RECD FROM PINNACLE GR NBF AED | C12: 1013 | E12: =E11+C12-D12 -> 1105031.6
A13: 11.03.2026 | B13: TT TRF TO METEOR SMB (USD 300010) | D13: 1104036.8 | E13: =E12+C13-D13 -> 994.81
A14: 30.03.2026 | B14: CASH DEPOSIT | C14: 200000 | E14: =E13+C14-D14 -> 200994.81
A15: 30.03.2026 | B15: TT TRF TO ORBIT PLUS WIO AED | D15: 200315 | E15: =E14+C15-D15 -> 679.81
A16: 30.03.2026 | B16: BANK CHARGES | D16: 1.05 | E16: =E15+C16-D16 -> 678.76
A17: 30.03.2026 | B17: FUND RECD FROM INVESTRADE PTE | C17: 998895 | E17: =E16+C17-D17 -> 999573.76
A18: 30.03.2026 | B18: TT TRF TO BLACK PEPPER GT SIB AED | D18: 999010 | E18: =E17+C18-D18 -> 563.76
A19: 01.04.2026 | B19: BANK CHARGES | D19: 425.25 | E19: =E18+C19-D19 -> 138.51
A20: 02.04.2026 | B20: CASH DEPOSIT | C20: 200000 | E20: =E19+C20-D20 -> 200138.51
A21: 02.04.2026 | B21: TT TRF TO BLACK PEPPER GT SIB AED | D21: 199868 | E21: =E20+C21-D21 -> 270.51
A22: 06.04.2026 | B22: CASH DEPOSIT | C22: 200000 | E22: =E21+C22-D22 -> 200270.51
A23: 07.04.2026 | B23: TT TRF TO BLACK PEPPER GT SIB AED | D23: 199500 | E23: =E22+C23-D23 -> 770.51
A24: 10.04.2026 | B24: CASH DEPOSIT | C24: 200000 | E24: =E23+C24-D24 -> 200770.51
A25: 10.04.2026 | B25: TT TRF TO BLACK PEPPER NBF AED | D25: 199686 | E25: =E24+C25-D25 -> 1084.51
A26: 10.04.2026 | B26: BANK CHARGES | D26: 1.05 | E26: =E25+C26-D26 -> 1083.46
A27: 13.04.2026 | B27: FUND RECD FROM PINNACLE GR NBF AED | C27: 622130 | E27: =E26+C27-D27 -> 623213.46
A28: 13.04.2026 | B28: FUND RECD FROM AMINEX SIB AED | C28: 14880 | E28: =E27+C28-D28 -> 638093.46
A29: 13.04.2026 | B29: FUND RECD FROM ROYAL EN EM NBF AED | C29: 100325 | E29: =E28+C29-D29 -> 738418.46
A30: 13.04.2026 | B30: TT TRF TO METEOR SMB (USD 200000) | D30: 736000 | E30: =E29+C30-D30 -> 2418.46
A31: 15.04.206 | B31: CASH DEPOSIT | C31: 200000 | E31: =E30+C31-D31 -> 202418.46
A32: 15.04.206 | B32: TT TRF TO CROSSFIT SIB AED | D32: 201560 | E32: =E31+C32-D32 -> 858.46
A33: 17.04.2026 | B33: CASH DEPOSIT | C33: 200000 | E33: =E32+C33-D33 -> 200858.46
A34: 17.04.2026 | B34: FUND RECD FROM AMINEX SIB AED | C34: 217569 | E34: =E33+C34-D34 -> 418427.46
A35: 17.04.2026 | B35: TT TRF TO BLACK PEPPER GT NBF | D35: 417880 | E35: =E34+C35-D35 -> 547.46
A36: 17.04.2026 | B36: BANK CHARGES | D36: 1.05 | E36: =E35+C36-D36 -> 546.41
A37: 18.04.2026 | B37: CASH DEPOSIT | C37: 98440 | E37: =E36+C37-D37 -> 98986.41
A38: 18.04.2026 | B38: TT TRF TO COMIDA GOODS NBF AED | D38: 98750 | E38: =E37+C38-D38 -> 236.41
A39: 21.04.2026 | B39: FUND RECD FROM AMINEX SIB AED | C39: 364023 | E39: =E38+C39-D39 -> 364259.41
A40: 21.04.2026 | B40: FUND RECD FROM BLACK PEPPER GT NBF | C40: 4500 | E40: =E39+C40-D40 -> 368759.41
A41: 21.04.2026 | B41: TT TRF TO METEOR SMB (USD 100000) | D41: 367900 | E41: =E40+C41-D41 -> 859.41
A42: 27.04.2026 | B42: FUND RECD FROM AMINEX SIB AED | C42: 50132 | E42: =E41+C42-D42 -> 50991.41
A43: 27.04.2026 | B43: TT TRF TO TANVEER HUSSAIN MSQ AED | D43: 50000 | E43: =E42+C43-D43 -> 991.41
A44: 27.04.2026 | B44: BANK CHARGES | D44: 0.5 | E44: =E43+C44-D44 -> 990.91
A45: 28.04.2026 | B45: FUND RECD FROM AMINEX SIB AED | C45: 105320 | E45: =E44+C45-D45 -> 106310.91
A46: 28.04.2026 | B46: TT TRF TO RHINE MULTY NBF AED | D46: 105323 | E46: =E45+C46-D46 -> 987.91
A47: 28.04.2026 | B47: BANK CHARGES | D47: 1.05 | E47: =E46+C47-D47 -> 986.86
A48: 28.04.2026 | B48: FUND RECD FROM AMINEX SIB AED | C48: 3012 | E48: =E47+C48-D48 -> 3998.86
A49: 28.04.2026 | B49: FTA PAYMENT | D49: 2875.3 | E49: =E48+C49-D49 -> 1123.56
A50: 30.04.2026 | B50: CASH DEPOSIT | C50: 200000 | E50: =E49+C50-D50 -> 201123.56
A51: 30.04.2026 | B51: TT TRF TO M J S STAR SIB AED | D51: 200465 | E51: =E50+C51-D51 -> 658.56
A52: 01.05.2026 | B52: FUND RECD FROM AMINEX SIB AED | C52: 656843 | E52: =E51+C52-D52 -> 657501.56
A53: 01.05.2026 | B53: TT TRF TO BLACK PEPPER GT NBF | D53: 655980 | E53: =E52+C53-D53 -> 1521.56
A54: 01.05.2026 | B54: BANK CHARGES | D54: 3.15 | E54: =E53+C54-D54 -> 1518.41
A55: 01.05.2026 | B55: BANK CHARGES | D55: 425.25 | E55: =E54+C55-D55 -> 1093.16
E56: =E55+C56-D56 -> 1093.16
E57: =E56+C57-D57 -> 1093.16
E58: =E57+C58-D58 -> 1093.16
E59: =E58+C59-D59 -> 1093.16
E60: =E59+C60-D60 -> 1093.16
E61: =E60+C61-D61 -> 1093.16
E62: =E61+C62-D62 -> 1093.16
E63: =E62+C63-D63 -> 1093.16
E64: =E63+C64-D64 -> 1093.16
E65: =E64+C65-D65 -> 1093.16
E66: =E65+C66-D66 -> 1093.16
E67: =E66+C67-D67 -> 1093.16
... E153: =E152+C153-D153 -> 1093.16

Sheet MJS STAR SIB USD
A1: M J S STAR
A2: SIB USD
A3: DATE | B3: PARTICULAR | C3: DEPOSIT | D3: WITHDRAWAL | E3: BALANCE
B4: OPENING BALANCE | E4: 0
A5: 02.03.2026 | B5: AED TO USD | C5: 100 | E5: =E4+C5-D5 -> 100
A6: 02.03.2026 | B6: BANK CHARGES | D6: 10.01 | E6: =E5+C6-D6 -> 89.99
A7: 13.03.2026 | B7: FUND RECD FROM ROYAL EN EM | C7: 200200 | E7: =E6+C7-D7 -> 200289.99
A8: 13.03.2026 | B8: TT TRF TO METEOR | D8: 200003 | E8: =E7+C8-D8 -> 286.99
E9: =E8+C9-D9 -> 286.99
E10: =E9+C10-D10 -> 286.99
E11: =E10+C11-D11 -> 286.99
E12: =E11+C12-D12 -> 286.99
E13: =E12+C13-D13 -> 286.99
E14: =E13+C14-D14 -> 286.99
E15: =E14+C15-D15 -> 286.99
E16: =E15+C16-D16 -> 286.99
E17: =E16+C17-D17 -> 286.99
E18: =E17+C18-D18 -> 286.99
E19: =E18+C19-D19 -> 286.99
E20: =E19+C20-D20 -> 286.99
... E100: =E99+C100-D100 -> 286.99

Sheet GRENEW FZE NBF
A1: GRENEW FZE NBF AED
E4: =C4 -> 0
A5: 07.11.2025 | B5: CASH DEPOSIT | C5: 7810 | E5: =E4+C5-D5 -> 7810
A6: 14.11.2025 | B6: FUND RECD FREOM MIDDLE EAST COMPUTERS SYSTEM | C6: 879.75 | E6: =E5+C6-D6 -> 8689.75
A7: 27.11.2025 | B7: FUND RECD FROM PINNACLE GR NBF | C7: 40800 | E7: =E6+C7-D7 -> 49489.75
A8: 27.11.2025 | B8: TT TRF TO Alhayat Aljadeeda Electro | D8: 27615 | E8: =E7+C8-D8 -> 21874.75
A9: 29.11.2025 | B9: CHQ PAID | D9: 13125 | E9: =E8+C9-D9 -> 8749.75
A10: 29.11.2025 | B10: BANK CHARGES | D10: 17.5 | E10: =E9+C10-D10 -> 8732.25
A11: 29.11.2025 | B11: BANK CHARGES | D11: 350 | E11: =E10+C11-D11 -> 8382.25
A12: 05.12.2025 | B12: TT TRF TO SOMNATH NEERAJ SRIVASTAV AXIS INR 150K | D12: 6210 | E12: =E11+C12-D12 -> 2172.25
A13: 09.12.2025 | B13: FUND RECD FROM PINNACLE GR NBF | C13: 71000 | E13: =E12+C13-D13 -> 73172.25
E14: =E13+C14-D14 -> 73172.25
E15: =E14+C15-D15 -> 73172.25
E16: =E15+C16-D16 -> 73172.25
E17: =E16+C17-D17 -> 73172.25
E18: =E17+C18-D18 -> 73172.25
E19: =E18+C19-D19 -> 73172.25
E20: =E19+C20-D20 -> 73172.25
E21: =E20+C21-D21 -> 73172.25
E22: =E21+C22-D22 -> 73172.25
E23: =E22+C23-D23 -> 73172.25
E24: =E23+C24-D24 -> 73172.25
E25: =E24+C25-D25 -> 73172.25
... E27: =E26+C27-D27 -> 73172.25
E28: =E27+C28-D28 -> 73172.25 | G28: =+E28-1138.34 -> 72033.91
E29: =E28+C29-D29 -> 73172.25
E30: =E29+C30-D30 -> 73172.25
E31: =E30+C31-D31 -> 73172.25
E32: =E31+C32-D32 -> 73172.25
E33: =E32+C33-D33 -> 73172.25
E34: =E33+C34-D34 -> 73172.25
E35: =E34+C35-D35 -> 73172.25
E36: =E35+C36-D36 -> 73172.25
E37: =E36+C37-D37 -> 73172.25
E38: =E37+C38-D38 -> 73172.25
E39: =E38+C39-D39 -> 73172.25
E40: =E39+C40-D40 -> 73172.25
... E210: =E209+C210-D210 -> 73172.25

Sheet SWIFT BRIDGE SIB AED
A1: SWIFT BRIDGE SIB AED
A4: 31-07-2025 | B4: OPENING BALANCE | C4: 4825.75 | E4: =C4 -> 4825.75
A5: 31-07-2025 | B5: BANK CHARGES | D5: 315 | E5: =E4+C5-D5 -> 4510.75
A6: 30-08-2025 | B6: BANK CHARGES | D6: 320.25 | E6: =E5+C6-D6 -> 4190.5
A7: 17.09.2025 | B7: FUND RECD FROM Y A X A TRADING LLC AED | C7: 499723 | E7: =E6+C7-D7 -> 503913.5
A8: 17.09.2025 | B8: TT TRF TO SHRIJI INT EIB AED | D8: 498521 | E8: =E7+C8-D8 -> 5392.5
A9: 17.09.2025 | B9: BANK CHARGES | D9: 1.05 | E9: =E8+C9-D9 -> 5391.45
A10: 30.09.2025 | B10: BANK CHARGES | D10: 320.25 | E10: =E9+C10-D10 -> 5071.2
A11: 01.10.2025 | B11: FUND RECD FROM SILVER CROSS EQUIPMENT TRADING | C11: 751070 | E11: =E10+C11-D11 -> 756141.2
A12: 01.10.2025 | B12: TT TRF TO SHRIJI INT EIB AED | D12: 499683 | E12: =E11+C12-D12 -> 256458.2
A13: 01.10.2025 | B13: BANK CHARGES | D13: 1.05 | E13: =E12+C13-D13 -> 256457.15
A14: 02.10.2025 | B14: TT TRF TO SHRIJI INT EIB AED | D14: 255760 | E14: =E13+C14-D14 -> 697.15
A15: 02.10.2025 | B15: BANK CHARGES | D15: 1.058 | E15: =E14+C15-D15 -> 696.092
A16: 11.10.2025 | B16: BANK CHARGES | D16: 210 | E16: =E15+C16-D16 -> 486.092
A17: 17.10.2025 | B17: FUND RECD FROM CAPS LOCK FAB | C17: 7236 | E17: =E16+C17-D17 -> 7722.092
A18: 17.10.2025 | B18: TT TRF TO LOVEDEEP SINGH MSQ AED | D18: 5000 | E18: =E17+C18-D18 -> 2722.092
A19: 17.10.2025 | B19: BANK CHARGES | D19: 0.5 | E19: =E18+C19-D19 -> 2721.592
A20: 24.10.2025 | B20: FUND RECD FROM TAJ INTERNATIONAL (INDIA) | C20: 67996.14 | E20: =E19+C20-D20 -> 70717.732
A21: 24.10.2025 | B21: TT TRF TO SHRIJI INT EIB AED | D21: 68960 | E21: =E20+C21-D21 -> 1757.732
A22: 24.10.2025 | B22: BANK CHARGES | D22: 1.05 | E22: =E21+C22-D22 -> 1756.682
A23: 28.10.2025 | B23: CASH DEPOSIT | C23: 225000 | E23: =E22+C23-D23 -> 226756.68
A24: 28.10.2025 | B24: TT TRF TO SHRIJI INT EIB AED | D24: 225643 | E24: =E23+C24-D24 -> 1113.682
A25: 28.10.2025 | B25: BANK CHARGES | D25: 1.05 | E25: =E24+C25-D25 -> 1112.632
A26: 31.10.2025 | B26: CASH DEPOSIT | C26: 225000 | E26: =E25+C26-D26 -> 226112.63
A27: 31.10.2025 | B27: TT TRF TO SHRIJI INT EIB AED | D27: 224968 | E27: =E26+C27-D27 -> 1144.632
A28: 31.10.2025 | B28: BANK CHARGES | D28: 1.05 | E28: =E27+C28-D28 -> 1143.582 | G28: =+E28-1138.34 -> 5.242
A29: 31.10.2025 | B29: BANK CHARGES | D29: 5.24 | E29: =E28+C29-D29 -> 1138.342
A30: 31.10.2025 | B30: BANK CHARGES | D30: 315 | E30: =E29+C30-D30 -> 823.342
A31: 11.12.2025 | B31: CASH DEPOSIT | C31: 125000 | E31: =E30+C31-D31 -> 125823.34
A32: 11.12.2025 | B32: CASH DEPOSIT | C32: 77000 | E32: =E31+C32-D32 -> 202823.34
A33: 11.12.2025 | B33: TT TRF TO AMINEX SIB | D33: 201569 | E33: =E32+C33-D33 -> 1254.342
A34: 11.12.2025 | B34: BANK CHARGES | D34: 477.75 | E34: =E33+C34-D34 -> 776.592 | G34: =1254.34-776.59 -> 477.75
A35: 12.12.2025 | B35: CASH DEPOSIT | C35: 250000 | E35: =E34+C35-D35 -> 250776.59
A36: 12.12.2025 | B36: TT TRF TO AMINEX SIB | D36: 249804 | E36: =E35+C36-D36 -> 972.592
A37: 16.12.2025 | B37: CASH DEPOSIT | C37: =175000+24500+50000 -> 249500 | E37: =E36+C37-D37 -> 250472.59
A38: 16.12.2025 | B38: TT TRF TO SHRIJI INT EIB AED | D38: 248968 | E38: =E37+C38-D38 -> 1504.592
A39: 16.12.2025 | B39: BANK CHARGES | D39: 1.05 | E39: =E38+C39-D39 -> 1503.542
A40: 17.12.2025 | B40: CASH DEPOSIT | C40: 300000 | E40: =E39+C40-D40 -> 301503.54
A41: 17.12.2025 | B41: TT TRF TO AMINEX SIB | D41: 300428 | E41: =E40+C41-D41 -> 1075.542
A42: 19.12.2025 | B42: CASH DEPOSIT | C42: 300000 | E42: =E41+C42-D42 -> 301075.54
A43: 19.12.2025 | B43: TT TRF TO AMINEX SIB | D43: 300539 | E43: =E42+C43-D43 -> 536.542
A44: 02.01.2026 | B44: BANK CHARGES | D44: 320.25 | E44: =E43+C44-D44 -> 216.292 | F44: =+E44-216.29 -> 0.002
A45: 16.01.2026 | B45: CASH DEPOSIT | C45: 150000 | E45: =E44+C45-D45 -> 150216.29
A46: 16.01.2026 | B46: TT TRF TO AMINEX SIB | D46: 149863 | E46: =E45+C46-D46 -> 353.292
A47: 20.01.2026 | B47: CASH DEPOSIT | C47: 296000 | E47: =E46+C47-D47 -> 296353.29
A48: 20.01.2026 | B48: TT TRF TO PINNACLE GR NBF | D48: 295967 | E48: =E47+C48-D48 -> 386.292
A49: 20.01.2026 | B49: BANK CHARGES | D49: 1.05 | E49: =E48+C49-D49 -> 385.242
A50: 21.01.2026 | B50: CASH DEPOSIT | C50: 250000 | E50: =E49+C50-D50 -> 250385.24
A51: 21.01.2026 | B51: TT TRF TO PINNACLE GR NBF | D51: 249968 | E51: =E50+C51-D51 -> 417.242
A52: 21.01.2026 | B52: BANK CHARGES | D52: 1.05 | E52: =E51+C52-D52 -> 416.192
A53: 23.01.2026 | B53: CASH DEPOSIT | C53: 200000 | E53: =E52+C53-D53 -> 200416.19
A54: 23.01.2026 | B54: TT TRF TO SILVER STONE WIO | D54: 200048 | E54: =E53+C54-D54 -> 368.192
A55: 23.01.2026 | B55: BANK CHARGES | D55: 1.05 | E55: =E54+C55-D55 -> 367.142
A56: 27.01.2026 | B56: CASH DEPOSIT | C56: 200000 | E56: =E55+C56-D56 -> 200367.14
A57: 27.01.2026 | B57: TT TRF TO AMINEX SIB | D57: 200150 | E57: =E56+C57-D57 -> 217.142
A58: 28.01.2026 | B58: CASH DEPOSIT | C58: 250000 | E58: =E57+C58-D58 -> 250217.14
A59: 28.01.2026 | B59: TT TRF TO SHRIJI INT EIB AED | D59: 249804 | E59: =E58+C59-D59 -> 413.142
A60: 28.01.2026 | B60: BANK CHARGES | D60: 1.05 | E60: =E59+C60-D60 -> 412.092
A61: 03.02.2026 | B61: CASH DEPOSIT | C61: =224500+24500 -> 249000 | E61: =E60+C61-D61 -> 249412.09
A62: 03.02.2026 | B62: TT TRF TO ORBIT PLUS SIB AED | D62: 248804 | E62: =E61+C62-D62 -> 608.092
A63: 04.02.2026 | B63: CASH DEPOSIT | C63: 250000 | E63: =E62+C63-D63 -> 250608.09
A64: 04.02.2026 | B64: TT TRF TO ORBIT PLUS SIB AED | D64: 249250 | E64: =E63+C64-D64 -> 1358.092
A65: 04.02.2026 | B65: BANK CHARGES | D65: 320.25 | E65: =E64+C65-D65 -> 1037.842
A66: 09.02.2026 | B66: FUND RECD FROM TRADERS VENTURES EIB | C66: 49047 | E66: =E65+C66-D66 -> 50084.842
A67: 09.02.2026 | B67: TT TRF TO AMINEX SIB | D67: 49520 | E67: =E66+C67-D67 -> 564.842
A68: 10.02.2026 | B68: CASH DEPOSIT | C68: 250000 | E68: =E67+C68-D68 -> 250564.84
A69: 10.02.2026 | B69: TT TRF TO SILVER STONE WIO | D69: 250030 | E69: =E68+C69-D69 -> 534.842
A70: 10.02.2026 | B70: BANK CHARGES | D70: 1.05 | E70: =E69+C70-D70 -> 533.792
A71: 24.02.2026 | B71: FUND RECD AMINEX SIB AED | C71: 30820 | E71: =E70+C71-D71 -> 31353.792
A72: 24.02.2026 | B72: TT TRF TO TB ORIGINATIONS (USD 8102.71) | D72: =8102.71*3.69137 -> 29910.101 | E72: =E71+C72-D72 -> 1443.6914
A73: 24.02.2026 | B73: BANK CHARGES | D73: 52.5 | E73: =E72+C73-D73 -> 1391.1914
A74: 24.02.2026 | B74: BANK CHARGES | D74: 50 | E74: =E73+C74-D74 -> 1341.1914
A75: 03.03.2026 | B75: FUND RECD FROM SHRIJI INT EIB AED | C75: 499362 | E75: =E74+C75-D75 -> 500703.19
A76: 03.03.2026 | B76: BANK CHARGES | D76: 320.25 | E76: =E75+C76-D76 -> 500382.94
A77: 03.03.2026 | B77: TT TRF TO AMINEX SIB | D77: 500132 | E77: =E76+C77-D77 -> 250.94139
A78: 05.03.2026 | B78: FUND RECD FROM BLACK PEPPER GT NBF AED | C78: 483869 | E78: =E77+C78-D78 -> 484119.94
A79: 05.03.2026 | B79: FUND RECD FROM AMINEX SIB AED | C79: 70380 | E79: =E78+C79-D79 -> 554499.94
A80: 05.03.2026 | B80: FUND RECD FROM AMINEX SIB AED | C80: 5000 | E80: =E79+C80-D80 -> 559499.94
A81: 05.03.2026 | B81: TT TRF TO TB ORIGINATIONS (USD 135K) | D81: 496665 | E81: =E80+C81-D81 -> 62834.941
A82: 05.03.2026 | B82: BANK CHARGES | D82: 52.5 | E82: =E81+C82-D82 -> 62782.441
A83: 05.03.2026 | B83: BANK CHARGES | D83: 50 | E83: =E82+C83-D83 -> 62732.441
A84: 06.03.2026 | B84: CASH DEPOSIT | C84: 200000 | E84: =E83+C84-D84 -> 262732.44
A85: 06.03.2026 | B85: TT TRF TO SHRIJI INT EIB AED | D85: 262091 | E85: =E84+C85-D85 -> 641.44139
A86: 06.03.2026 | B86: BANK CHARGES | D86: 1.05 | E86: =E85+C86-D86 -> 640.39139
A87: 13.03.2026 | B87: FUND RECD FROM COMIDA NBF AED | C87: 741023 | E87: =E86+C87-D87 -> 741663.39
A88: 13.03.2026 | B88: TT TRF TO TB ORIGINATIONS (USD 200K) | D88: 741210 | E88: =E87+C88-D88 -> 453.39139
A89: 13.03.2026 | B89: BANK CHARGES | D89: 102.5 | E89: =E88+C89-D89 -> 350.89139
A90: 13.03.2026 | B90: BANK CHARGES | D90: 210 | E90: =E89+C90-D90 -> 140.89139
A91: 14.03.2026 | B91: FUND RECD FROM SHRIJI INT EIB AED | C91: 720133 | E91: =E90+C91-D91 -> 720273.89
A92: 14.03.2026 | B92: TT TRF TO SWIFT BRIDGE ENBD | D92: 5000 | E92: =E91+C92-D92 -> 715273.89
A93: 14.03.2026 | B93: BANK CHARGES | D93: 0.5 | E93: =E92+C93-D93 -> 715273.39
A94: 14.03.2026 | B94: TT TRF TO SWIFT BRIDGE ENBD | D94: 714350 | E94: =E93+C94-D94 -> 923.39139
A95: 18.03.2026 | B95: CASH DEPOSIT | C95: =150000+23500 -> 173500 | E95: =E94+C95-D95 -> 174423.39
A96: 18.03.2026 | B96: TT TRF TO AMINEX SIB | D96: 150235 | E96: =E95+C96-D96 -> 24188.391
A97: 18.03.2026 | B97: TT TRF TO AMINEX SIB | D97: 24000 | E97: =E96+C97-D97 -> 188.39139
A98: 30.03.2026 | B98: CASH DEPOSIT | C98: 150000 | E98: =E97+C98-D98 -> 150188.39
A99: 30.03.2026 | B99: TT TRF TO ORBIT PLUS SIB AED | D99: 149680 | E99: =E98+C99-D99 -> 508.39139
A100: 30.03.2026 | B100: FUND RECD FROM SHRIJI INT EIB AED | C100: 328015 | E100: =E99+C100-D100 -> 328523.39
A101: 30.03.2026 | B101: TT TRF TO AMINEX SIB | D101: 327968 | E101: =E100+C101-D101 -> 555.39139
A102: 31.03.2026 | B102: FUND RECD FROM SHRIJI INT EIB AED | C102: 455980 | E102: =E101+C102-D102 -> 456535.39
...

Sheet SWIFT BRIDGE ADIB AED
A1: SWIFT BRIDGE ADIB AED
A4: 23.04.2026 | B4: FUND RECD FROM BLACK PEPPER NBF AED | C4: 12300 | E4: =C4 -> 12300 | G4: A/C OPENED
A5: 23.04.2026 | B5: AED TO USD | D5: 6000 | E5: =E4+C5-D5 -> 6300
A6: 29.04.2026 | B6: USD TO AED | C6: 5816 | E6: =E5+C6-D6 -> 12116
A7: 29.04.2026 | B7: TT TRF TO SWIFT BRIDGE SIB AED | D7: 11200 | E7: =E6+C7-D7 -> 916
A8: 29.04.2026 | B8: BANK CHARGES | D8: 15.75 | E8: =E7+C8-D8 -> 900.25
E9: =E8+C9-D9 -> 900.25
E10: =E9+C10-D10 -> 900.25
E11: =E10+C11-D11 -> 900.25
E12: =E11+C12-D12 -> 900.25
E13: =E12+C13-D13 -> 900.25
E14: =E13+C14-D14 -> 900.25
E15: =E14+C15-D15 -> 900.25
E16: =E15+C16-D16 -> 900.25
E17: =E16+C17-D17 -> 900.25
E18: =E17+C18-D18 -> 900.25
E19: =E18+C19-D19 -> 900.25
E20: =E19+C20-D20 -> 900.25
... E210: =E209+C210-D210 -> 900.25

Sheet SWIFT BRIDGE ADIB USD
A1: SWIFT BRIDGE ADIB USD
A4: 23.04.2026 | B4: AED TO USD | C4: 1617.47 | E4: =C4 -> 1617.47
A5: 29.04.2026 | B5: USD TO AED | D5: 1600 | E5: =E4+C5-D5 -> 17.47
E6: =E5+C6-D6 -> 17.47
E7: =E6+C7-D7 -> 17.47
E8: =E7+C8-D8 -> 17.47
E9: =E8+C9-D9 -> 17.47
E10: =E9+C10-D10 -> 17.47
E11: =E10+C11-D11 -> 17.47
E12: =E11+C12-D12 -> 17.47
E13: =E12+C13-D13 -> 17.47
E14: =E13+C14-D14 -> 17.47
E15: =E14+C15-D15 -> 17.47
E16: =E15+C16-D16 -> 17.47
E17: =E16+C17-D17 -> 17.47
... E210: =E209+C210-D210 -> 17.47

Sheet SWIFT BRIDGE SIB USD
A1: SWIFT BRIDGE SIB USD
A4: 21.04.2026 | B4: FUND RECD FROM BILLION RIGHT | C4: 450494.68 | E4: =C4 -> 450494.68
A5: 21.04.2026 | B5: TT TRF TO TB ORIGINATIONS | D5: 200000 | E5: =E4+C5-D5 -> 250494.68
A6: 21.04.2026 | B6: TT TRF TO TB ORIGINATIONS | D6: 250000 | E6: =E5+C6-D6 -> 494.68
A7: 21.04.2026 | B7: BANK CHARGES | D7: 55.8 | E7: =E6+C7-D7 -> 438.88
E8: =E7+C8-D8 -> 438.88
E9: =E8+C9-D9 -> 438.88
E10: =E9+C10-D10 -> 438.88
E11: =E10+C11-D11 -> 438.88
E12: =E11+C12-D12 -> 438.88
E13: =E12+C13-D13 -> 438.88
E14: =E13+C14-D14 -> 438.88
E15: =E14+C15-D15 -> 438.88
E16: =E15+C16-D16 -> 438.88
E17: =E16+C17-D17 -> 438.88
E18: =E17+C18-D18 -> 438.88
E19: =E18+C19-D19 -> 438.88
... E161: =E160+C161-D161 -> 438.88

Sheet SWIFT BRIDGE WIO AED
A1: SWIFT BRIDGE WIO AED
A4: 23.04.2026 | B4: FUND RECD FROM INFINITY SIB AED | C4: 37013 | E4: =C4 -> 37013 | G4: A/C OPENED
A5: 23.04.2026 | B5: TT TRF TO SHRIJI INT EIB AED | D5: 36460 | E5: =E4+C5-D5 -> 553
A6: 24.04.2026 | B6: FUND RECD FROM INFINITY SIB AED | C6: 237474 | E6: =E5+C6-D6 -> 238027
A7: 24.04.2026 | B7: TT TRF TO SHRIJI INT EIB AED | D7: 237465 | E7: =E6+C7-D7 -> 562
E8: =E7+C8-D8 -> 562
E9: =E8+C9-D9 -> 562
E10: =E9+C10-D10 -> 562
E11: =E10+C11-D11 -> 562
E12: =E11+C12-D12 -> 562
E13: =E12+C13-D13 -> 562
E14: =E13+C14-D14 -> 562
E15: =E14+C15-D15 -> 562
E16: =E15+C16-D16 -> 562
E17: =E16+C17-D17 -> 562
E18: =E17+C18-D18 -> 562
E19: =E18+C19-D19 -> 562
... E136: =E135+C136-D136 -> 562

Sheet ORBIT PLUS WIO USD
A1: ORBIT PLUS WIO
E3: =C3 -> 0
A4: 10.02.2026 | B4: FUND RECD FROM GLOBAL ISLAND LTD | C4: 145130 | E4: =E3+C4-D4 -> 145130
A5: 10.02.2026 | B5: USD TO AED | D5: 145120 | E5: =E4+C5-D5 -> 10
A6: 21.02.2026 | B6: FUND RECD FROM GLOBAL ISLAND LTD | C6: 88653.96 | E6: =E5+C6-D6 -> 88663.96
A7: 21.02.2026 | B7: USD TO AED | D7: 88660 | E7: =E6+C7-D7 -> 3.96
A8: 24.02.2026 | B8: FUND RECD FROM GLOBAL ISLAND LTD | C8: 84560.4 | E8: =E7+C8-D8 -> 84564.36
A9: 24.02.2026 | B9: FUND RECD FROM GLOBAL ISLAND LTD | C9: 54900 | E9: =E8+C9-D9 -> 139464.36
A10: 24.02.2026 | B10: FUND RECD FROM COMIDA GOODS WHOLESALERS LLC | C10: 99560.16 | E10: =E9+C10-D10 -> 239024.52
A11: 24.02.2026 | B11: USD TO AED | D11: 239020 | E11: =E10+C11-D11 -> 4.52
A12: 27.02.2026 | B12: FUND RECD FROM GLOBAL ISLAND LTD | C12: 155210 | E12: =E11+C12-D12 -> 155214.52
A13: 27.02.2026 | B13: USD TO AED | D13: 155210 | E13: =E12+C13-D13 -> 4.52
A14: 28.02.2026 | B14: FUND RECD FROM GLOBAL ISLAND LTD | C14: 88200 | E14: =E13+C14-D14 -> 88204.52
A15: 28.02.2026 | B15: USD TO AED | D15: 88200 | E15: =E14+C15-D15 -> 4.52
A16: 04.03.2026 | B16: FUND RECD FROM GLOBAL ISLAND LTD | C16: 174600 | E16: =E15+C16-D16 -> 174604.52
A17: 04.03.2026 | B17: USD TO AED | D17: 174600 | E17: =E16+C17-D17 -> 4.52
A18: 05.03.2026 | B18: FUND RECD FROM GLOBAL ISLAND LTD | C18: 147500 | E18: =E17+C18-D18 -> 147504.52
A19: 05.03.2026 | B19: FUND RECD FROM GLOBAL ISLAND LTD | C19: 194300 | E19: =E18+C19-D19 -> 341804.52
A20: 05.03.2026 | B20: USD TO AED | D20: 341800 | E20: =E19+C20-D20 -> 4.52
A21: 10.03.2026 | B21: FUND RECD FROM GLOBAL ISLAND LTD | C21: 315700 | E21: =E20+C21-D21 -> 315704.52
A22: 10.03.2026 | B22: USD TO AED | D22: 315703 | E22: =E21+C22-D22 -> 1.52
A23: 11.03.2026 | B23: FUND RECD FROM COMIDA GOODS WHOLESALERS LLC | C23: 328900 | E23: =E22+C23-D23 -> 328901.52
A24: 11.03.2026 | B24: USD TO AED | D24: 328900 | E24: =E23+C24-D24 -> 1.52
A25: 12.03.2026 | B25: FUND RECD FROM NIYAT GOODS WHOLESALERS PAYONEER | C25: 374100 | E25: =E24+C25-D25 -> 374101.52
A26: 12.03.2026 | B26: USD TO AED | D26: 374100 | E26: =E25+C26-D26 -> 1.52
A27: 13.03.2026 | B27: FUND RECD FROM ROYAL EN EM PAYONEER | C27: 235700 | E27: =E26+C27-D27 -> 235701.52
A28: 13.03.2026 | B28: FUND RECD FROM GLOBAL ISLAND LTD | C28: 141810 | E28: =E27+C28-D28 -> 377511.52
A29: 13.03.2026 | B29: FUND RECD FROM NIYAT GOODS WHOLESALERS PAYONEER | C29: 153010 | E29: =E28+C29-D29 -> 530521.52
A30: 13.03.2026 | B30: FUND RECD FROM GLOBAL ISLAND LTD | C30: 29860 | E30: =E29+C30-D30 -> 560381.52
A31: 13.03.2026 | B31: USD TO AED | D31: 300000 | E31: =E30+C31-D31 -> 260381.52
A32: 14.03.2026 | B32: USD TO AED | D32: 260380 | E32: =E31+C32-D32 -> 1.52
A33: 17.03.2026 | B33: FUND RECD FROM ROYAL EN EM PAYONEER | C33: 89600 | E33: =E32+C33-D33 -> 89601.52
A34: 17.03.2026 | B34: USD TO AED | D34: 89600 | E34: =E33+C34-D34 -> 1.52
A35: 18.03.2026 | B35: FUND RECD FROM GLOBAL ISLAND LTD | C35: 113010 | E35: =E34+C35-D35 -> 113011.52
A36: 18.03.2026 | B36: USD TO AED | D36: 113010 | E36: =E35+C36-D36 -> 1.52
A37: 23.03.2026 | B37: FUND RECD FROM ROYAL EN EM PAYONEER | C37: 352110 | E37: =E36+C37-D37 -> 352111.52
A38: 23.03.2026 | B38: USD TO AED | D38: 352110 | E38: =E37+C38-D38 -> 1.52
A39: 24.03.2026 | B39: FUND RECD FROM GLOBAL ISLAND LTD | C39: 74510 | E39: =E38+C39-D39 -> 74511.52
A40: 24.03.2026 | B40: USD TO AED | D40: 74510 | E40: =E39+C40-D40 -> 1.52
A41: 03.04.2026 | B41: FUND RECD FROM BOLDWAY AIRWALLEX | C41: 99745 | E41: =E40+C41-D41 -> 99746.52
A42: 03.04.2026 | B42: FUND RECD FROM BOLDWAY AIRWALLEX | C42: 85695 | E42: =E41+C42-D42 -> 185441.52
A43: 03.04.2026 | B43: USD TO AED | D43: 100000 | E43: =E42+C43-D43 -> 85441.52
A44: 04.04.2026 | B44: AED TO USD | C44: 18241.22 | E44: =E43+C44-D44 -> 103682.74
A45: 04.04.2026 | B45: TT TRF TO ALHIJAZ METAL TRADING USD | D45: 103457.7 | E45: =E44+C45-D45 -> 225.04
A46: 06.04.2026 | B46: FUND RECD FROM BILLION RIGHT LIMITED | C46: 98724.69 | E46: =E45+C46-D46 -> 98949.73
A47: 06.04.2026 | B47: USD TO AED | D47: 8000 | E47: =E46+C47-D47 -> 90949.73
A48: 07.04.2026 | B48: AED TO USD | C48: 39800 | E48: =E47+C48-D48 -> 130749.73
A49: 07.04.2026 | B49: TT TRF TO ALHIJAZ METAL TRADING USD | D49: =130663+14.9 -> 130677.9 | E49: =E48+C49-D49 -> 71.83
A50: 08.04.2026 | B50: FUND RECD FROM BILLION RIGHT LIMITED | C50: 99634.68 | E50: =E49+C50-D50 -> 99706.51
A51: 08.04.2026 | B51: USD TO AED | D51: 99700 | E51: =E50+C51-D51 -> 6.51
A52: 09.04.2026 | B52: FUND RECD FROM BOLDWAY AIRWALLEX | C52: 151875 | E52: =E51+C52-D52 -> 151881.51
A53: 09.04.2026 | B53: USD TO AED | D53: 151880 | E53: =E52+C53-D53 -> 1.51
A54: 13.04.2026 | B54: FUND RECD FROM BILLION RIGHT LIMITED | C54: 201984.69 | E54: =E53+C54-D54 -> 201986.2
A55: 13.04.2026 | B55: USD TO AED | D55: 201985 | E55: =E54+C55-D55 -> 1.2
A56: 15.04.2026 | B56: FUND RECD FROM UNITED GLOBAL EXIM LIMITED | C56: 1635 | E56: =E55+C56-D56 -> 1636.2
A57: 16.04.2026 | B57: FUND RECD FROM HT SOFTWARE SOLUTIONS LLC | C57: 45455 | E57: =E56+C57-D57 -> 47091.2
A58: 16.04.2026 | B58: FUND RECD FROM LYTHA VENTURES LLC | C58: 64955 | E58: =E57+C58-D58 -> 112046.2
A59: 16.04.2026 | B59: TT TRF TO ALHIJAZ METAL TRADING USD | D59: =93737.4+14.7 -> 93752.1 | E59: =E58+C59-D59 -> 18294.1
A60: 16.04.2026 | B60: USD TO AED | D60: 18000 | E60: =E59+C60-D60 -> 294.1
A61: 21.04.2026 | B61: FUND RECD FROM HT SOFTWARE SOLUTIONS LLC | C61: 93422 | E61: =E60+C61-D61 -> 93716.1
A62: 21.04.2026 | B62: FUND RECD FROM LYTHA VENTURES LLC | C62: 76515 | E62: =E61+C62-D62 -> 170231.1
A63: 21.04.2026 | B63: AED TO USD | C63: 20350 | E63: =E62+C63-D63 -> 190581.1
A64: 21.04.2026 | B64: AED TO USD | C64: 136.13 | E64: =E63+C64-D64 -> 190717.23
A65: 21.04.2026 | B65: TT TRF TO ALHIJAZ METAL TRADING USD | D65: 190579.7 | E65: =E64+C65-D65 -> 137.53
A66: 21.04.2026 | B66: FUND RECD FROM BOLDWAY AIRWALLEX | C66: 446745 | E66: =E65+C66-D66 -> 446882.53
A67: 21.04.2026 | B67: USD TO AED | D67: 446880 | E67: =E66+C67-D67 -> 2.53
A68: 22.04.2026 | B68: FUND RECD FROM TOOLCARE TRADING LIMITED | C68: 148824.68 | E68: =E67+C68-D68 -> 148827.21
A69: 22.04.2026 | B69: TT TRF TO ALHIJAZ METAL TRADING USD | D69: =148750+14.7 -> 148764.7 | E69: =E68+C69-D69 -> 62.51
A70: 23.04.2026 | B70: FUND RECD FROM BOLDWAY AIRWALLEX | C70: 98185 | E70: =E69+C70-D70 -> 98247.51
A71: 23.04.2026 | B71: TT TRF TO ALHIJAZ METAL TRADING USD | D71: 88098.85 | E71: =E70+C71-D71 -> 10148.66
A72: 23.04.2026 | B72: USD TO AED | D72: 10148 | E72: =E71+C72-D72 -> 0.66
A73: 24.04.2026 | B73: FUND RECD FROM LYTHA VENTURES LLC | C73: 39955 | E73: =E72+C73-D73 -> 39955.66
A74: 24.04.2026 | B74: FUND RECD FROM HT SOFTWARE SOLUTIONS LLC | C74: 29955 | E74: =E73+C74-D74 -> 69910.66
A75: 24.04.2026 | B75: FUND RECD FROM TOOLCARE TRADING LIMITED | C75: 374354.68 | E75: =E74+C75-D75 -> 444265.34
A76: 24.04.2026 | B76: TT TRF TO Ready Betontechnik GmbH WISE (EUR 54402) | D76: =64641.53+14.7 -> 64656.23 | E76: =E75+C76-D76 -> 379609.11
A77: 24.04.2026 | B77: USD TO AED | D77: 379609 | E77: =E76+C77-D77 -> 0.11
A78: 27.04.2026 | B78: FUND RECD FROM TOOLCARE TRADING LIMITED | C78: 480680 | E78: =E77+C78-D78 -> 480680.11
A79: 27.04.2026 | B79: FUND RECD FROM BOLDWAY AIRWALLEX | C79: 99945 | E79: =E78+C79-D79 -> 580625.11
A80: 27.04.2026 | B80: FUND RECD FROM GLOBAL ISLAND LTD YEEPAY | C80: 181475 | E80: =E79+C80-D80 -> 762100.11
A81: 27.04.2026 | B81: USD TO AED | D81: 762100 | E81: =E80+C81-D81 -> 0.11
A82: 28.04.2026 | B82: FUND RECD FROM LYTHA VENTURES LLC | C82: 73056 | E82: =E81+C82-D82 -> 73056.11
A83: 28.04.2026 | B83: FUND RECD FROM HT SOFTWARE SOLUTIONS LLC | C83: 18205 | E83: =E82+C83-D83 -> 91261.11
A84: 28.04.2026 | B84: AED TO USD | C84: 44949.63 | E84: =E83+C84-D84 -> 136210.74
A85: 28.04.2026 | B85: TT TRF TO ALHIJAZ METAL TRADING USD | D85: 136128.91 | E85: =E84+C85-D85 -> 81.83
E86: =E85+C86-D86 -> 81.83
E87: =E86+C87-D87 -> 81.83
E88: =E87+C88-D88 -> 81.83
E89: =E88+C89-D89 -> 81.83
E90: =E89+C90-D90 -> 81.83
E91: =E90+C91-D91 -> 81.83
E92: =E91+C92-D92 -> 81.83
E93: =E92+C93-D93 -> 81.83
E94: =E93+C94-D94 -> 81.83
E95: =E94+C95-D95 -> 81.83
E96: =E95+C96-D96 -> 81.83
E97: =E96+C97-D97 -> 81.83
... E209: =E208+C209-D209 -> 81.83

Sheet ORBIT PLUS WIO AED
A1: ORBIT PLUS WIO
E3: =C3 -> 0
C4: 249805 | E4: =E3+C4-D4 -> 249805
D5: 249201 | E5: =E4+C5-D5 -> 604
A6: 05.02.2026 | B6: FUND RECD FROM PINNACLE INT SIB | C6: 207403 | E6: =E5+C6-D6 -> 208007
A7: 05.02.2026 | B7: FUND RECD FROM PINNACLE INT FAB | C7: 142580 | E7: =E6+C7-D7 -> 350587
A8: 05.02.2026 | B8: TT TRF TO FABREX ENTERPRISES BOB (USD 94950) | D8: =348696.26+52.5 -> 348748.76 | E8: =E7+C8-D8 -> 1838.24
A9: 05.02.2026 | B9: CASH DEPOSIT | C9: 10000 | E9: =E8+C9-D9 -> 11838.24
A10: 05.02.2026 | B10: TT TRF TO SILVER STONE WIO AED | D10: 10235 | E10: =E9+C10-D10 -> 1603.24
A11: 10.02.2026 | B11: USD TO AED | C11: 532590.4 | E11: =E10+C11-D11 -> 534193.64
A12: 10.02.2026 | B12: TT TRF TO AMINEX SIB AED | D12: 481013 | E12: =E11+C12-D12 -> 53180.64
A13: 10.02.2026 | B13: CASH DEPOSIT | C13: =94500+104000+2000 -> 200500 | E13: =E12+C13-D13 -> 253680.64
A14: 10.02.2026 | B14: TT TRF TO SILVER STONE WIO AED | D14: 252964 | E14: =E13+C14-D14 -> 716.64
A15: 12.02.2026 | B15: CASH DEPOSIT | C15: 250000 | E15: =E14+C15-D15 -> 250716.64
A16: 12.02.2026 | B16: TT TRF TO SILVER STONE WIO AED | D16: 250145 | E16: =E15+C16-D16 -> 571.64
A17: 13.02.2026 | B17: CASH DEPOSIT | C17: =98500+51000+67500+68000+13500 -> 298500 | E17: =E16+C17-D17 -> 299071.64
A18: 13.02.2026 | B18: FUND RECD FROM AMINEX SIB | C18: 1800 | E18: =E17+C18-D18 -> 300871.64
A19: 13.02.2026 | B19: TT TRF TO MAADAN ALHAZAZ SAR 305807 | D19: =299944.67+52.5 -> 299997.17 | E19: =E18+C19-D19 -> 874.47
A20: 14.02.2026 | B20: FUND RECD FROM PINNACLE INT SIB | C20: 350487 | E20: =E19+C20-D20 -> 351361.47
A21: 14.02.2026 | B21: TT TRF TO MAADAN ALHAZAZ (SAR 356815) | D21: 350035.99 | E21: =E20+C21-D21 -> 1325.48
A22: 17.02.2026 | B22: FUND RECD FROM INFINITY SIB AED | C22: 94211 | E22: =E21+C22-D22 -> 95536.48
A23: 18.02.2026 | B23: FUND RECD FROM ORBIT UBL AED | C23: 274000 | E23: =E22+C23-D23 -> 369536.48
A24: 18.02.2026 | B24: TT TRF TO ALHIJAZ METAL TRADING CO (SAR 374872) | D24: =367697.44+52.5 -> 367749.94 | E24: =E23+C24-D24 -> 1786.54
A25: 20.02.2026 | B25: CASH DEPOSIT | C25: 200000 | E25: =E24+C25-D25 -> 201786.54
A26: 20.02.2026 | B26: FUND RECD FROM PINNACLE GR NBF | C26: 50000 | E26: =E25+C26-D26 -> 251786.54
A27: 20.02.2026 | B27: FUND RECD FROM PINNACLE GR NBF | C27: 50000 | E27: =E26+C27-D27 -> 301786.54
A28: 20.02.2026 | B28: FUND RECD FROM PINNACLE GR NBF | C28: 41012 | E28: =E27+C28-D28 -> 342798.54
A29: 20.02.2026 | B29: FUND RECD FROM PINNACLE INT FAB | C29: 123856 | E29: =E28+C29-D29 -> 466654.54
A30: 20.02.2026 | B30: CASH DEPOSIT | C30: 15000 | E30: =E29+C30-D30 -> 481654.54
A31: 20.02.2026 | B31: TT TRF TO ALHIJAZ METAL TRADING CO (SAR 489242) | D31: =479796.57+52.5 -> 479849.07 | E31: =E30+C31-D31 -> 1805.47
A32: 21.02.2026 | B32: BANK CHARGES | D32: 99 | E32: =E31+C32-D32 -> 1706.47
A33: 21.02.2026 | B33: USD TO AED | C33: 325382.2 | E33: =E32+C33-D33 -> 327088.67
A34: 21.02.2026 | B34: TT TRF TO ALHIJAZ METAL TRADING CO (SAR 244385) | D34: =239640.83+52.5 -> 239693.33 | E34: =E33+C34-D34 -> 87395.34
A35: 21.02.2026 | B35: TT TRF TO AMINEX SIB AED | D35: 86204 | E35: =E34+C35-D35 -> 1191.34
A36: 23.02.2026 | B36: FUND RECD FROM INFINITY SIB AED | C36: 479231 | E36: =E35+C36-D36 -> 480422.34
A37: 23.02.2026 | B37: TT TRF TO ALHIJAZ METAL TRADING CO (SAR 488886) | D37: =479447.41+52.5 -> 479499.91 | E37: =E36+C37-D37 -> 922.43
A38: 24.02.2026 | B38: USD TO AED | C38: 877203.4 | E38: =E37+C38-D38 -> 878125.83
A39: 24.02.2026 | B39: TT TRF TO AMINEX SIB AED | D39: 450213 | E39: =E38+C39-D39 -> 427912.83
A40: 24.02.2026 | B40: TT TRF TO SILVER STONE WIO AED | D40: 426801 | E40: =E39+C40-D40 -> 1111.83
E41: =E40+C41-D41 -> 1111.83
E42: =E41+C42-D42 -> 1111.83
A43: 27.02.2026 | B43: USD TO AED | C43: 569620.7 | E43: =E42+C43-D43 -> 570732.53
A44: 27.02.2026 | B44: CASH DEPOSIT | C44: 105000 | E44: =E43+C44-D44 -> 675732.53
A45: 27.02.2026 | B45: TT TRF TO ALHIJAZ METAL TRADING CO (SAR 685704) | D45: =671732.28+52.5 -> 671784.78 | E45: =E44+C45-D45 -> 3947.75
A46: 28.02.2026 | B46: USD TO AED | C46: 323694 | E46: =E45+C46-D46 -> 327641.75
A47: 28.02.2026 | B47: TT TRF TO AMINEX SIB AED | D47: 326968 | E47: =E46+C47-D47 -> 673.75
A48: 04.03.2026 | B48: USD TO AED | C48: 640782 | E48: =E47+C48-D48 -> 641455.75
A49: 04.03.2026 | B49: TT TRF TO AGNIRA WIO | D49: 490235 | E49: =E48+C49-D49 -> 151220.75
A50: 04.03.2026 | B50: TT TRF TO AMINEX SIB AED | D50: 150845 | E50: =E49+C50-D50 -> 375.75
A51: 05.03.2026 | B51: FUND RECD FROM ORBIT SIB AED | C51: 164988 | E51: =E50+C51-D51 -> 165363.75
A52: 05.03.2026 | B52: TT TRF TO AGNIRA WIO | D52: 164805 | E52: =E51+C52-D52 -> 558.75
A53: 05.03.2026 | B53: USD TO AED | C53: 1254406 | E53: =E52+C53-D53 -> 1254964.8
A54: 05.03.2026 | B54: TT TRF TO SILVER STONE WIO AED | D54: 650311 | E54: =E53+C54-D54 -> 604653.75
A55: 05.03.2026 | B55: TT TRF TO SILVER STONE WIO AED | D55: 451785 | E55: =E54+C55-D55 -> 152868.75
A56: 05.03.2026 | B56: TT TRF TO AMINEX SIB AED | D56: 152031 | E56: =E55+C56-D56 -> 837.75
A57: 05.03.2026 | B57: FUND RECD FROM INFINITY SIB AED | C57: 35023 | E57: =E56+C57-D57 -> 35860.75
A58: 05.03.2026 | B58: TT TRF TO PT GLOBEXIM USD 9450 | D58: =34654.76+52.5 -> 34707.26 | E58: =E57+C58-D58 -> 1153.49
A59: 07.03.2026 | B59: FUND RECD FROM DEEPAK JAIN FAB | C59: 50000 | E59: =E58+C59-D59 -> 51153.49
A60: 09.03.2026 | B60: TT RETURNED TO DEEPAK JAIN FAB AED | D60: 50000 | E60: =E59+C60-D60 -> 1153.49
A61: 10.03.2026 | B61: USD TO AED | C61: 1158630 | E61: =E60+C61-D61 -> 1159783.5
A62: 10.03.2026 | B62: TT TRF TO AMINEX SIB AED | D62: 742501 | E62: =E61+C62-D62 -> 417282.5
A63: 10.03.2026 | B63: TT TRF TO ENFLOW SIB AED | D63: 1000 | E63: =E62+C63-D63 -> 416282.5
A64: 10.03.2026 | B64: TT TRF TO AMINEX SIB AED | D64: 415869 | E64: =E63+C64-D64 -> 413.5
A65: 11.03.2026 | B65: USD TO AED | C65: 1207063 | E65: =E64+C65-D65 -> 1207476.5
A66: 11.03.2026 | B66: TT TRF TO AMINEX SIB AED | D66: 658841 | E66: =E65+C66-D66 -> 548635.5
A67: 11.03.2026 | B67: TT TRF TO AMINEX SIB AED | D67: 547922 | E67: =E66+C67-D67 -> 713.5
A68: 12.03.2026 | B68: USD TO AED | C68: 1372947 | E68: =E67+C68-D68 -> 1373660.5
A69: 12.03.2026 | B69: TT TRF TO AGNIRA WIO | D69: 978470 | E69: =E68+C69-D69 -> 395190.5
A70: 12.03.2026 | B70: TT TRF TO AMINEX SIB AED | D70: 394527 | E70: =E69+C70-D70 -> 663.5
A71: 13.03.2026 | B71: USD TO AED | C71: 1101000 | E71: =E70+C71-D71 -> 1101663.5
A72: 13.03.2026 | B72: TT TRF TO AGNIRA WIO | D72: 995809 | E72: =E71+C72-D72 -> 105854.5
A73: 13.03.2026 | B73: FUND RECD FROM FINJURIS COUNSEL FZ LLC | C73: 75000 | E73: =E72+C73-D73 -> 180854.5
A74: 13.03.2026 | B74: FUND RECD FROM FINJURIS COUNSEL FZ LLC | C74: 75000 | E74: =E73+C74-D74 -> 255854.5
A75: 13.03.2026 | B75: TT TRF TO AMINEX SIB AED | D75: 254638 | E75: =E74+C75-D75 -> 1216.5
A76: 14.03.2026 | B76: USD TO AED | C76: 955594.6 | E76: =E75+C76-D76 -> 956811.1
A77: 14.03.2026 | B77: TT TRF TO AMINEX SIB AED | D77: 238032 | E77: =E76+C77-D77 -> 718779.1
A78: 14.03.2026 | B78: TT TRF TO SHRIJI INT EIB | D78: 718030 | E78: =E77+C78-D78 -> 749.1
A79: 14.03.2026 | B79: BANK CHARGES | D79: 1.05 | E79: =E78+C79-D79 -> 748.05
A80: 17.03.2026 | B80: USD TO AED | C80: 328832 | E80: =E79+C80-D80 -> 329580.05
A81: 17.03.2026 | B81: BANK CHARGES | D81: 1.05 | E81: =E80+C81-D81 -> 329579
A82: 17.03.2026 | B82: TT TRF TO AMINEX SIB AED | D82: 329013 | E82: =E81+C82-D82 -> 566
A83: 17.03.2026 | B83: BANK CHARGES | D83: 1.05 | E83: =E82+C83-D83 -> 564.95
A84: 18.03.2026 | B84: USD TO AED | C84: 414746.7 | E84: =E83+C84-D84 -> 415311.65
A85: 18.03.2026 | B85: TT TRF TO AMINEX SIB AED | D85: 414985 | E85: =E84+C85-D85 -> 326.65
A86: 23.03.2026 | B86: USD TO AED | C86: 1292243.7 | E86: =E85+C86-D86 -> 1292570.4
A87: 23.03.2026 | B87: TT TRF TO AMINEX SIB AED | D87: 1291203 | E87: =E86+C87-D87 -> 1367.35
A88: 24.03.2026 | B88: USD TO AED | C88: 273451.7 | E88: =E87+C88-D88 -> 274819.05
A89: 24.03.2026 | B89: TT TRF TO AMINEX SIB AED | D89: 273860 | E89: =E88+C89-D89 -> 959.05
A90: 27.03.2026 | B90: FUND RECD FROM INFINITY SIB AED | C90: 214500 | E90: =E89+C90-D90 -> 215459.05
A91: 27.03.2026 | B91: TT TRF TO RP ENTERPRISES (USD 58360) | D91: =214301.19+52.5 -> 214353.69 | E91: =E90+C91-D91 -> 1105.36
A92: 30.03.2026 | B92: FUND RECD FROM BLACK PEPPER GT NBF | C92: 251032 | E92: =E91+C92-D92 -> 252137.36
A93: 30.03.2026 | B93: FUND RECD FRO MJS STAR SIB AED | C93: 200315 | E93: =E92+C93-D93 -> 452452.36
A94: 30.03.2026 | B94: FUND RECD FROM ORBIT PLUS SIB AED | C94: 350000 | E94: =E93+C94-D94 -> 802452.36
A95: 30.03.2026 | B95: BANK CHARGES | D95: 1.05 | E95: =E94+C95-D95 -> 802451.31
A96: 30.03.2026 | B96: TT TRF TO LIMITELESS CONTRACTING PVT LTD (USD 197606.83) | D96: =725757.4+52.5 -> 725809.9 | E96: =E95+C96-D96 -> 76641.41
A97: 30.03.2026 | B97: TT TRF TO AMINEX SIB AED | D97: 75013 | E97: =E96+C97-D97 -> 1628.41
A98: 30.03.2026 | B98: BANK CHARGES | D98: 1.05 | E98: =E97+C98-D98 -> 1627.36
A99: 31.03.2026 | B99: BANK CHARGES | D99: 95.52 | E99: =E98+C99-D99 -> 1531.84
A100: 31.03.2026 | B100: FUND RECD FROM SWIFT BRIDGE SIB | C100: 706132 | E100: =E99+C100-D100 -> 707663.84
A101: 31.03.2026 | B101: FUND RECD FROM ORBIT SIB AED | C101: 199100 | E101: =E100+C101-D101 -> 906763.84
...

Sheet ORBIT PLUS UBL AED
A1: ORBIT PLUS UBL AED
E3: =C3 -> 0
A4: 06.02.2026 | B4: CASH DEPOSIT | C4: 600000 | E4: =E3+C4-D4 -> 600000
A5: 07.02.2026 | B5: TT TRF TO SHRIJI INT EIB AED | D5: 380640 | E5: =E4+C5-D5 -> 219360
A6: 07.02.2026 | B6: BANK CHARGES | D6: 1.05 | E6: =E5+C6-D6 -> 219358.95
A7: 07.02.2026 | B7: TT TRF TO SHRIJI INT EIB AED | D7: 214203 | E7: =E6+C7-D7 -> 5155.95
A8: 07.02.2026 | B8: BANK CHARGES | D8: 1.05 | E8: =E7+C8-D8 -> 5154.9
A9: 07.02.2026 | B9: CASH DEPOSIT | C9: 600000 | E9: =E8+C9-D9 -> 605154.9
A10: 07.02.2026 | B10: TT TRF TO SILVER STONE WIO | D10: 502385 | E10: =E9+C10-D10 -> 102769.9
A11: 07.02.2026 | B11: BANK CHARGES | D11: 1.05 | E11: =E10+C11-D11 -> 102768.85
A12: 09.02.2026 | B12: TT TRF TO AMINEX SIB AED | D12: 97520 | E12: =E11+C12-D12 -> 5248.85
A13: 09.02.2026 | B13: BANK CHARGES | D13: 1.05 | E13: =E12+C13-D13 -> 5247.8
A14: 09.02.2026 | B14: CASH DEPOSIT | C14: 850000 | E14: =E13+C14-D14 -> 855247.8
A15: 09.02.2026 | B15: TT TRF TO AMINEX SIB AED | D15: 452081 | E15: =E14+C15-D15 -> 403166.8
A16: 09.02.2026 | B16: BANK CHARGES | D16: 1.05 | E16: =E15+C16-D16 -> 403165.75
A17: 10.02.2026 | B17: TT TRF TO SILVER STONE WIO | D17: 399856 | E17: =E16+C17-D17 -> 3309.75
A18: 10.02.2026 | B18: BANK CHARGES | D18: 1.05 | E18: =E17+C18-D18 -> 3308.7
A19: 10.02.2026 | B19: CASH DEPOSIT | C19: 1600000 | E19: =E18+C19-D19 -> 1603308.7
A20: 10.02.2026 | B20: TT TRF TO SILVER STONE WIO | D20: 650130 | E20: =E19+C20-D20 -> 953178.7
A21: 12.02.2026 | B21: TT TRF TO M J S STAR EIB AED | D21: 949856 | E21: =E20+C21-D21 -> 3322.7
A22: 12.02.2026 | B22: BANK CHARGES | D22: 1.05 | E22: =E21+C22-D22 -> 3321.65
A23: 12.02.2026 | B23: CASH DEPOSIT | C23: 2400000 | E23: =E22+C23-D23 -> 2403321.6
A24: 12.02.2026 | B24: TT TRF TO M J S STAR EIB AED | D24: 1063000 | E24: =E23+C24-D24 -> 1340321.6
A25: 12.02.2026 | B25: BANK CHARGES | D25: 1.05 | E25: =E24+C25-D25 -> 1340320.6
A26: 12.02.2026 | B26: BANK CHARGES | D26: 1.05 | E26: =E25+C26-D26 -> 1340319.5
A27: 12.02.2026 | B27: TT TRF TO AMINEX SIB AED | D27: 480146 | E27: =E26+C27-D27 -> 860173.55
A28: 12.02.2026 | B28: BANK CHARGES | D28: 1.05 | E28: =E27+C28-D28 -> 860172.5
A29: 12.02.2026 | B29: TT TRF TO ENFLOW SIB AED | D29: 799857 | E29: =E28+C29-D29 -> 60315.5
A30: 12.02.2026 | B30: BANK CHARGES | D30: 1.05 | E30: =E29+C30-D30 -> 60314.45
A31: 17.02.2026 | B31: CASH DEPOSIT | C31: 2500000 | E31: =E30+C31-D31 -> 2560314.4
A32: 17.02.2026 | B32: TT TRF TO AMINEX SIB AED | D32: 612870 | E32: =E31+C32-D32 -> 1947444.4
A33: 17.02.2026 | B33: BANK CHARGES | D33: 1.05 | E33: =E32+C33-D33 -> 1947443.4
A34: 17.02.2026 | B34: TT TRF TO AMINEX SIB AED | D34: 637133 | E34: =E33+C34-D34 -> 1310310.4
A35: 17.02.2026 | B35: BANK CHARGES | D35: 1.05 | E35: =E34+C35-D35 -> 1310309.3
A36: 17.02.2026 | B36: TT TRF TO AMINEX SIB AED | D36: 145213 | E36: =E35+C36-D36 -> 1165096.3
A37: 17.02.2026 | B37: BANK CHARGES | D37: 1.05 | E37: =E36+C37-D37 -> 1165095.3
A38: 18.02.2026 | B38: TT TRF TO ORBIT PLUS WIO | D38: 274000 | E38: =E37+C38-D38 -> 891095.3
A39: 18.02.2026 | B39: BANK CHARGES | D39: 1.05 | E39: =E38+C39-D39 -> 891094.25
A40: 18.02.2026 | B40: TT TRF TO SHRIJI INT EIB AED | D40: 879080 | E40: =E39+C40-D40 -> 12014.25
A41: 18.02.2026 | B41: BANK CHARGES | D41: 1.05 | E41: =E40+C41-D41 -> 12013.2
A42: 25.02.2026 | B42: TT TRF TO TURNING POINT TOURISM LLC ADCB AED | D42: 6260 | E42: =E41+C42-D42 -> 5753.2
A43: 25.02.2026 | B43: BANK CHARGES | D43: 1.05 | E43: =E42+C43-D43 -> 5752.15
A44: 16.04.2026 | B44: BANK CHARGES | D44: 472.5 | E44: =E43+C44-D44 -> 5279.65
A45: 16.04.2026 | B45: CASH DEPOSIT | C45: 1002697.5 | E45: =E44+C45-D45 -> 1007977.1
A46: 17.04.2026 | B46: TT TRF TO ORBIT WIO AED | D46: 123500 | E46: =E45+C46-D46 -> 884477.15
A47: 17.04.2026 | B47: BANK CHARGES | D47: 1.05 | E47: =E46+C47-D47 -> 884476.1
A48: 17.04.2026 | B48: TT TRF TO AMINEX SIB AED | D48: 881503 | E48: =E47+C48-D48 -> 2973.1
A49: 17.04.2026 | B49: BANK CHARGES | D49: 1.05 | E49: =E48+C49-D49 -> 2972.05
A50: 02.05.2026 | B50: BANK CHARGES | D50: 367.5 | E50: =E49+C50-D50 -> 2604.55
A51: 05.05.2026 | B51: CASH DEPOSIT | C51: 1100000 | E51: =E50+C51-D51 -> 1102604.5
A52: 05.05.2026 | B52: TT TRF TO AMINEX SIB AED | D52: 589046 | E52: =E51+C52-D52 -> 513558.55
A53: 05.05.2026 | B53: BANK CHARGES | D53: 1.05 | E53: =E52+C53-D53 -> 513557.5
A54: 05.05.2026 | B54: TT TRF TO AMINEX SIB AED | D54: 511680 | E54: =E53+C54-D54 -> 1877.5
A55: 05.05.2026 | B55: BANK CHARGES | D55: 1.05 | E55: =E54+C55-D55 -> 1876.45
E56: =E55+C56-D56 -> 1876.45
E57: =E56+C57-D57 -> 1876.45
E58: =E57+C58-D58 -> 1876.45
E59: =E58+C59-D59 -> 1876.45
E60: =E59+C60-D60 -> 1876.45
E61: =E60+C61-D61 -> 1876.45
E62: =E61+C62-D62 -> 1876.45
E63: =E62+C63-D63 -> 1876.45
E64: =E63+C64-D64 -> 1876.45
E65: =E64+C65-D65 -> 1876.45
E66: =E65+C66-D66 -> 1876.45
E67: =E66+C67-D67 -> 1876.45
... E100: =E99+C100-D100 -> 1876.45

Sheet ORBIT PLUS SIB
C3: 5000 | E3: =C3 -> 5000
B4: BANK CHARGES | D4: 628.5 | E4: =E3+C4-D4 -> 4371.5
A5: 12.12.2025 | B5: CASH DEPOSIT | C5: 244000 | E5: =E4+C5-D5 -> 248371.5
A6: 12.12.2025 | B6: TT TRF TO AMINEX SIB | D6: 246908 | E6: =E5+C6-D6 -> 1463.5
A7: 12.12.2025 | B7: BANK CHARGES | D7: 425.25 | E7: =E6+C7-D7 -> 1038.25
A8: 16.12.2025 | B8: CASH DEPOSIT | C8: 250000 | E8: =E7+C8-D8 -> 251038.25
A9: 16.12.2025 | B9: TT TRF TO SHRIJI INT EIB | D9: 250031 | E9: =E8+C9-D9 -> 1007.25
A10: 16.12.2025 | B10: BANK CHARGES | D10: 1.05 | E10: =E9+C10-D10 -> 1006.2
A11: 16.12.2025 | B11: CASH DEPOSIT | C11: 100000 | E11: =E10+C11-D11 -> 101006.2
A12: 16.12.2025 | B12: TT TRF TO AMINEX SIB | D12: 100264 | E12: =E11+C12-D12 -> 742.2
A13: 17.12.2025 | B13: CASH DEPOSIT | C13: 250000 | E13: =E12+C13-D13 -> 250742.2
A14: 17.12.2025 | B14: CASH DEPOSIT | C14: 99500 | E14: =E13+C14-D14 -> 350242.2
A15: 17.12.2025 | B15: TT TRF TO ROYAL ENBD AED | D15: 349985 | E15: =E14+C15-D15 -> 257.2
A16: 17.12.2025 | B16: BANK CHARGES | D16: 1.05 | E16: =E15+C16-D16 -> 256.15
A17: 19.12.2025 | B17: CASH DEPOSIT | C17: 250000 | E17: =E16+C17-D17 -> 250256.15
A18: 19.12.2025 | B18: TT TRF TO AMINEX SIB | D18: 249893 | E18: =E17+C18-D18 -> 363.15
A19: 31.12.2025 | B19: CASH DEPOSIT | C19: 100000 | E19: =E18+C19-D19 -> 100363.15
A20: 31.12.2025 | B20: FUND RECD FROM BULLFROG NBF | C20: 154000 | E20: =E19+C20-D20 -> 254363.15
A21: 31.12.2025 | B21: FUND RECD FROM BULLFROG NBF | C21: 177023 | E21: =E20+C21-D21 -> 431386.15
A22: 31.12.2025 | B22: TT TRF TO JUDICIARY DEPT. ABU DHABI COURT AJIT RAO | D22: 400000 | E22: =E21+C22-D22 -> 31386.15
A23: 31.12.2025 | B23: TT TRF TO ROYAL SIB AED | D23: 31023 | E23: =E22+C23-D23 -> 363.15
A24: 02.01.2026 | B24: BANK CHARGES | D24: 336 | E24: =E23+C24-D24 -> 27.15
A25: 02.01.2026 | B25: BANK CHARGES | D25: 20 | E25: =E24+C25-D25 -> 7.15
A26: 02.01.2026 | B26: BANK CHARGES | D26: 71.05 | E26: =E25+C26-D26 -> -63.9
A27: 16.01.2026 | B27: CASH DEPOSIT | C27: 142500 | E27: =E26+C27-D27 -> 142436.1
A28: 16.01.2026 | B28: TT TRF TO AMINEX SIB | D28: 142031 | E28: =E27+C28-D28 -> 405.1
A29: 19.01.2026 | B29: CASH DEPOSIT | C29: 79900 | E29: =E28+C29-D29 -> 80305.1
A30: 19.01.2026 | B30: TT TRF TO AMINEX SIB | D30: 79803 | E30: =E29+C30-D30 -> 502.1
A31: 20.01.2026 | B31: CASH DEPOSIT | C31: 263000 | E31: =E30+C31-D31 -> 263502.1
A32: 20.01.2026 | B32: TT TRF TO ROYAL ENBD AED | D32: 263003 | E32: =E31+C32-D32 -> 499.1
A33: 20.01.2026 | B33: BANK CHARGES | D33: 1.05 | E33: =E32+C33-D33 -> 498.05
A34: 21.01.2026 | B34: CASH DEPOSIT | C34: 250000 | E34: =E33+C34-D34 -> 250498.05
A35: 21.01.2026 | B35: TT TRF TO SILVER STONE WIO | D35: 250031 | E35: =E34+C35-D35 -> 467.05
A36: 21.01.2026 | B36: BANK CHARGES | D36: 1.05 | E36: =E35+C36-D36 -> 466
A37: 23.01.2026 | B37: CASH DEPOSIT | C37: 200000 | E37: =E36+C37-D37 -> 200466
A38: 23.01.2026 | B38: TT TRF TO SILVER STONE WIO | D38: 200104 | E38: =E37+C38-D38 -> 362
A39: 23.01.2026 | B39: BANK CHARGES | D39: 1.05 | E39: =E38+C39-D39 -> 360.95
A40: 27.01.2026 | B40: CASH DEPOSIT | C40: 200000 | E40: =E39+C40-D40 -> 200360.95
A41: 27.01.2026 | B41: TT TRF TO AMINEX SIB | D41: 200013 | E41: =E40+C41-D41 -> 347.95
A42: 28.01.2026 | B42: CASH DEPOSIT | C42: 250000 | E42: =E41+C42-D42 -> 250347.95
A43: 28.01.2026 | B43: TT TRF TO SHRIJI INT EIB | D43: 250014 | E43: =E42+C43-D43 -> 333.95
A44: 28.01.2026 | B44: BANK CHARGES | D44: 1.05 | E44: =E43+C44-D44 -> 332.9
A45: 02.02.2026 | B45: BANK CHARGES | D45: 308.4 | E45: =E44+C45-D45 -> 24.5
A46: 02.02.2026 | B46: BANK CHARGES | D46: 116.1 | E46: =E45+C46-D46 -> -91.6 | F46: =+D46-8 -> 108.1
A47: 03.02.2026 | B47: CASH DEPOSIT | C47: =225000+25000 -> 250000 | E47: =E46+C47-D47 -> 249908.4
A48: 03.02.2026 | B48: FUND RECD FROM SWIFT BRIDGE SIB | C48: 248804 | E48: =E47+C48-D48 -> 498712.4
A49: 03.02.2026 | B49: TT TRF TO ENFLOW SIB AED | D49: 299230 | E49: =E48+C49-D49 -> 199482.4 | F49: =+E49-498712.4 -> -299230
A50: 03.02.2026 | B50: TT TRF TO AMINEX SIB | D50: 199024 | E50: =E49+C50-D50 -> 458.4
A51: 04.02.2026 | B51: CASH DEPOSIT | C51: 200000 | E51: =E50+C51-D51 -> 200458.4
A52: 04.02.2026 | B52: FUND RECD FROM SWIFT BRIDGE SIB | C52: 249250 | E52: =E51+C52-D52 -> 449708.4
A53: 04.02.2026 | B53: TT TRF TO ENFLOW SIB AED | D53: 448950 | E53: =E52+C53-D53 -> 758.4
A54: 07.02.2026 | B54: FUND RECD FROM BULLFROG NBF | C54: 50000 | E54: =E53+C54-D54 -> 50758.4
A55: 07.02.2026 | B55: TT TRF TO TRADERS VENTURES EIB | D55: 1000 | E55: =E54+C55-D55 -> 49758.4
A56: 07.02.2026 | B56: TT TRF TO TRADERS VENTURES EIB | D56: 49015 | E56: =E55+C56-D56 -> 743.4
A57: 07.02.2026 | B57: BANK CHARGES | D57: 1 | E57: =E56+C57-D57 -> 742.4
A58: 10.02.2026 | B58: CASH DEPOSIT | C58: 248000 | E58: =E57+C58-D58 -> 248742.4
A59: 10.02.2026 | B59: TT TRF TO SILVER STONE WIO | D59: 248234 | E59: =E58+C59-D59 -> 508.4
A60: 10.02.2026 | B60: BANK CHARGES | D60: 1.05 | E60: =E59+C60-D60 -> 507.35
A61: 10.02.2026 | B61: FUND RECD FROM BLACK PEPPER SIB AED | C61: 249203 | E61: =E60+C61-D61 -> 249710.35
A62: 10.02.2026 | B62: TT TRF TO SILVER STONE WIO | D62: 149201 | E62: =E61+C62-D62 -> 100509.35
A63: 10.02.2026 | B63: BANK CHARGES | D63: 1.05 | E63: =E62+C63-D63 -> 100508.3
A64: 10.02.2026 | B64: TT TRF TO KOTHARI MISR AED | D64: 100014 | E64: =E63+C64-D64 -> 494.3
A65: 10.02.2026 | B65: BANK CHARGES | D65: 1.05 | E65: =E64+C65-D65 -> 493.25
A66: 12.02.2026 | B66: FUND RECD FROM BULLFROG NBF | C66: 22500 | E66: =E65+C66-D66 -> 22993.25
A67: 12.02.2026 | B67: TT TRF TO ROSHAN ZAMEER MSQ | D67: 22400 | E67: =E66+C67-D67 -> 593.25
A68: 12.02.2026 | B68: BANK CHARGES | D68: 0.5 | E68: =E67+C68-D68 -> 592.75
A69: 02.03.2026 | B69: FUND RECD FROM AMINEX SIB AED | C69: 1687 | E69: =E68+C69-D69 -> 2279.75
A70: 02.03.2026 | B70: FTA PAYMENT | D70: 1743.07 | E70: =E69+C70-D70 -> 536.68
A71: 02.03.2026 | B71: BANK CHARGES | D71: 0.5 | E71: =E70+C71-D71 -> 536.18
A72: 02.03.2026 | B72: BANK CHARGES | D72: 425.25 | E72: =E71+C72-D72 -> 110.93
A73: 04.03.2026 | B73: FUND RECD FROM PINNACLE GR NBF AED | C73: 665230 | E73: =E72+C73-D73 -> 665340.93
A74: 04.03.2026 | B74: TT TRF TO ROYAL NBF AED | D74: 499903 | E74: =E73+C74-D74 -> 165437.93
A75: 04.03.2026 | B75: BANK CHARGES | D75: 1.05 | E75: =E74+C75-D75 -> 165436.88
A76: 05.03.2026 | B76: TT TRF TO ORBIT WIO AED | D76: 164988 | E76: =E75+C76-D76 -> 448.88
A77: 06.03.2026 | B77: CASH DEPOSIT | C77: 199000 | E77: =E76+C77-D77 -> 199448.88
A78: 06.03.2026 | B78: BANK CHARGES | D78: 1.6 | E78: =E77+C78-D78 -> 199447.28
A79: 06.03.2026 | B79: TT TRF TO SHRIJI INT EIB | D79: 199023 | E79: =E78+C79-D79 -> 424.28
A80: 06.03.2026 | B80: BANK CHARGES | D80: 1.05 | E80: =E79+C80-D80 -> 423.23
A81: 18.03.2026 | B81: CASH DEPOSIT | C81: 176500 | E81: =E80+C81-D81 -> 176923.23
A82: 18.03.2026 | B82: BANK CHARGES | D82: 210 | E82: =E81+C82-D82 -> 176713.23
A83: 18.03.2026 | B83: TT TRF TO AMINEX SIB | D83: 175969 | E83: =E82+C83-D83 -> 744.23
A84: 30.03.2026 | B84: CASH DEPOSIT | C84: 200000 | E84: =E83+C84-D84 -> 200744.23
A85: 30.03.2026 | B85: FUND RECD FROM SWIFT BRIDGE SIB | C85: 149680 | E85: =E84+C85-D85 -> 350424.23
A86: 30.03.2026 | B86: TT TRF TO ORBIT WIO AED | D86: 350000 | E86: =E85+C86-D86 -> 424.23
A87: 30.03.2026 | B87: BANK CHARGES | D87: 1.05 | E87: =E86+C87-D87 -> 423.18
A88: 31.03.2026 | B88: CASH DEPOSIT | C88: 199000 | E88: =E87+C88-D88 -> 199423.18
A89: 31.03.2026 | B89: BANK CHARGES | D89: 5.25 | E89: =E88+C89-D89 -> 199417.93
A90: 31.03.2026 | B90: TT TRF TO ORBIT WIO AED | D90: 199100 | E90: =E89+C90-D90 -> 317.93
A91: 31.03.2026 | B91: BANK CHARGES | D91: 1.05 | E91: =E90+C91-D91 -> 316.88
A92: 31.03.2026 | B92: FUND RECD FROM BLACK PEPPER NBF AED | C92: 8520 | E92: =E91+C92-D92 -> 8836.88
A93: 31.03.2026 | B93: TT TRF TO ROSHAN ZAMEER MSQ | D93: 8300 | E93: =E92+C93-D93 -> 536.88
A94: 31.03.2026 | B94: BANK CHARGES | D94: 0.5 | E94: =E93+C94-D94 -> 536.38
A95: 01.04.2026 | B95: BANK CHARGES | D95: 420 | E95: =E94+C95-D95 -> 116.38
A96: 06.04.2026 | B96: CASH DEPOSIT | C96: 274500 | E96: =E95+C96-D96 -> 274616.38
A97: 07.04.2026 | B97: TT TRF TO AMINEX SIB | D97: 273980 | E97: =E96+C97-D97 -> 636.38
A98: 08.04.2026 | B98: FUND RECD FROM INVESTRADE PTE | C98: 789755 | E98: =E97+C98-D98 -> 790391.38
A99: 08.04.2026 | B99: TT TRF TO VERTEX VISION FAB AED | D99: 499996 | E99: =E98+C99-D99 -> 290395.38
A100: 08.04.2026 | B100: BANK CHARGES | D100: 1.05 | E100: =E99+C100-D100 -> 290394.33
A101: 08.04.2026 | B101: TT TRF TO AMINEX SIB | D101: 288968 | E101: =E100+C101-D101 -> 1426.33
A102: 09.04.2026 | B102: FUND RECD FROM INVESTRADE PTE | C102: 327835 | E102: =E101+C102-D102 -> 329261.33
...

Sheet ORBIT PLUS ADIB AED
A1: ORBIT PLUS ADIB AED
E3: =C3 -> 0
A4: 26.02.2026 | B4: FUND RECD FROM PINNACLE GR NBF | C4: 6000 | E4: =E3+C4-D4 -> 6000
A5: 27.02.2026 | B5: BANK CHARGES | D5: 105 | E5: =E4+C5-D5 -> 5895
A6: 27.02.2026 | B6: AED TO USD | D6: 927.38 | E6: =E5+C6-D6 -> 4967.62
A7: 28.02.2026 | B7: AED TO USD | D7: 4700 | E7: =E6+C7-D7 -> 267.62
A8: 01.03.2026 | B8: BANK CHARGES | D8: 105 | E8: =E7+C8-D8 -> 162.62
A9: 02.05.2026 | B9: BANK CHARGES | D9: 105 | E9: =E8+C9-D9 -> 57.62
E10: =E9+C10-D10 -> 57.62
E11: =E10+C11-D11 -> 57.62
E12: =E11+C12-D12 -> 57.62
E13: =E12+C13-D13 -> 57.62
E14: =E13+C14-D14 -> 57.62
E15: =E14+C15-D15 -> 57.62
E16: =E15+C16-D16 -> 57.62
E17: =E16+C17-D17 -> 57.62
E18: =E17+C18-D18 -> 57.62
E19: =E18+C19-D19 -> 57.62
E20: =E19+C20-D20 -> 57.62
E21: =E20+C21-D21 -> 57.62
... E140: =E139+C140-D140 -> 57.62

Sheet ORBIT PLUS ADIB USD
A1: ORBIT PLUS ADIB USD
E3: =C3 -> 0
A4: 27.02.2026 | B4: AED TO USD | C4: 250 | E4: =E3+C4-D4 -> 250
A5: 28.02.2026 | B5: AED TO USD | C5: 1267.02 | E5: =E4+C5-D5 -> 1517.02
A6: 01.04.2026 | B6: BANK INTEREST | C6: 0.36 | E6: =E5+C6-D6 -> 1517.38
E7: =E6+C7-D7 -> 1517.38
E8: =E7+C8-D8 -> 1517.38
E9: =E8+C9-D9 -> 1517.38
E10: =E9+C10-D10 -> 1517.38
E11: =E10+C11-D11 -> 1517.38
E12: =E11+C12-D12 -> 1517.38
E13: =E12+C13-D13 -> 1517.38
E14: =E13+C14-D14 -> 1517.38
E15: =E14+C15-D15 -> 1517.38
E16: =E15+C16-D16 -> 1517.38
E17: =E16+C17-D17 -> 1517.38
E18: =E17+C18-D18 -> 1517.38
... E100: =E99+C100-D100 -> 1517.38

Sheet CROSSFIT MSQ
A1: CROSSFIT MSQ AED
A2: DATE | B2: PARTICULARS | C2: DEPOSIT | D2: WITHDRAWAL | E2: BALANCE
C3: 11021 | E3: =C3 -> 11021
D4: 9500 | E4: =E3+C4-D4 -> 1521
A5: 19.11.2025 | B5: CASH DEPSOT | C5: 299000 | E5: =E4+C5-D5 -> 300521
A6: 19.11.2025 | B6: TT TRF TO AMINEX ADIB | D6: 100000 | E6: =E5+C6-D6 -> 200521
A7: 19.11.2025 | B7: TT TRF TO AMINEX ADIB | D7: 199696 | E7: =E6+C7-D7 -> 825
A8: 19.11.2025 | B8: BANK CHARGES | D8: 2.1 | E8: =E7+C8-D8 -> 822.9
A9: 13.12.2025 | B9: FUND RECD FROM SILVER CROSS EQUIPMENT MISR | C9: 980528 | E9: =E8+C9-D9 -> 981350.9
A10: 13.12.2025 | B10: TT TRF TO SILVER SAGE MSQ | D10: 120018 | E10: =E9+C10-D10 -> 861332.9
A11: 23.12.2025 | B11: CASH DEPOSIT | C11: 120500 | E11: =E10+C11-D11 -> 981832.9
A12: 23.12.2025 | B12: BANK CHARGES | D12: 525 | E12: =E11+C12-D12 -> 981307.9
A13: 25.12.2025 | B13: RETURNED RECD FROM SILVER CROSS EQUIPMENT MISR | D13: 980528 | E13: =E12+C13-D13 -> 779.9 | F13: =+E13-779.9 -> 2.3305802e-11
A14: 02.01.2026 | B14: BANK CHARGES | D14: 210 | E14: =E13+C14-D14 -> 569.9
E15: =E14+C15-D15 -> 569.9
E16: =E15+C16-D16 -> 569.9
E17: =E16+C17-D17 -> 569.9
E18: =E17+C18-D18 -> 569.9
E19: =E18+C19-D19 -> 569.9
E20: =E19+C20-D20 -> 569.9
E21: =E20+C21-D21 -> 569.9
E22: =E21+C22-D22 -> 569.9
E23: =E22+C23-D23 -> 569.9
E24: =E23+C24-D24 -> 569.9
E25: =E24+C25-D25 -> 569.9
E26: =E25+C26-D26 -> 569.9
... E100: =E99+C100-D100 -> 569.9

Sheet CROSSFIT SIB AED
A1: CROSSFIT SIB AED
A2: DATE | B2: PARTICULARS | C2: DEPOSIT | D2: WITHDRAWAL | E2: BALANCE
A3: 30.01.2026 | C3: 5000 | E3: =C3 -> 5000
A4: 02.02.2026 | B4: BANK CHARGES | D4: 210 | E4: =E3+C4-D4 -> 4790
A5: 06.03.2026 | B5: BANK CHARGES | D5: 425.25 | E5: =E4+C5-D5 -> 4364.75
A6: 01.04.2026 | B6: BANK CHARGES | D6: 425.25 | E6: =E5+C6-D6 -> 3939.5
A7: 07.04.2026 | B7: TT TRF TO AGNIRA INT WIO AED | D7: 1000 | E7: =E6+C7-D7 -> 2939.5
A8: 07.04.2026 | B8: BANK CHARGES | D8: 0.5 | E8: =E7+C8-D8 -> 2939
A9: 07.04.2026 | B9: FUND RECD FROM OPTICORE SIB AED | C9: 202860 | E9: =E8+C9-D9 -> 205799
A10: 07.04.2026 | B10: TT TRF TO AGNIRA INT WIO AED | D10: 204890 | E10: =E9+C10-D10 -> 909
A11: 07.04.2026 | B11: BANK CHARGES | D11: 1.05 | E11: =E10+C11-D11 -> 907.95
A12: 10.04.2026 | B12: CASH DEPOSIT | E12: =E11+C12-D12 -> 907.95
A13: 10.04.2026 | B13: FUND RECD FROM OPTICORE SIB AED | C13: 250100 | E13: =E12+C13-D13 -> 251007.95
A14: 10.04.2026 | B14: CASH DEPOSIT | C14: 200000 | E14: =E13+C14-D14 -> 451007.95
A15: 10.04.2026 | B15: TT TRF TO SWIFT BRIDGE SIB | D15: 450645 | E15: =E14+C15-D15 -> 362.95
A16: 15.04.2026 | B16: CASH DEPOSIT | C16: 100000 | E16: =E15+C16-D16 -> 100362.95
A17: 15.04.2026 | B17: FUND RECD FROM OPTICORE SIB AED | C17: 243900 | E17: =E16+C17-D17 -> 344262.95
A18: 15.04.2026 | B18: TT TRF TO AGINCO MSQ | D18: 110230 | E18: =E17+C18-D18 -> 234032.95
A19: 15.04.2026 | B19: BANK CHARGES | D19: 1.05 | E19: =E18+C19-D19 -> 234031.9
A20: 15.04.2026 | B20: FUND RECD FROM M J S STAR SIB AED | C20: 201560 | E20: =E19+C20-D20 -> 435591.9
A21: 15.04.2026 | B21: TT TRF TO AGINCO MSQ | D21: 434550 | E21: =E20+C21-D21 -> 1041.9
A22: 15.04.2026 | B22: BANK CHARGES | D22: 1.05 | E22: =E21+C22-D22 -> 1040.85
A23: 17.04.2026 | B23: CASH DEPOSIT | C23: 56000 | E23: =E22+C23-D23 -> 57040.85
A24: 17.04.2026 | B24: TT TRF TO AMINEX SIB | D24: 56500 | E24: =E23+C24-D24 -> 540.85
A25: 30.04.2026 | B25: CASH DEPOSIT | C25: 200000 | E25: =E24+C25-D25 -> 200540.85
A26: 30.04.2026 | B26: TT TRF TO SWIFT BRIDGE SIB | D26: 200243 | E26: =E25+C26-D26 -> 297.85
E27: =E26+C27-D27 -> 297.85
E28: =E27+C28-D28 -> 297.85
E29: =E28+C29-D29 -> 297.85
E30: =E29+C30-D30 -> 297.85
E31: =E30+C31-D31 -> 297.85
E32: =E31+C32-D32 -> 297.85
E33: =E32+C33-D33 -> 297.85
E34: =E33+C34-D34 -> 297.85
E35: =E34+C35-D35 -> 297.85
E36: =E35+C36-D36 -> 297.85
E37: =E36+C37-D37 -> 297.85
E38: =E37+C38-D38 -> 297.85
... E130: =E129+C130-D130 -> 297.85

Sheet SWIFT BRIDGE ENBD AED
A1: SWIFT BRIDGE ENBD AED
A4: 14.03.2026 | B4: FUND RECD FROM SWIFT BRIDGE SIB AED | C4: 5000 | E4: =C4 -> 5000
A5: 10.04.2026 | B5: BANK CHARGES | D5: =7.5+150+4.95 -> 162.45 | E5: =E4+C5-D5 -> 4837.55
A6: 10.04.2026 | B6: BANK CHARGES | D6: 99 | E6: =E5+C6-D6 -> 4738.55
E7: =E6+C7-D7 -> 4738.55
E8: =E7+C8-D8 -> 4738.55
E9: =E8+C9-D9 -> 4738.55
E10: =E9+C10-D10 -> 4738.55
E11: =E10+C11-D11 -> 4738.55
E12: =E11+C12-D12 -> 4738.55
E13: =E12+C13-D13 -> 4738.55
E14: =E13+C14-D14 -> 4738.55
E15: =E14+C15-D15 -> 4738.55
E16: =E15+C16-D16 -> 4738.55
E17: =E16+C17-D17 -> 4738.55
E18: =E17+C18-D18 -> 4738.55
... E210: =E209+C210-D210 -> 4738.55

Sheet SWIFT BRIDGE MSQ AED
A1: SWIFT BRIDGE AED
A4: 23.10.2025 | B4: FUND RECD FROM | C4: 12896 | E4: =C4 -> 12896
A5: 23.10.2025 | B5: BANK CHARGES | D5: 640.5 | E5: =E4+C5-D5 -> 12255.5
A6: 24.10.2025 | B6: CHQ PAID 000001 TO BLUE TITAN BUSINESS CENTER | D6: 8333 | E6: =E5+C6-D6 -> 3922.5
B7: BANK CHARGES | D7: 210 | E7: =E6+C7-D7 -> 3712.5
B8: BANK CHARGES | D8: 315 | E8: =E7+C8-D8 -> 3397.5
A9: 01.12.2025 | B9: BANK CHARGES | D9: 210 | E9: =E8+C9-D9 -> 3187.5
A10: 01.12.2025 | B10: BANK CHARGES | D10: 315 | E10: =E9+C10-D10 -> 2872.5
A11: 02.01.2026 | B11: BANK CHARGES | D11: 210 | E11: =E10+C11-D11 -> 2662.5
A12: 24.02.2026 | B12: FUND RECD FROM CAPS LOCK FAB AED | C12: 8623 | E12: =E11+C12-D12 -> 11285.5
A13: 24.02.2026 | B13: BANK CHARGES | D13: 210 | E13: =E12+C13-D13 -> 11075.5
A14: 25.02.2026 | B14: CHQ PAID TO BLUE TITAN BUSINESS CENTER | D14: 8333 | E14: =E13+C14-D14 -> 2742.5
A15: 09.04.2026 | B15: BANK CHARGES | D15: 210 | E15: =E14+C15-D15 -> 2532.5
A16: 09.04.2026 | B16: BANK CHARGES | D16: 210 | E16: =E15+C16-D16 -> 2322.5
A17: 09.04.2026 | B17: FUND RECD FROM BLACK PEPPER NBF | C17: 7231 | E17: =E16+C17-D17 -> 9553.5
A18: 13.04.2026 | B18: CHQ PAID TO ALI SADEK HUSSAIN AL JAFFAR AND FUAD | D18: 8250 | E18: =E17+C18-D18 -> 1303.5
E19: =E18+C19-D19 -> 1303.5
E20: =E19+C20-D20 -> 1303.5
E21: =E20+C21-D21 -> 1303.5
E22: =E21+C22-D22 -> 1303.5
E23: =E22+C23-D23 -> 1303.5
E24: =E23+C24-D24 -> 1303.5
E25: =E24+C25-D25 -> 1303.5
E26: =E25+C26-D26 -> 1303.5
E27: =E26+C27-D27 -> 1303.5
E28: =E27+C28-D28 -> 1303.5
E29: =E28+C29-D29 -> 1303.5
E30: =E29+C30-D30 -> 1303.5
... E210: =E209+C210-D210 -> 1303.5

Sheet TRADERS EIB
A1: TRADERS VENTURES EIB AED
A2: DATE | B2: PARTICULAR | C2: DEPOSIT | D2: WITHDRAWAL | E2: BALANCE
A3: 07.10.2025 | B3: BANK CHARGES | E3: 1225.43
A4: 02.12.2025 | B4: BANK CHARGES | D4: 577.5 | E4: =E3+C4-D4 -> 647.93 | F4: =+E4-647.93 -> 0
A5: 02.01.2026 | B5: BANK CHARGES | D5: 225 | E5: =E4+C5-D5 -> 422.93
A6: 02.01.2026 | B6: BANK CHARGES | D6: 11 | E6: =E5+C6-D6 -> 411.93
A7: 07.02.2026 | B7: FUND RECD FROM ORBIT PLUS SIB AED | C7: 1000 | E7: =E6+C7-D7 -> 1411.93
A8: 07.02.2026 | B8: FUND RECD FROM ORBIT PLUS SIB AED | C8: 49015 | E8: =E7+C8-D8 -> 50426.93
A9: 09.02.2026 | B9: TT TRF TO SWIFT BRIDGE SIB AED | D9: 49047 | E9: =E8+C9-D9 -> 1379.93
A10: 09.02.2026 | B10: BANK CHARGES | D10: 1.05 | E10: =E9+C10-D10 -> 1378.88
A11: 06.03.2026 | B11: BANK CHARGES | D11: 631.3 | E11: =E10+C11-D11 -> 747.58
A12: 10.03.2026 | B12: FUND RECD FROM COMIDA NBF | C12: 9700 | E12: =E11+C12-D12 -> 10447.58
A13: 10.03.2026 | B13: TT TRF TO CRIF GULF CITI AED | D13: 9640.31 | E13: =E12+C13-D13 -> 807.27
A14: 25.03.2026 | B14: FUND RECD FROM AMINEX SIB AED | C14: 99588 | E14: =E13+C14-D14 -> 100395.27
A15: 25.03.2026 | B15: FUND RECD FROM AMINEX SIB AED | C15: 1863 | E15: =E14+C15-D15 -> 102258.27
A16: 25.03.2026 | B16: TT TRF TO DSK LEGAL (USD 27487) | D16: 101482 | E16: =E15+C16-D16 -> 776.27
A17: 11.04.2026 | B17: BANK CHARGES | D17: 290.85 | E17: =E16+C17-D17 -> 485.42
A18: 11.04.2026 | B18: FUND RECD FROM RAYMOND WIO | C18: 100 | E18: =E17+C18-D18 -> 585.42
A19: 11.04.2026 | B19: FUND RECD FROM RAYMOND WIO | C19: 333000 | E19: =E18+C19-D19 -> 333585.42
A20: 15.04.2026 | B20: TT TRF TO SWIFT BRIDGE SIB AED | D20: 332500 | E20: =E19+C20-D20 -> 1085.42
A21: 15.04.2026 | B21: BANK CHARGES | D21: 1.05 | E21: =E20+C21-D21 -> 1084.37
E22: =E21+C22-D22 -> 1084.37
E23: =E22+C23-D23 -> 1084.37
E24: =E23+C24-D24 -> 1084.37
E25: =E24+C25-D25 -> 1084.37
E26: =E25+C26-D26 -> 1084.37
E27: =E26+C27-D27 -> 1084.37
E28: =E27+C28-D28 -> 1084.37
E29: =E28+C29-D29 -> 1084.37
E30: =E29+C30-D30 -> 1084.37
E31: =E30+C31-D31 -> 1084.37
E32: =E31+C32-D32 -> 1084.37
E33: =E32+C33-D33 -> 1084.37
... E100: =E99+C100-D100 -> 1084.37

Sheet GLUCKRICH MISR AED
A1: GLUCKRICH MISR AED
A2: DATE | B2: PARTICULAR | C2: DEPOSIT | D2: WITHDRAWAL | E2: BALANCE
B3: O/P BAL | E3: 17931.15
A4: 04.10.2025 | B4: FUND RECD FROM PINNACLE GR NBF | C4: 100409 | E4: =E3+C4-D4 -> 118340.15
A5: 04.10.2025 | B5: SALARY PAID SANDEEP DHANUKA | D5: 75000 | E5: =E4+C5-D5 -> 43340.15 | J5: =+E6-43329.65 -> 0
A6: 04.10.2025 | B6: BANK CHARGES | D6: 10.5 | E6: =E5+C6-D6 -> 43329.65
A7: 14.10.2025 | B7: FUND RECD FROM PINNACLE GR NBF | C7: 62301 | E7: =E6+C7-D7 -> 105630.65
A8: 15.10.2025 | B8: TT TRF TO ASHISH DHANUKA MSQ AED | D8: 100000 | E8: =E7+C8-D8 -> 5630.65
A9: 15.10.2025 | B9: FUND RECD FROM PINNACLE GR NBF | C9: 21325 | E9: =E8+C9-D9 -> 26955.65
A10: 15.10.2025 | B10: TT TRF TO ASHISH DHANUKA MSQ AED | D10: 15000 | E10: =E9+C10-D10 -> 11955.65
A11: 15.10.2025 | B11: BANK CHARGES | D11: 10.5 | E11: =E10+C11-D11 -> 11945.15
A12: 14.11.2025 | B12: FUND RECD FROM PINNACLE GR NBF | C12: 737286 | E12: =E11+C12-D12 -> 749231.15
A13: 14.11.2025 | B13: FUND RECD FROM PINNACLE GR NBF | C13: 18596 | E13: =E12+C13-D13 -> 767827.15
A14: 17.11.2025 | B14: TT TRF TO SECOND STREET SBM (USD 206000) | D14: =206000*3.68 -> 758080 | E14: =E13+C14-D14 -> 9747.15
A15: 19.11.2025 | B15: BANK CHARGES | D15: 52.5 | E15: =E14+C15-D15 -> 9694.65
A16: 19.11.2025 | C16: 17.11 | E16: =E15+C16-D16 -> 9711.76
A17: 10.12.2025 | B17: TT TRF TO GLUCKRICH NBF AED | D17: 5000 | E17: =E16+C17-D17 -> 4711.76
E18: =E17+C18-D18 -> 4711.76
E19: =E18+C19-D19 -> 4711.76
E20: =E19+C20-D20 -> 4711.76
E21: =E20+C21-D21 -> 4711.76
E22: =E21+C22-D22 -> 4711.76
E23: =E22+C23-D23 -> 4711.76
E24: =E23+C24-D24 -> 4711.76
E25: =E24+C25-D25 -> 4711.76
E26: =E25+C26-D26 -> 4711.76
E27: =E26+C27-D27 -> 4711.76
E28: =E27+C28-D28 -> 4711.76
E29: =E28+C29-D29 -> 4711.76
... E100: =E99+C100-D100 -> 4711.76

Sheet GLUCKRICH NBF AED
A1: GLUCKRICH NBF AED
A2: DATE | B2: PARTICULAR | C2: DEPOSIT | D2: WITHDRAWAL | E2: BALANCE
A3: 10.12.2025 | B3: FUND RECD FROM GLUCKRICH MISR AED | C3: 5000 | E3: 5000
A4: 10.12.2025 | B4: BANK CHARGES | D4: 1.05 | E4: =E3+C4-D4 -> 4998.95
A5: 05.01.2026 | B5: FUND RECD FROM PINNACLE INT | C5: 26235 | E5: =E4+C5-D5 -> 31233.95
A6: 05.01.2026 | B6: FUND RECD FROM PINNACLE INT | C6: 2301 | E6: =E5+C6-D6 -> 33534.95
A7: 05.01.2026 | B7: TT TRF TO ASHISH DHANUKA | D7: 31000 | E7: =E6+C7-D7 -> 2534.95
A8: 06.01.2026 | B8: FUND RECD FROM PINNACLE GR NBF | C8: 3520 | E8: =E7+C8-D8 -> 6054.95
A9: 31.01.2026 | B9: BANK CHARGES | D9: =350+17.5 -> 367.5 | E9: =E8+C9-D9 -> 5687.45
A10: 21.02.2026 | B10: USD TO AED | D10: =368.75+17.5 -> 386.25 | E10: =E9+C10-D10 -> 5301.2
A11: 28.02.2026 | B11: BANK CHARGES | D11: 350 | E11: =E10+C11-D11 -> 4951.2
A12: 30.03.2026 | B12: USD TO AED | C12: 1082.92 | E12: =E11+C12-D12 -> 6034.12
A13: 02.04.2026 | B13: FUND RECD FROM PINNACLE GR NBF | C13: 198563 | E13: =E12+C13-D13 -> 204597.12
A14: 02.04.2026 | B14: BANK CHARGES | D14: 350 | E14: =E13+C14-D14 -> 204247.12
A15: 02.04.2026 | B15: BANK CHARGES | D15: 17.5 | E15: =E14+C15-D15 -> 204229.62
A16: 02.04.2026 | B16: TT TRF TO COMIDA NBF AED | D16: 203150 | E16: =E15+C16-D16 -> 1079.62
A17: 24.04.2026 | B17: FUND RECD FROM PINNACLE GR NBF | C17: 36000 | E17: =E16+C17-D17 -> 37079.62
A18: 24.04.2026 | B18: TT TRF TO ASHISH DHANUKA WIO AED | D18: 36000 | E18: =E17+C18-D18 -> 1079.62
E19: =E18+C19-D19 -> 1079.62
E20: =E19+C20-D20 -> 1079.62
E21: =E20+C21-D21 -> 1079.62
E22: =E21+C22-D22 -> 1079.62
E23: =E22+C23-D23 -> 1079.62
E24: =E23+C24-D24 -> 1079.62
E25: =E24+C25-D25 -> 1079.62
E26: =E25+C26-D26 -> 1079.62
E27: =E26+C27-D27 -> 1079.62
E28: =E27+C28-D28 -> 1079.62
E29: =E28+C29-D29 -> 1079.62
E30: =E29+C30-D30 -> 1079.62
... E100: =E99+C100-D100 -> 1079.62

Sheet GLUCKRICH NBF USD
A1: GLUCKRICH NBF USD
A2: DATE | B2: PARTICULAR | C2: DEPOSIT | D2: WITHDRAWAL | E2: BALANCE
A3: 21.02.2026 | B3: AED TO USD | C3: 100 | E3: 100
A4: 12.03.2026 | B4: FUND RECD FROM PINNACLE GR NBF USD | C4: 100 | E4: =E3+C4-D4 -> 200
A5: 12.03.2026 | B5: FUND RECD FROM PINNACLE GR NBF USD | C5: 200100 | E5: =E4+C5-D5 -> 200300
A6: 12.03.2026 | B6: TT TRF MINERVA SBM | D6: 200012 | E6: =E5+C6-D6 -> 288
A7: 13.03.2026 | B7: FUND RECD FROM PINNACLE GR NBF USD | C7: 99900 | E7: =E6+C7-D7 -> 100188
A8: 13.03.2026 | B8: TT TRF MINERVA SBM | D8: =100003+9.53+0.48 -> 100013.01 | E8: =E7+C8-D8 -> 174.99
A9: 14.03.2026 | B9: FUND RECD FROM SECOND STREET PARTNERS | C9: 99991 | E9: =E8+C9-D9 -> 100165.99
A10: 14.03.2026 | B10: BANK CHARGES | D10: 5.45 | E10: =E9+C10-D10 -> 100160.54
A11: 14.03.2026 | B11: BANK CHARGES | D11: 0.27 | E11: =E10+C11-D11 -> 100160.27
A12: 14.03.2026 | B12: BANK CHARGES | D12: 9.53 | E12: =E11+C12-D12 -> 100150.74
A13: 14.03.2026 | B13: BANK CHARGES | D13: 0.48 | E13: =E12+C13-D13 -> 100150.26
A14: 16.03.2026 | B14: FUND RECD FROM PINNACLE GR NBF USD | C14: 73000 | E14: =E13+C14-D14 -> 173150.26
A15: 16.03.2026 | B15: FUND RECD FROM PINNACLE GR NBF USD | C15: 27183.67 | E15: =E14+C15-D15 -> 200333.93
A16: 16.03.2026 | B16: TT TRF MINERVA SBM | D16: 200011 | E16: =E15+C16-D16 -> 322.93
A17: 16.03.2026 | B17: BANK CHARGES | D17: 10.01 | E17: =E16+C17-D17 -> 312.92
A18: 30.03.2026 | B18: BANK CHARGES | D18: 15 | E18: =E17+C18-D18 -> 297.92
A19: 30.03.2026 | B19: USD TO AED | D19: 296 | E19: =E18+C19-D19 -> 1.92
E20: =E19+C20-D20 -> 1.92
E21: =E20+C21-D21 -> 1.92
E22: =E21+C22-D22 -> 1.92
E23: =E22+C23-D23 -> 1.92
E24: =E23+C24-D24 -> 1.92
E25: =E24+C25-D25 -> 1.92
E26: =E25+C26-D26 -> 1.92
E27: =E26+C27-D27 -> 1.92
E28: =E27+C28-D28 -> 1.92
E29: =E28+C29-D29 -> 1.92
E30: =E29+C30-D30 -> 1.92
E31: =E30+C31-D31 -> 1.92
... E100: =E99+C100-D100 -> 1.92

Sheet GOLDENOVA RAK AED
A1: GOLDENOVA RAK AED
A3: DATE | B3: PARTICULAR | C3: DEPOSIT | D3: WITHDRAWAL | E3: BALANCE
A5: 02.10.2025 | B5: FUND RECD | C5: 10 | E5: =E4+C5-D5 -> 10
A6: 02.10.2025 | B6: FUND RECD FROM BLACK PEPPER GT NBF | C6: 5210 | E6: =E5+C6-D6 -> 5220
A7: 02.10.2025 | B7: BANK CHARGES | D7: 52.5 | E7: =E6+C7-D7 -> 5167.5
A8: 06.10.2025 | B8: BANK CHARGES | D8: 51.45 | E8: =E7+C8-D8 -> 5116.05
A9: 31.10.2025 | B9: BANK CHARGES | D9: 155.4 | E9: =E8+C9-D9 -> 4960.65 | F9: =+E9-4960.65 -> 0
A10: 23.12.2025 | B10: TT TRF TO RED STONE WIO | D10: 4500 | E10: =E9+C10-D10 -> 460.65
A11: 23.12.2025 | B11: BANK CHARGES | D11: 4.2 | E11: =E10+C11-D11 -> 456.45
A12: 02.01.2026 | B12: BANK CHARGES | D12: 51.45 | E12: =E11+C12-D12 -> 405
A13: 02.01.2026 | B13: BANK CHARGES | D13: 103.95 | E13: =E12+C13-D13 -> 301.05
A14: 01.04.2026 | B14: BANK CHARGES | D14: 301.05 | E14: =E13+C14-D14 -> 5.6843419e-13
E15: =E14+C15-D15 -> 5.6843419e-13
E16: =E15+C16-D16 -> 5.6843419e-13
E17: =E16+C17-D17 -> 5.6843419e-13
E18: =E17+C18-D18 -> 5.6843419e-13
E19: =E18+C19-D19 -> 5.6843419e-13
E20: =E19+C20-D20 -> 5.6843419e-13
E21: =E20+C21-D21 -> 5.6843419e-13
E22: =E21+C22-D22 -> 5.6843419e-13
E23: =E22+C23-D23 -> 5.6843419e-13
E24: =E23+C24-D24 -> 5.6843419e-13
E25: =E24+C25-D25 -> 5.6843419e-13
E26: =E25+C26-D26 -> 5.6843419e-13
... E118: =E117+C118-D118 -> 5.6843419e-13

Sheet IDEA GROVE EIB AED
A1: IDEA GROVE EIB AED
A3: DATE | B3: PARTICULAR | C3: DEPOSIT | D3: WITHDRAWAL | E3: BALANCE
B4: PARTICULAR
A5: 09.08.2025 | B5: FUND RECD FROM IDEA GROVE | C5: 1500 | E5: =E4+C5-D5 -> 1500
A6: 10.08.2025 | B6: BANK CHARGES | D6: =225+11.25+225+11.25+52.5 -> 525 | E6: =E5+C6-D6 -> 975
A7: 29-08-2025 | B7: FUND RECD FROM PINNACLE INT AED | C7: 9852 | E7: =E6+C7-D7 -> 10827
A8: 02.09.2025 | B8: BANK CHARGES | D8: =225+11.25 -> 236.25 | E8: =E7+C8-D8 -> 10590.75
A9: 02.09.2025 | B9: BANK CHARGES | D9: 52.5 | E9: =E8+C9-D9 -> 10538.25
A10: 02.09.2025 | B10: FUND RECD FROM PINNACLE INT AED | C10: 56379 | E10: =E9+C10-D10 -> 66917.25
A11: 02.09.2025 | B11: TT TRF TO ROYAL ENBD | D11: 64967 | E11: =E10+C11-D11 -> 1950.25
A12: 16.09.2025 | B12: CASH DEPOSIT | C12: 250000 | E12: =E11+C12-D12 -> 251950.25
A13: 16.09.2025 | B13: FUND RECD FROM Y A X A TRADING LLC | C13: 498206 | E13: =E12+C13-D13 -> 750156.25
A14: 16.09.2025 | B14: TT TRF TO ROYAL ENBD | D14: 498504 | E14: =E13+C14-D14 -> 251652.25
A15: 16.09.2025 | B15: TT TRF TO ROYAL ENBD | D15: 248931 | E15: =E14+C15-D15 -> 2721.25
A16: 17.09.2025 | B16: CHEQUE DEPOSIT Y A X A TRADING LLC | C16: 1800000 | E16: =E15+C16-D16 -> 1802721.2
A17: 17.09.2025 | B17: TT TRF TO ROYAL ENBD | D17: 498995 | E17: =E16+C17-D17 -> 1303726.2
A18: 17.09.2025 | B18: TT TRF TO ROYAL ENBD | D18: 499572 | E18: =E17+C18-D18 -> 804154.25
A19: 17.09.2025 | B19: TT TRF TO AGNIRA WIO AED | D19: 499680 | E19: =E18+C19-D19 -> 304474.25
A20: 17.09.2025 | B20: TT TRF TO ROYAL ENBD | D20: 301251 | E20: =E19+C20-D20 -> 3223.25
A21: 18.09.2025 | B21: FUND RECD FROM SHRIJI INT EIB | C21: 499950 | E21: =E20+C21-D21 -> 503173.25
A22: 18.09.2025 | B22: TT TRF TO ROYAL ENBD | D22: 498571 | E22: =E21+C22-D22 -> 4602.25
A23: 18.09.2025 | B23: BANK CHARGES | D23: 2.1 | E23: =E22+C23-D23 -> 4600.15
A24: 18.09.2025 | B24: FUND RECD FROM AGINCO MSQ | C24: 103524 | E24: =E23+C24-D24 -> 108124.15
A25: 18.09.2025 | B25: TT TRF TO ROYAL ENBD | D25: 106324 | E25: =E24+C25-D25 -> 1800.15
A26: 22.09.2025 | B26: FUND RECD FROM SILVER CROSS EQUIPMENT | C26: 586900 | E26: =E25+C26-D26 -> 588700.15
A27: 22.09.2025 | B27: TT TRF FROM IDEA GROVE EIB TO ROYAL ENBD | D27: 586954 | E27: =E26+C27-D27 -> 1746.15
A28: 23.09.2025 | B28: FUND RECD FROM SILVER STONE WIO | C28: 538204 | E28: =E27+C28-D28 -> 539950.15
A29: 23.09.2025 | B29: FUND RECD FROM SILVER STONE WIO | C29: 298642 | E29: =E28+C29-D29 -> 838592.15
A30: 23.09.2025 | B30: TT TRF TO AGNIRA WIO AED | D30: 499582 | E30: =E29+C30-D30 -> 339010.15
A31: 23.09.2025 | B31: TT TRF TO ROYAL ENBD | D31: 336527 | E31: =E30+C31-D31 -> 2483.15
A32: 24.09.2025 | B32: FUND RECD FROM SILVER CROSS EQUIPMENT | C32: 885692 | E32: =E31+C32-D32 -> 888175.15
A33: 24.09.2025 | B33: TT TRF TO ROYAL ENBD AED | D33: 558410 | E33: =E32+C33-D33 -> 329765.15
A34: 24.09.2025 | B34: TT TRF TO ROYAL ENBD AED | D34: 326450 | E34: =E33+C34-D34 -> 3315.15
A35: 25.09.2025 | B35: CASH DEPOSIT | C35: 235000 | E35: =E34+C35-D35 -> 238315.15
A36: 25.09.2025 | B36: TT TRF TO ROYAL ENBD AED | D36: 110362 | E36: =E35+C36-D36 -> 127953.15
A37: 25.09.2025 | B37: TT TRF TO AGNIRA EIB AED | D37: 125254 | E37: =E36+C37-D37 -> 2699.15
A38: 29.09.2025 | B38: CASH DEPOSIT | C38: 149000 | E38: =E37+C38-D38 -> 151699.15
A39: 29.09.2025 | B39: CASH DEPOSIT | C39: 69000 | E39: =E38+C39-D39 -> 220699.15
A40: 29.09.2025 | B40: FUND RECD FROM RED STONE WIO AED | C40: 201309 | E40: =E39+C40-D40 -> 422008.15
A41: 29.09.2025 | B41: CASH DEPOSIT | C41: 101000 | E41: =E40+C41-D41 -> 523008.15
A42: 29.09.2025 | B42: CASH DEPOSIT | C42: 33500 | E42: =E41+C42-D42 -> 556508.15
A43: 29.09.2025 | B43: TT TRF TO ROYAL ENBD AED | D43: 454201 | E43: =E42+C43-D43 -> 102307.15
A44: 29.09.2025 | B44: TT TRF TO ROYAL ENBD AED | D44: 101329 | E44: =E43+C44-D44 -> 978.15
A45: 30.09.2025 | B45: CASH DEPOSIT | C45: 139000 | E45: =E44+C45-D45 -> 139978.15
A46: 30.09.2025 | B46: CASH DEPOSIT | C46: 61000 | E46: =E45+C46-D46 -> 200978.15
A47: 30.09.2025 | B47: TT TRF TO ROYAL EN EM ENBD | D47: 198340 | E47: =E46+C47-D47 -> 2638.15
A48: 30.09.2025 | B48: BANK CHARGES | D48: 2.1 | E48: =E47+C48-D48 -> 2636.05
A49: 01.10.2025 | B49: FUND RECD FROM RED STONE WIO AED | C49: 254860 | E49: =E48+C49-D49 -> 257496.05
A50: 01.10.2025 | B50: TT TRF TO ROYAL EN EM ENBD | D50: 256349 | E50: =E49+C50-D50 -> 1147.05
A51: 01.10.2025 | B51: FUND RECD FROM SHRIJI INT EIB | C51: 497682 | E51: =E50+C51-D51 -> 498829.05
A52: 01.10.2025 | B52: TT TRF TO ROYAL EN EM ENBD | D52: 496872 | E52: =E51+C52-D52 -> 1957.05
A53: 02.10.2025 | B53: FUND RECD FROM SHRIJI INT EIB | C53: 255691 | E53: =E52+C53-D53 -> 257648.05
A54: 02.10.2025 | B54: TT TRF TO AGNIRA EIB AED | D54: 251673 | E54: =E53+C54-D54 -> 5975.05
A55: 03.10.2025 | B55: FUND RECD FROM ENFLOW UBL AED | C55: 95647 | E55: =E54+C55-D55 -> 101622.05
A56: 03.10.2025 | B56: FUND RECD FROM SILVER STONE WIO | C56: 450310 | E56: =E55+C56-D56 -> 551932.05
A57: 03.10.2025 | B57: TT TRF TO AGNIRA EIB AED | D57: 549634 | E57: =E56+C57-D57 -> 2298.05
A58: 03.10.2025 | B58: FUND RECD FROM RED STONE WIO AED | C58: 430152 | E58: =E57+C58-D58 -> 432450.05
A59: 03.10.2025 | B59: TT TRF TO ROYAL EN EM ENBD | D59: 430210 | E59: =E58+C59-D59 -> 2240.05
A60: 04.10.2025 | B60: FUND RECD FROM RED STONE WIO AED | C60: 243967 | E60: =E59+C60-D60 -> 246207.05
A61: 04.10.2025 | B61: TT TRF TO AGNIRA EIB AED | D61: 243684 | E61: =E60+C61-D61 -> 2523.05
A62: 01.10.2025 | B62: BANK CHARGES | D62: 50 | E62: =E61+C62-D62 -> 2473.05
A63: 01.10.2025 | B63: BANK CHARGES | D63: 2.5 | E63: =E62+C63-D63 -> 2470.55
A64: 01.10.2025 | B64: BANK CHARGES | D64: 225 | E64: =E63+C64-D64 -> 2245.55
A65: 01.10.2025 | B65: BANK CHARGES | D65: 11.25 | E65: =E64+C65-D65 -> 2234.3
A66: 07.10.2025 | B66: FUND RECD FROM RED STONE WIO AED | C66: 512013 | E66: =E65+C66-D66 -> 514247.3
A67: 07.10.2025 | B67: TT TRF TO AGNIRA WIO AED | D67: 513021 | E67: =E66+C67-D67 -> 1226.3
A68: 07.10.2025 | B68: BANK CHARGES | D68: 2.1 | E68: =E67+C68-D68 -> 1224.2
A69: 07.10.2025 | B69: FUND RECD FROM SHRIJI INT EIB | C69: 509461 | E69: =E68+C69-D69 -> 510685.2
A70: 07.10.2025 | B70: TT TRF TO ROYAL EN EM ENBD | D70: 508649 | E70: =E69+C70-D70 -> 2036.2
A71: 09.10.2025 | B71: FUND RECD FROM RED STONE WIO AED | C71: 628314 | E71: =E70+C71-D71 -> 630350.2
A72: 09.10.2025 | B72: TT TRF TO AGNIRA EIB AED | D72: 453120 | E72: =E71+C72-D72 -> 177230.2
A73: 09.10.2025 | B73: TT TRF TO ROYAL EN EM ENBD | D73: 175201 | E73: =E72+C73-D73 -> 2029.2
A74: 09.10.2025 | B74: FUND RECD FROM SHRIJI INT EIB | C74: 269845 | E74: =E73+C74-D74 -> 271874.2
A75: 09.10.2025 | B75: TT TRF TO ROYAL EN EM ENBD | D75: 269876 | E75: =E74+C75-D75 -> 1998.2
A76: 10.10.2025 | B76: FUND RECD FROM SHRIJI INT EIB | C76: 440318 | E76: =E75+C76-D76 -> 442316.2
A77: 10.10.2025 | B77: TT TRF TO ROYAL EN EM ENBD | D77: 440231 | E77: =E76+C77-D77 -> 2085.2
A78: 11.10.2025 | B78: FUND RECD FROM SHRIJI INT EIB | C78: 512346 | E78: =E77+C78-D78 -> 514431.2
A79: 11.10.2025 | B79: TT TRF TO AGNIRA EIB AED | D79: 513620 | E79: =E78+C79-D79 -> 811.2
A80: 14.10.2025 | B80: CASH DEPOSIT | C80: 184000 | E80: =E79+C80-D80 -> 184811.2
A81: 14.10.2025 | B81: CASH DEPOSIT | C81: 4000 | E81: =E80+C81-D81 -> 188811.2
A82: 14.10.2025 | B82: TT TRF TO ROYAL EN EM ENBD | D82: 187203 | E82: =E81+C82-D82 -> 1608.2
A83: 15.10.2025 | B83: FUND RECD FROM RED STONE WIO AED | C83: 552309 | E83: =E82+C83-D83 -> 553917.2
A84: 15.10.2025 | B84: TT TRF TO ROYAL EN EM ENBD | D84: 551689 | E84: =E83+C84-D84 -> 2228.2
A85: 16.10.2025 | B85: FUND RECD FROM SILVER STONE WIO | C85: 550348 | E85: =E84+C85-D85 -> 552576.2
A86: 16.10.2025 | B86: FUND RECD FROM SILVER STONE WIO | C86: 578063 | E86: =E85+C86-D86 -> 1130639.2
A87: 16.10.2025 | B87: FUND RECD FROM SILVER STONE WIO | C87: 369567 | E87: =E86+C87-D87 -> 1500206.2
A88: 16.10.2025 | B88: TT TRF TO ROYAL EN EM ENBD | D88: 551320 | E88: =E87+C88-D88 -> 948886.2
A89: 16.10.2025 | B89: TT TRF TO ROYAL EN EM ENBD | D89: 600328 | E89: =E88+C89-D89 -> 348558.2
A90: 16.10.2025 | B90: TT TRF TO ROYAL EN EM ENBD | D90: 345690 | E90: =E89+C90-D90 -> 2868.2
A91: 16.10.2025 | B91: FUND RECD FROM SHRIJI INT EIB | C91: 325968 | E91: =E90+C91-D91 -> 328836.2
A92: 16.10.2025 | B92: TT TRF TO ROYAL EN EM ENBD | D92: 327948 | E92: =E91+C92-D92 -> 888.2
A93: 17.10.2025 | B93: CASH DEPOSIT | C93: 180000 | E93: =E92+C93-D93 -> 180888.2
A94: 17.10.2025 | B94: TT TRF TO ROYAL EN EM ENBD | D94: 178964 | E94: =E93+C94-D94 -> 1924.2
A95: 17.10.2025 | B95: FUND RECD FROM RED STONE WIO AED | C95: 265684 | E95: =E94+C95-D95 -> 267608.2
A96: 17.10.2025 | B96: TT TRF TO ROYAL EN EM ENBD | D96: 265314 | E96: =E95+C96-D96 -> 2294.2
A97: 17.10.2025 | B97: FUND RECD FROM RAS AL MARWA TRADING LLC | C97: 845600 | E97: =E96+C97-D97 -> 847894.2
A98: 17.10.2025 | B98: TT TRF TO ROYAL EN EM ENBD | D98: 845671 | E98: =E97+C98-D98 -> 2223.2
A99: 21.10.2025 | B99: FUND RECD FROM ALTARIQ ALMETHALI | C99: 839120 | E99: =E98+C99-D99 -> 841343.2
A100: 21.10.2025 | B100: TT TRF TO ROYAL EN EM ENBD | D100: 840237 | E100: =E99+C100-D100 -> 1106.2
A101: 22.10.2025 | B101: FUND RECD FROM ALTARIQ ALMETHALI | C101: 932570 | E101: =E100+C101-D101 -> 933676.2
...

Sheet IDEA GROVE RAK AED
A1: IDEA GROVE RAK AED
A3: DATE | B3: PARTICULAR | C3: DEPOSIT | D3: WITHDRAWAL | E3: BALANCE
A5: 03.12.2025 | B5: FUND RECD FROM IDEA GROVE EIB AED | C5: 5000 | E5: =E4+C5-D5 -> 5000
A6: 04.12.2025 | B6: BANK CHARGES | D6: 103.95 | E6: =E5+C6-D6 -> 4896.05
A7: 04.12.2025 | B7: BANK CHARGES | D7: 52.5 | E7: =E6+C7-D7 -> 4843.55
A8: 04.12.2025 | B8: BANK CHARGES | D8: 103.95 | E8: =E7+C8-D8 -> 4739.6
A9: 04.12.2025 | B9: BANK CHARGES | D9: 52.5 | E9: =E8+C9-D9 -> 4687.1
A10: 04.12.2025 | B10: BANK CHARGES | D10: 103.95 | E10: =E9+C10-D10 -> 4583.15
A11: 04.12.2025 | B11: BANK CHARGES | D11: 52.5 | E11: =E10+C11-D11 -> 4530.65
A12: 04.12.2025 | B12: BANK CHARGES | D12: 52.5 | E12: =E11+C12-D12 -> 4478.15
A13: 04.12.2025 | B13: BANK CHARGES | D13: 156.45 | E13: =E12+C13-D13 -> 4321.7
A14: 22.12.2025 | B14: TT TRF TO ROYAL EN EM NBF AED | D14: 3960 | E14: =E13+C14-D14 -> 361.7
A15: 22.12.2025 | B15: BANK CHARGES | D15: 1.05 | E15: =E14+C15-D15 -> 360.65
A16: 02.01.2026 | B16: BANK CHARGES | D16: 103.95 | E16: =E15+C16-D16 -> 256.7
A17: 26.01.2026 | B17: BANK CHARGES | D17: 156.2 | E17: =E16+C17-D17 -> 100.5
A18: 27.01.2026 | B18: FUND RECD FROM IDEA GROVE EIB AED | C18: 18000 | E18: =E17+C18-D18 -> 18100.5
A19: 02.02.2026 | B19: BANK CHARGES | D19: 103.95 | E19: =E18+C19-D19 -> 17996.55
A20: 24.02.2026 | B20: CHQ PAID TO DUBAI INVESTMENT | D20: 17565 | E20: =E19+C20-D20 -> 431.55
A21: 31.03.2026 | B21: FUND RECD FROM BLACK PEPPER GT NBF AED | C21: 16800 | E21: =E20+C21-D21 -> 17231.55
A22: 31.03.2026 | B22: BANK CHARGES | D22: 156.45 | E22: =E21+C22-D22 -> 17075.1
A23: 31.03.2026 | B23: BANK CHARGES | D23: 103.95 | E23: =E22+C23-D23 -> 16971.15
A24: 31.03.2026 | B24: BANK CHARGES | D24: 156.45 | E24: =E23+C24-D24 -> 16814.7
A25: 01.04.2026 | B25: CHQ PAID TO DUBAI INVESTMENT | D25: 16250 | E25: =E24+C25-D25 -> 564.7
A26: 01.04.2026 | B26: BANK CHARGES | D26: 103.95 | E26: =E25+C26-D26 -> 460.75
A27: 01.05.2026 | B27: BANK CHARGES | D27: 103.95 | E27: =E26+C27-D27 -> 356.8
A28: 01.05.2026 | B28: BANK CHARGES | D28: 156.45 | E28: =E27+C28-D28 -> 200.35
A29: 05.05.2026 | B29: FUND RECD FROM INFINITY FORTUNE NBF AED | C29: 9050 | E29: =E28+C29-D29 -> 9250.35
E30: =E29+C30-D30 -> 9250.35
E31: =E30+C31-D31 -> 9250.35
E32: =E31+C32-D32 -> 9250.35
E33: =E32+C33-D33 -> 9250.35
E34: =E33+C34-D34 -> 9250.35
E35: =E34+C35-D35 -> 9250.35
E36: =E35+C36-D36 -> 9250.35
E37: =E36+C37-D37 -> 9250.35
E38: =E37+C38-D38 -> 9250.35
E39: =E38+C39-D39 -> 9250.35
E40: =E39+C40-D40 -> 9250.35
E41: =E40+C41-D41 -> 9250.35
... E145: =E144+C145-D145 -> 9250.35
E146: =E145+C146-D146 -> 9250.35 | F146: =+E146-1510.15 -> 7740.2
E147: =E146+C147-D147 -> 9250.35
E148: =E147+C148-D148 -> 9250.35
E149: =E148+C149-D149 -> 9250.35
E150: =E149+C150-D150 -> 9250.35
E151: =E150+C151-D151 -> 9250.35
E152: =E151+C152-D152 -> 9250.35
E153: =E152+C153-D153 -> 9250.35
E154: =E153+C154-D154 -> 9250.35
E155: =E154+C155-D155 -> 9250.35
E156: =E155+C156-D156 -> 9250.35
E157: =E156+C157-D157 -> 9250.35
E158: =E157+C158-D158 -> 9250.35
... E181: =E180+C181-D181 -> 9250.35
E182: =E181+C182-D182 -> 9250.35 | F182: =+E183-728206.75 -> -718956.4
E183: =E182+C183-D183 -> 9250.35
E184: =E183+C184-D184 -> 9250.35
E185: =E184+C185-D185 -> 9250.35
E186: =E185+C186-D186 -> 9250.35
E187: =E186+C187-D187 -> 9250.35
E188: =E187+C188-D188 -> 9250.35
E189: =E188+C189-D189 -> 9250.35
E190: =E189+C190-D190 -> 9250.35
E191: =E190+C191-D191 -> 9250.35
E192: =E191+C192-D192 -> 9250.35
E193: =E192+C193-D193 -> 9250.35
E194: =E193+C194-D194 -> 9250.35
... E215: =E214+C215-D215 -> 9250.35

Sheet IDEA GROVE SIB AED
A1: IDEA GROVE SIB AED
A3: DATE | B3: PARTICULAR | C3: DEPOSIT | D3: WITHDRAWAL | E3: BALANCE
A5: 06.03.2026 | B5: FUND RECD | C5: 5000 | E5: =E4+C5-D5 -> 5000
A6: 06.04.2026 | B6: BANK CHARGES | D6: 210 | E6: =E5+C6-D6 -> 4790
A7: 08.04.2026 | B7: FTA | D7: 70.67 | E7: =E6+C7-D7 -> 4719.33
A8: 08.04.2026 | B8: FUND RECD FROM INVESTRADE PTE LTD | C8: 548425 | E8: =E7+C8-D8 -> 553144.33
A9: 08.04.2026 | B9: BANK CHARGES | D9: 1.05 | E9: =E8+C9-D9 -> 553143.28
A10: 08.04.2026 | B10: TT TRF TO ASHIEAT AISHAMS GT NBF AED | D10: 365000 | E10: =E9+C10-D10 -> 188143.28
A11: 08.04.2026 | B11: BANK CHARGES | D11: 1.05 | E11: =E10+C11-D11 -> 188142.23
A12: 08.04.2026 | B12: TT TRF TO AMINEX SIB AED | D12: 187056 | E12: =E11+C12-D12 -> 1086.23
A13: 09.04.2026 | B13: FUND RECD FROM INVESTRADE PTE LTD | C13: 182595 | E13: =E12+C13-D13 -> 183681.23
A14: 09.04.2026 | B14: FUND RECD FROM ORBIT PLUS SIB | C14: 328500 | E14: =E13+C14-D14 -> 512181.23
A15: 09.04.2026 | B15: TT TRF TO SWIFT BRIDGE SIB AED | D15: 511046 | E15: =E14+C15-D15 -> 1135.23
A16: 09.04.2026 | B16: TT TRF TO SWIFT BRIDGE SIB AED | D16: 1000 | E16: =E15+C16-D16 -> 135.23
A17: 10.04.2026 | B17: CASH DEPOSIT | C17: 200000 | E17: =E16+C17-D17 -> 200135.23
A18: 10.04.2026 | B18: TT TRF TO SWIFT BRIDGE SIB AED | D18: 199546 | E18: =E17+C18-D18 -> 589.23
A19: 23.04.2026 | B19: FUND RECD FROM INVESTRADE PTE LTD | C19: 315285 | E19: =E18+C19-D19 -> 315874.23
A20: 23.04.2026 | B20: FUND RECD FROM AMINEX SIB | C20: 584203 | E20: =E19+C20-D20 -> 900077.23
A21: 23.04.2026 | B21: TT TRF TO SWIFT BRIDGE SIB AED | D21: 735790 | E21: =E20+C21-D21 -> 164287.23
A22: 23.04.2026 | B22: TT TRF TO ROYAL EN EM SIB AED | D22: 163520 | E22: =E21+C22-D22 -> 767.23
A23: 30.04.2026 | B23: CASH DEPOSIT | C23: 200000 | E23: =E22+C23-D23 -> 200767.23
A24: 30.04.2026 | B24: BANK CHARGES | D24: 5.25 | E24: =E23+C24-D24 -> 200761.98
A25: 30.04.2026 | B25: TT TRF TO ROYAL EN EM SIB AED | D25: 200154 | E25: =E24+C25-D25 -> 607.98
A26: 01.05.2026 | B26: BANK CHARGES | D26: 420 | E26: =E25+C26-D26 -> 187.98
E27: =E26+C27-D27 -> 187.98
E28: =E27+C28-D28 -> 187.98
E29: =E28+C29-D29 -> 187.98
E30: =E29+C30-D30 -> 187.98
E31: =E30+C31-D31 -> 187.98
E32: =E31+C32-D32 -> 187.98
E33: =E32+C33-D33 -> 187.98
E34: =E33+C34-D34 -> 187.98
E35: =E34+C35-D35 -> 187.98
E36: =E35+C36-D36 -> 187.98
E37: =E36+C37-D37 -> 187.98
E38: =E37+C38-D38 -> 187.98
... E100: =E99+C100-D100 -> 187.98

Sheet FUTURE BRIDGE MSQ AED
A1: FUTURE BRIDGE MSQ AED
A2: MSQ BANK AED
A3: DATE | B3: PARTICULAR | C3: DEPOSIT | D3: WITHDRAWAL | E3: BALANCE
A5: 07.08.2025 | B5: FUND RECD FROM ROYAL EN EM | C5: 203518 | E5: =E4+C5-D5 -> 203518
A6: 07.08.2025 | B6: BANK CHARGES | D6: 210 | E6: =E5+C6-D6 -> 203308
A7: 11.08.2025 | B7: TT TRF TO BLACK PEPPER NBF | D7: 202108 | E7: =E6+C7-D7 -> 1200
A8: 11.08.2025 | B8: BANK CHARGES | D8: 1.05 | E8: =E7+C8-D8 -> 1198.95
A9: 18.08.2025 | B9: FUND RECD FROM ROYAL EN EM AED | C9: 203052 | E9: =E8+C9-D9 -> 204250.95
A10: 20.08.2025 | B10: TT TRF TO BEIJING AOKUN | D10: 202190 | E10: =E9+C10-D10 -> 2060.95
A11: 30.08.2025 | B11: BANK CHARGES | D11: 210 | E11: =E10+C11-D11 -> 1850.95
A12: 30.09.2025 | B12: BANK CHARGES | D12: 210 | E12: =E11+C12-D12 -> 1640.95
E13: =E12+C13-D13 -> 1640.95
E14: =E13+C14-D14 -> 1640.95
E15: =E14+C15-D15 -> 1640.95
E16: =E15+C16-D16 -> 1640.95
E17: =E16+C17-D17 -> 1640.95
E18: =E17+C18-D18 -> 1640.95
E19: =E18+C19-D19 -> 1640.95
E20: =E19+C20-D20 -> 1640.95
E21: =E20+C21-D21 -> 1640.95
E22: =E21+C22-D22 -> 1640.95
E23: =E22+C23-D23 -> 1640.95
E24: =E23+C24-D24 -> 1640.95
... E115: =E114+C115-D115 -> 1640.95

Sheet SHRIJI INT EIB AED
A1: SHRIJI INTERNATIONAL
A2: EIB BANK AED ACC .NO -
A3: DATE | B3: PARTICULAR | C3: DEPOSIT | D3: WITHDRAWAL | E3: BALANCE
A5: 11.09.2025 | B5: FUND RECD FROM CAPS LOCK FAB AED | C5: 81245 | E5: =E4+C5-D5 -> 81245
A6: 11.09.2025 | B6: TT TRF TO RED STONE WIO AED | D6: 79854 | E6: =E5+C6-D6 -> 1391
A7: 11.09.2025 | B7: BANK CHARGES | D7: 1.05 | E7: =E6+C7-D7 -> 1389.95
A8: 11.09.2025 | B8: BANK CHARGES | D8: 451.5 | E8: =E7+C8-D8 -> 938.45
A9: 12.09.2025 | B9: BANK CHARGES | D9: 451.5 | E9: =E8+C9-D9 -> 486.95
A10: 12.09.2025 | B10: FUND RECD FROM CAPS LOCK FAB AED | C10: 99683 | E10: =E9+C10-D10 -> 100169.95
A11: 12.09.2025 | B11: TT TRF TO SILVER STONE WIO | D11: 99804 | E11: =E10+C11-D11 -> 365.95
A12: 15.09.2025 | B12: FUND RECD FROM CAPS LOCK FAB AED | C12: 197524 | E12: =E11+C12-D12 -> 197889.95
A13: 15.09.2025 | B13: TT TRF TO RED STONE WIO AED | D13: 194587 | E13: =E12+C13-D13 -> 3302.95
A14: 15.09.2025 | B14: BANK CHARGES | D14: 11.2 | E14: =E13+C14-D14 -> 3291.75
A15: 16.09.2025 | B15: FUND RECD FROM ROYAL EN EM ENBD AED | C15: 412571 | E15: =E14+C15-D15 -> 415862.75
A16: 16.09.2025 | B16: TT TRF TO RED STONE WIO AED | D16: 412350 | E16: =E15+C16-D16 -> 3512.75
A17: 16.09.2025 | B17: BANK CHARGES | D17: 11.2 | E17: =E16+C17-D17 -> 3501.55
A18: 17.09.2025 | B18: FUND RECD FROM SWIFT BRIDGE SIB AED | C18: 498521 | E18: =E17+C18-D18 -> 502022.55
A19: 17.09.2025 | B19: BANK CHARGES | D19: 12.25 | E19: =E18+C19-D19 -> 502010.3
A20: 18.09.2025 | B20: TT TRF TO IDEA GROVE EIB AED | D20: 499950 | E20: =E19+C20-D20 -> 2060.3
A21: 19.09.2025 | B21: FUND RECD FROM ROYAL EN EM ENBD AED | C21: 301682 | E21: =E20+C21-D21 -> 303742.3
A22: 19.09.2025 | B22: TT TRF FROM SHRIJI INT EIB TO RED STONE WIO AED | D22: 300309 | E22: =E21+C22-D22 -> 3433.3
A23: 23.09.2025 | B23: FUND RECD FROM ROYAL EN EM ENBD AED | C23: 485671 | E23: =E22+C23-D23 -> 489104.3
A24: 23.09.2025 | B24: TT TRF TO RED STONE WIO AED | D24: 486245 | E24: =E23+C24-D24 -> 2859.3
A25: 23.09.2025 | B25: BANK CHARGES | D25: 11.55 | E25: =E24+C25-D25 -> 2847.75
A26: 24.09.2025 | B26: FUND RECD FROM CAPS LOCK FAB AED | C26: 580124 | E26: =E25+C26-D26 -> 582971.75
A27: 24.09.2025 | B27: TT TRF TO SILVER STONE WIO | D27: 581476 | E27: =E26+C27-D27 -> 1495.75
A28: 24.09.2025 | B28: BANK CHARGES | D28: 11.55 | E28: =E27+C28-D28 -> 1484.2
A29: 01.10.2025 | B29: FUND RECD FROM SWIFT BRIDGE SIB AED | C29: 499683 | E29: =E28+C29-D29 -> 501167.2
A30: 01.10.2025 | B30: TT TRF TO IDEA GROVE EIB AED | D30: 497682 | E30: =E29+C30-D30 -> 3485.2
A31: 02.10.2025 | B31: FUND RECD FROM SWIFT BRIDGE SIB AED | C31: 255760 | E31: =E30+C31-D31 -> 259245.2
A32: 02.10.2025 | B32: TT TRF TO IDEA GROVE EIB AED | D32: 255691 | E32: =E31+C32-D32 -> 3554.2
A33: 02.10.2025 | B33: BANK CHARGES | D33: 425 | E33: =E32+C33-D33 -> 3129.2
A34: 02.10.2025 | B34: BANK CHARGES | D34: 21.25 | E34: =E33+C34-D34 -> 3107.95
A35: 02.10.2025 | B35: BANK CHARGES | D35: 11.55 | E35: =E34+C35-D35 -> 3096.4
A36: 07.10.2025 | B36: FUND RECD FROM CAPS LOCK FAB AED | C36: 511031 | E36: =E35+C36-D36 -> 514127.4
A37: 07.10.2025 | B37: TT TRF TO IDEA GROVE EIB AED | D37: 509461 | E37: =E36+C37-D37 -> 4666.4
A38: 09.10.2025 | B38: FUND RECD FROM CAPS LOCK FAB AED | C38: 419687 | E38: =E37+C38-D38 -> 424353.4
A39: 09.10.2025 | B39: FUND RECD FROM ROYAL EN EM ENBD AED | C39: 150341 | E39: =E38+C39-D39 -> 574694.4
A40: 09.10.2025 | B40: TT TRF TO RED STONE WIO AED | D40: 300541 | E40: =E39+C40-D40 -> 274153.4
A41: 09.10.2025 | B41: BANK CHARGES | D41: 11.55 | E41: =E40+C41-D41 -> 274141.85
A42: 09.10.2025 | B42: TT TRF TO IDEA GROVE EIB AED | D42: 269845 | E42: =E41+C42-D42 -> 4296.85
A43: 10.10.2025 | B43: FUND RECD FROM CAPS LOCK FAB AED | C43: 443120 | E43: =E42+C43-D43 -> 447416.85
A44: 10.10.2025 | B44: TT TRF TO IDEA GROVE EIB AED | D44: 440318 | E44: =E43+C44-D44 -> 7098.85
A45: 11.10.2025 | B45: FUND RECD FROM ROYAL EN EM ENBD AED | C45: 510342 | E45: =E44+C45-D45 -> 517440.85
A46: 11.10.2025 | B46: TT TRF TO IDEA GROVE EIB AED | D46: 512346 | E46: =E45+C46-D46 -> 5094.85
A47: 16.10.2025 | B47: FUND RECD FROM ROYAL EN EM ENBD AED | C47: 326802 | E47: =E46+C47-D47 -> 331896.85
A48: 16.10.2025 | B48: TT TRF TO IDEA GROVE EIB AED | D48: 325968 | E48: =E47+C48-D48 -> 5928.85
A49: 18.10.2025 | B49: FUND RECD FROM CAPS LOCK FAB AED | C49: 516983 | E49: =E48+C49-D49 -> 522911.85
A50: 18.10.2025 | B50: TT TRF TO RED STONE WIO AED | D50: 518968 | E50: =E49+C50-D50 -> 3943.85
A51: 18.10.2025 | B51: BANK CHARGES | D51: 11.55 | E51: =E50+C51-D51 -> 3932.3
A52: 24.10.2025 | B52: FUND RECD FROM ROYAL EN EM ENBD AED | C52: 401529 | E52: =E51+C52-D52 -> 405461.3
A53: 24.10.2025 | B53: TT TRF TO IDEA GROVE EIB AED | D53: 402326 | E53: =E52+C53-D53 -> 3135.3
A54: 24.10.2025 | B54: FUND RECD FROM SWIFT BRIDGE SIB AED | C54: 68960 | E54: =E53+C54-D54 -> 72095.3
A55: 24.10.2025 | B55: TT TRF TO RED STONE WIO AED | D55: 23345 | E55: =E54+C55-D55 -> 48750.3
A56: 24.10.2025 | B56: BANK CHARGES | D56: 11.55 | E56: =E55+C56-D56 -> 48738.75
A57: 24.10.2025 | B57: TT TRF TO IDEA GROVE EIB AED | D57: 45960 | E57: =E56+C57-D57 -> 2778.75
A58: 28.10.2025 | B58: FUND RECD FROM SWIFT BRIDGE SIB AED | C58: 225643 | E58: =E57+C58-D58 -> 228421.75
A59: 28.10.2025 | B59: TT TRF TO SILVER STONE WIO | D59: 226100 | E59: =E58+C59-D59 -> 2321.75
A60: 28.10.2025 | B60: BANK CHARGES | D60: 11.55 | E60: =E59+C60-D60 -> 2310.2
A61: 30.10.2025 | B61: FUND RECD FROM CAPS LOCK FAB AED | C61: 299890 | E61: =E60+C61-D61 -> 302200.2
A62: 30.10.2025 | B62: TT TRF TO IDEA GROVE EIB AED | D62: 300045 | E62: =E61+C62-D62 -> 2155.2
A63: 31.10.2025 | B63: FUND RECD FROM SWIFT BRIDGE SIB AED | C63: 224968 | E63: =E62+C63-D63 -> 227123.2
A64: 31.10.2025 | B64: TT TRF TO IDEA GROVE EIB AED | D64: 223964 | E64: =E63+C64-D64 -> 3159.2
A65: 06.11.2025 | B65: FUND RECD FROM AMINEX SIB | C65: 580649 | E65: =E64+C65-D65 -> 583808.2
A66: 06.11.2025 | B66: TT TRF TO RED STONE WIO AED | D66: 579804 | E66: =E65+C66-D66 -> 4004.2
A67: 06.11.2025 | B67: BANK CHARGES | D67: 11.55 | E67: =E66+C67-D67 -> 3992.65
A68: 06.11.2025 | B68: BANK CHARGES | D68: 425 | E68: =E67+C68-D68 -> 3567.65
A69: 06.11.2025 | B69: BANK CHARGES | D69: 21.25 | E69: =E68+C69-D69 -> 3546.4
A70: 08.11.2025 | B70: FUND RECD FROM AMINEX SIB | C70: 283643 | E70: =E69+C70-D70 -> 287189.4
A71: 08.11.2025 | B71: FUND RECD FROM ROYAL EN EM ENBD AED | C71: 390586 | E71: =E70+C71-D71 -> 677775.4
A72: 08.11.2025 | B72: TT TRF TO IDEA GROVE EIB AED | D72: 672469 | E72: =E71+C72-D72 -> 5306.4
A73: 11.11.2025 | B73: FUND RECD FROM CAPS LOCK FAB AED | C73: 425641 | E73: =E72+C73-D73 -> 430947.4
A74: 11.11.2025 | B74: TT TRF TO IDEA GROVE EIB AED | D74: 426351 | E74: =E73+C74-D74 -> 4596.4
A75: 14.11.2025 | B75: FUND RECD FROM AMINEX SIB | C75: 850346 | E75: =E74+C75-D75 -> 854942.4
A76: 14.11.2025 | B76: TT TRF TO SILVER STONE WIO | D76: 851024 | E76: =E75+C76-D76 -> 3918.4
A77: 15.11.2025 | B77: FUND RECD FROM INFINITY WIO | C77: 502346 | E77: =E76+C77-D77 -> 506264.4
A78: 15.11.2025 | B78: FUND RECD FROM ROYAL EN EM ENBD AED | C78: 119539 | E78: =E77+C78-D78 -> 625803.4
A79: 15.11.2025 | B79: TT TRF TO IDEA GROVE EIB AED | D79: 623591 | E79: =E78+C79-D79 -> 2212.4
A80: 15.11.2025 | B80: BANK CHARGES | D80: 11.55 | E80: =E79+C80-D80 -> 2200.85
A81: 15.11.2025 | B81: FUND RECD FROM ROYAL EN EM ENBD AED | C81: 254690 | E81: =E80+C81-D81 -> 256890.85
A82: 17.11.2025 | B82: FUND RECD FROM INFINITY WIO | C82: 475690 | E82: =E81+C82-D82 -> 732580.85
A83: 17.11.2025 | B83: TT TRF TO IDEA GROVE EIB AED | D83: 725460 | E83: =E82+C83-D83 -> 7120.85
A84: 19.11.2025 | B84: FUND RECD FROM INFINITY WIO | C84: 215460 | E84: =E83+C84-D84 -> 222580.85
A85: 19.11.2025 | B85: TT TRF TO SILVER STONE WIO | D85: 216302 | E85: =E84+C85-D85 -> 6278.85
A86: 21.11.2025 | B86: FUND RECD FROM ROYAL EN EM ENBD AED | C86: 330250 | E86: =E85+C86-D86 -> 336528.85
A87: 21.11.2025 | B87: TT TRF TO IDEA GROVE EIB AED | D87: 332012 | E87: =E86+C87-D87 -> 4516.85
A88: 25.11.2025 | B88: FUND RECD FROM CAPS LOCK FAB AED | C88: 702694 | E88: =E87+C88-D88 -> 707210.85
A89: 25.11.2025 | B89: TT TRF TO IDEA GROVE EIB AED | D89: 703269 | E89: =E88+C89-D89 -> 3941.85
A90: 25.11.2025 | B90: BANK CHARGES | D90: 11.55 | E90: =E89+C90-D90 -> 3930.3
A91: 26.11.2025 | B91: FUND RECD FROM INFINITY WIO | C91: 802314 | E91: =E90+C91-D91 -> 806244.3
A92: 26.11.2025 | B92: TT TRF TO IDEA GROVE EIB AED | D92: 803917 | E92: =E91+C92-D92 -> 2327.3
A93: 27.11.2025 | B93: FUND RECD FROM INFINITY MSQ | C93: 463259 | E93: =E92+C93-D93 -> 465586.3
A94: 27.11.2025 | B94: TT TRF TO RED STONE WIO AED | D94: 462503 | E94: =E93+C94-D94 -> 3083.3
A95: 27.11.2025 | B95: BANK CHARGES | D95: 11.55 | E95: =E94+C95-D95 -> 3071.75
A96: 28.11.2025 | B96: FUND RECD FROM CAPS LOCK FAB AED | C96: 200315 | E96: =E95+C96-D96 -> 203386.75
A97: 28.11.2025 | B97: TT TRF TO IDEA GROVE EIB AED | D97: 199203 | E97: =E96+C97-D97 -> 4183.75
A98: 30.11.2025 | B98: BANK CHARGES | D98: 425 | E98: =E97+C98-D98 -> 3758.75
A99: 30.11.2025 | B99: BANK CHARGES | D99: 21.25 | E99: =E98+C99-D99 -> 3737.5 | F99: =+E99-3737.5 -> 5.8207661e-11
A100: 03.12.2025 | B100: FUND RECD FROM AMINEX SIB | C100: 662390 | E100: =E99+C100-D100 -> 666127.5
A101: 03.12.2025 | B101: TT TRF TO IDEA GROVE EIB AED | D101: 664021 | E101: =E100+C101-D101 -> 2106.5
...

Sheet CAPS LOCK FAB USD
A1: CAPS LOCK FAB USD
A2: USD
A3: DATE | B3: PARTICULAR | C3: DEPOSIT | D3: WITHDRAWAL | E3: BALANCE
E4: 0
A5: 15.09.2025 | B5: FUND RECD FROM CENTURY EXPORTS LTD USD | C5: 506230 | E5: =E4+C5-D5 -> 506230
A6: 15.09.2025 | B6: TT TRF TO AMINEX ADIB USD | D6: 98590 | E6: =E5+C6-D6 -> 407640
A7: 15.09.2025 | B7: BANK CHARGES | D7: 42.88 | E7: =E6+C7-D7 -> 407597.12
A8: 15.09.2025 | B8: TT TRF TO FABREX ENTERPRISES BOB USD | D8: 93010 | E8: =E7+C8-D8 -> 314587.12
A9: 15.09.2025 | B9: TT TRF TO KOTHARI MSQ USD | D9: 313092 | E9: =E8+C9-D9 -> 1495.12
A10: 18.09.2025 | B10: FUND RECD FROM CENTURY EXPORTS LTD BOB USD | C10: 927300 | E10: =E9+C10-D10 -> 928795.12
A11: 18.09.2025 | B11: TT TRF TO EVERSHINE GLOBAL LIMITED USD | D11: 249284 | E11: =E10+C11-D11 -> 679511.12
A12: 19.09.2025 | B12: TT TRF FROM CAPS LOCK FAB TO EVERSHINE GLOBAL USD C/O CENTURY | D12: 249561 | E12: =E11+C12-D12 -> 429950.12
A13: 19.09.2025 | B13: TT TRF FROM CAPS LOCK FAB TO ECOQUEST MSQ USD C/O | D13: 102040 | E13: =E12+C13-D13 -> 327910.12
A14: 19.09.2025 | B14: TT TRF FROM CAPS LOCK FAB TO TRESCA FAB USD C/O | D14: 327909 | E14: =E13+C14-D14 -> 1.12
A15: 17.12.2025 | B15: FUND RECD FROM DIVINE GLOBAL IOB | C15: 640425 | E15: =E14+C15-D15 -> 640426.12
A16: 17.12.2025 | B16: TT TRF TO ROYAL EN EM ENBD USD | D16: 278640 | E16: =E15+C16-D16 -> 361786.12
A17: 17.12.2025 | B17: BANK CHARGES | D17: 42.88 | E17: =E16+C17-D17 -> 361743.24
A18: 17.12.2025 | B18: TT TRF TO ROYAL EN EM ENBD USD | D18: 361700 | E18: =E17+C18-D18 -> 43.24
A19: 17.12.2025 | B19: BANK CHARGES | D19: 42.88 | E19: =E18+C19-D19 -> 0.36
A20: 09.01.2026 | B20: FUND RECD FROM DIVINE GLOBAL IOB | C20: 502305 | E20: =E19+C20-D20 -> 502305.36
A21: 09.01.2026 | B21: TT TRF TO ROYAL EN EM ENBD USD | D21: 380453 | E21: =E20+C21-D21 -> 121852.36
A22: 09.01.2026 | B22: BANK CHARGES | D22: 85.76 | E22: =E21+C22-D22 -> 121766.6 | M22: k
A23: 09.01.2026 | B23: TT TRF TO ROYAL EN EM ENBD USD | D23: 121765 | E23: =E22+C23-D23 -> 1.6
E24: =E23+C24-D24 -> 1.6
E25: =E24+C25-D25 -> 1.6
E26: =E25+C26-D26 -> 1.6
E27: =E26+C27-D27 -> 1.6
E28: =E27+C28-D28 -> 1.6 | M28: k
E29: =E28+C29-D29 -> 1.6 | M29: k
E30: =E29+C30-D30 -> 1.6
E31: =E30+C31-D31 -> 1.6
E32: =E31+C32-D32 -> 1.6
E33: =E32+C33-D33 -> 1.6
E34: =E33+C34-D34 -> 1.6
E35: =E34+C35-D35 -> 1.6
E36: =E35+C36-D36 -> 1.6
E37: =E36+C37-D37 -> 1.6
E38: =E37+C38-D38 -> 1.6
E39: =E38+C39-D39 -> 1.6
E40: =E39+C40-D40 -> 1.6
E41: =E40+C41-D41 -> 1.6
... E110: =E109+C110-D110 -> 1.6

Sheet PINNACLE MSQ AED 
A1: PINNACLE GROUPS FZ LLC
A2: MSQ BANK AED ACC .NO -
A3: DATE | B3: PARTICULAR | C3: DEPOSIT | D3: WITHDRAWAL | E3: BALANCE
E4: 1143
A5: 30.12.2023 | B5: BANK CHARGES | D5: 787.5 | E5: =E4+C5-D5 -> 355.5
A6: 45293 | B6: BANK CHARGES | D6: 137.5 | E6: =E5+C6-D6 -> 218
A7: 45294 | D7: 218 | E7: =E6+C7-D7 -> 0
A8: 45300 | B8: recd from rhine wio | C8: 6721 | E8: =E7+C8-D8 -> 6721
A9: 45301 | B9: charges | D9: 122.84 | E9: =E8+C9-D9 -> 6598.16
A10: 45307 | B10: ETISALAT PAYMENT | D10: 2296.16 | E10: =E9+C10-D10 -> 4302
E11: =E10+C11-D11 -> 4302
A12: 45309 | B12: RECD PINNACLE INT MSQ | C12: 385000 | E12: =E11+C12-D12 -> 389302
A13: 45309 | B13: TRF TO KOTHARI | D13: 140175 | E13: =E12+C13-D13 -> 249127
A14: 45311 | B14: TRF COMIDA ADIB | D14: 248098 | E14: =E13+C14-D14 -> 1029
A15: 45311 | B15: charges | D15: 1.05 | E15: =E14+C15-D15 -> 1027.95
A16: 45322 | B16: reced from hedges adib | C16: 23984 | E16: =E15+C16-D16 -> 25011.95
A17: 45322 | B17: BANK CHARGES | D17: 788.45 | E17: =E16+C17-D17 -> 24223.5
A18: 45324 | B18: Clearing cheque | D18: 23000 | E18: =E17+C18-D18 -> 1223.5
A19: 45337 | B19: RECD PINNACLE GR WIO | C19: 50100 | E19: =E18+C19-D19 -> 51323.5
A20: 45338 | B20: trf to pinnacle gr wio | D20: 20200 | E20: =E19+C20-D20 -> 31123.5
A21: 45338 | B21: trf to pinnacle gr wio | D21: 26530 | E21: =E20+C21-D21 -> 4593.5
A22: 45338 | B22: charges | D22: 1.15 | E22: =E21+C22-D22 -> 4592.35
A23: 45351 | B23: charges | D23: 787.5 | E23: =E22+C23-D23 -> 3804.85
A24: 45366 | B24: RECD FROM PINNACLE INT MSQ AED | C24: 305000 | E24: =E23+C24-D24 -> 308804.85
A25: 45366 | B25: TRF TO KOTHARI MSQ AED | D25: 304500 | E25: =E24+C25-D25 -> 4304.85
A26: 45369 | B26: etisalat pmnt | D26: 313.96 | E26: =E25+C26-D26 -> 3990.89
A27: 45369 | B27: eitasalat office | D27: 2230.72 | E27: =E26+C27-D27 -> 1760.17
A28: 45369 | B28: dewa pmnt | D28: 462.03 | E28: =E27+C28-D28 -> 1298.14
A29: 45372 | B29: RECD FROM HEDGES MSQ AED | C29: 130211 | E29: =E28+C29-D29 -> 131509.14
A30: 45373 | B30: TRF TO GRENEW FZE | D30: 127050 | E30: =E29+C30-D30 -> 4459.14
A31: 45373 | B31: charges | D31: 1.05 | E31: =E30+C31-D31 -> 4458.09
A32: 45376 | B32: PAYMENT TO ORIENTAL INS | D32: 911.37 | E32: =E31+C32-D32 -> 3546.72
A33: 45380 | B33: TAX PAYMENT | D33: 2517.9 | E33: =E32+C33-D33 -> 1028.82
A34: 45382 | B34: charges | D34: 787.5 | E34: =E33+C34-D34 -> 241.32
A35: 45397 | B35: cash deposit | C35: 100000 | E35: =E34+C35-D35 -> 100241.32
A36: 45397 | B36: etisalat payment | D36: 2013.64 | E36: =E35+C36-D36 -> 98227.68
A37: 45397 | B37: etisalat pinnacle home | D37: 310 | E37: =E36+C37-D37 -> 97917.68
A38: 45400 | B38: DEWA BILL PAYMENT | D38: 268.16 | E38: =E37+C38-D38 -> 97649.52
A39: 45400 | B39: BILL PAYMENT | D39: 387.94 | E39: =E38+C39-D39 -> 97261.58
A40: 45400 | B40: CHARGES | D40: 15.85 | E40: =E39+C40-D40 -> 97245.73
A41: 45405 | B41: CHEQUE NO 000020 | D41: 82470 | E41: =E40+C41-D41 -> 14775.73
A42: 45407 | B42: TRF TO PA INTERNATIONAL EXPORT IMPORT MSQ ACCOUNT | D42: 500 | E42: =E41+C42-D42 -> 14275.73
A43: 45321 | B43: RECD FROM PINNCLE GR ADIB | C43: 14550 | E43: =E42+C43-D43 -> 28825.73
A44: 45413 | B44: charges | D44: 787.5 | E44: =E43+C44-D44 -> 28038.23
A45: 45414 | B45: CHEQUE NO 000012 | D45: 23000 | E45: =E44+C45-D45 -> 5038.23
A46: 45415 | B46: recd fro royal adib | C46: 60568 | E46: =E45+C46-D46 -> 65606.23
A47: 45418 | B47: cheque debit | D47: 60000 | E47: =E46+C47-D47 -> 5606.23
A48: 45426 | B48: etisalat pmnt | D48: 2184.08 | E48: =E47+C48-D48 -> 3422.15
A49: 45426 | B49: etisalat pmnt | D49: 356.66 | E49: =E48+C49-D49 -> 3065.49
A50: 45429 | B50: DEWA | D50: 260.24 | E50: =E49+C50-D50 -> 2805.25
A51: 45429 | B51: DEWA | D51: 478.68 | E51: =E50+C51-D51 -> 2326.57
A52: 45804 | B52: RECHARGE EMARAT CARD | D52: 1000 | E52: =E51+C52-D52 -> 1326.57
A53: 45444 | B53: charges | D53: 787.5 | E53: =E52+C53-D53 -> 539.07
A54: 45453 | B54: RECD | C54: 25000 | E54: =E53+C54-D54 -> 25539.07
A55: 45454 | B55: pamnt to hamriya free zone | D55: 3510 | E55: =E54+C55-D55 -> 22029.07
A56: 45454 | B56: TRF TO DHL MASHREQ ACCOUNT | D56: 944.81 | E56: =E55+C56-D56 -> 21084.26
A57: 45455 | B57: DUBAI CHAMBERS | D57: 101.05 | E57: =E56+C57-D57 -> 20983.21
A58: 45457 | B58: ETISALAT PAYMENT | D58: 365.41 | E58: =E57+C58-D58 -> 20617.8
A61: 45462 | B61: trf to premium exim adib | D61: 13684 | E61: =E58+C61-D61 -> 6933.8
A62: 45472 | B62: etisalat pmnt | D62: 115.5 | E62: =E61+C62-D62 -> 6818.3
A63: 45474 | B63: charges | D63: 787.5 | E63: =E62+C63-D63 -> 6030.8 | H63: 99
A64: 45475 | B64: EMARAT CARD RECHARGE | D64: 1000 | E64: =E63+C64-D64 -> 5030.8
A65: 45475 | B65: VAT PMNT | D65: 2735.89 | E65: =E64+C65-D65 -> 2294.91
A66: 45477 | B66: cash deposit | C66: 60000 | E66: =E65+C66-D66 -> 62294.91
A67: 45477 | B67: cheque debit | D67: 60000 | E67: =E66+C67-D67 -> 2294.91
A68: 45478 | B68: EMARAT CARD RECHARGE | D68: 1000 | E68: =E67+C68-D68 -> 1294.91
A69: 45490 | B69: ETISALAT PMNT | D69: 359.95 | E69: =E68+C69-D69 -> 934.96
A70: 45505 | B70: charges | D70: =5+100+32.5+650 -> 787.5 | E70: =E69+C70-D70 -> 147.46
A71: 45505 | B71: charges | D71: 32.5 | E71: =E70+C71-D71 -> 114.96
A72: 45535 | B72: charges | D72: 114.96 | E72: =E71+C72-D72 -> -3.292655e-11
A73: 45539 | B73: recd from dollar acc | C73: 640.04 | E73: =E72+C73-D73 -> 640.04
A74: 45539 | B74: charges | D74: 640.04 | E74: =E73+C74-D74 -> -3.2969183e-11
A75: 45539 | B75: RECD FROM ROYAL ENBD | C75: 61354 | E75: =E74+C75-D75 -> 61354
A76: 45540 | B76: cheque debit | D76: 60000 | E76: =E75+C76-D76 -> 1354
A77: 45561 | B77: Balance requirement charges | D77: 533.54 | E77: =E76+C77-D77 -> 820.46
A78: 45566 | B78: charges | D78: 253.96 | E78: =E77+C78-D78 -> 566.5
A79: 45302 | B79: Monthly Bank Charges | D79: 566.5 | E79: =E78+C79-D79 -> -3.6379788e-11
A80: 45600 | B80: RECD FROM ROYAL ENBD | C80: 62131 | E80: =E79+C80-D80 -> 62131
A81: 45600 | B81: CHARGES | D81: 160.96 | E81: =E80+C81-D81 -> 61970.04
A82: 45601 | B82: inward clearing cheque | D82: 60000 | E82: =E81+C82-D82 -> 1970.04
D83: 787.5 | E83: =E82+C83-D83 -> 1182.54
A84: 45694 | D84: 1182.54 | E84: =E83+C84-D84 -> -3.5470293e-11
E85: =E84+C85-D85 -> -3.5470293e-11
E86: =E85+C86-D86 -> -3.5470293e-11
E87: =E86+C87-D87 -> -3.5470293e-11
E88: =E87+C88-D88 -> -3.5470293e-11
E89: =E88+C89-D89 -> -3.5470293e-11
E90: =E89+C90-D90 -> -3.5470293e-11
E91: =E90+C91-D91 -> -3.5470293e-11
E92: =E91+C92-D92 -> -3.5470293e-11
E93: =E92+C93-D93 -> -3.5470293e-11
E94: =E93+C94-D94 -> -3.5470293e-11
E95: =E94+C95-D95 -> -3.5470293e-11
E96: =E95+C96-D96 -> -3.5470293e-11
... E102: =E101+C102-D102 -> -3.5470293e-11

Sheet PINNACLE MSQ USD
A1: PINNACLE GROUPS FZ LLC
A2: MSQ BANK USD ACC .NO -
A3: DATE | B3: PARTICULAR | C3: DEPOSIT | D3: WITHDRAWAL | E3: BALANCE
E4: 84.7
A5: 45295 | B5: charges | D5: 84.7 | E5: =E4+C5-D5 -> 0
A6: 45514 | B6: recd from eagle trans shipping | C6: 17756.19 | E6: =E5+C6-D6 -> 17756.19
A7: 45516 | B7: trf to pinnacle int adib usd | D7: 17550 | E7: =E6+C7-D7 -> 206.19
A8: 45516 | B8: charges | D8: 14.38 | E8: =E7+C8-D8 -> 191.81
A9: 45539 | B9: trf to AED acc | D9: 175.36 | E9: =E8+C9-D9 -> 16.45
E10: =E9+C10-D10 -> 16.45
E11: =E10+C11-D11 -> 16.45
E12: =E11+C12-D12 -> 16.45
E13: =E12+C13-D13 -> 16.45
E14: =E13+C14-D14 -> 16.45
E15: =E14+C15-D15 -> 16.45
E16: =E15+C16-D16 -> 16.45
E17: =E16+C17-D17 -> 16.45
E18: =E17+C18-D18 -> 16.45
E19: =E18+C19-D19 -> 16.45
E20: =E19+C20-D20 -> 16.45
E21: =E20+C21-D21 -> 16.45
... E96: =E95+C96-D96 -> 16.45
E97: =E96+C97-D97 -> 16.45 | G97: 162429
E98: =E97+C98-D98 -> 16.45
E99: =E98+C99-D99 -> 16.45
E100: =E99+C100-D100 -> 16.45

Sheet SILVER STONE WIO
A1: SILVER STONE WIO
A2: WIO
A3: DATE | B3: PARTICULAR | C3: DEPOSIT | D3: WITHDRAWAL | E3: BALANCE
A4: 45807 | B4: OPENING BALANCE | C4: 385 | E4: =C4 -> 385
A5: 45807 | B5: CASH DEPOSITED | C5: 4000 | E5: =E4+C5-D5 -> 4385
A6: 45782 | B6: CASH DEPOSITED | C6: 15000 | E6: =E5+C6-D6 -> 19385
A7: 45782 | B7: TT TRANSFER TO PANKAJ CHADHA WIO C/O BONDFLOW | D7: 15000 | E7: =E6+C7-D7 -> 4385
A8: 15-5-2025 | B8: CASH DEPOSITED | C8: =100000+96000+53500 -> 249500 | E8: =E7+C8-D8 -> 253885
A9: 15-5-2025 | B9: IDEA GROVE WIO A/C | D9: 252142 | E9: =E8+C9-D9 -> 1743
A10: 27-5-2025 | B10: INEXCO INTERNATIONAL | C10: 699650 | E10: =E9+C10-D10 -> 701393
A11: 27-5-2025 | B11: IDEA GROVE WIO A/C | D11: 699450 | E11: =E10+C11-D11 -> 1943
A12: 30-5-2025 | B12: CASH DEPOSITED | C12: 100000 | E12: =E11+C12-D12 -> 101943
A13: 30-5-2025 | B13: TT TRANSFER TO PANKAJ CHADHA WIO C/O BONDFLOW | D13: 92000 | E13: =E12+C13-D13 -> 9943
A14: 31-5-2025 | B14: IDEA GROVE WIO A/C | D14: 9512 | E14: =E13+C14-D14 -> 431
A15: 45753 | B15: ROYAL EN EM ENBD | C15: 14951 | E15: =E14+C15-D15 -> 15382
A16: 45753 | B16: TT TRANSFER TO PANKAJ CHADHA WIO C/O BONDFLOW | D16: 15000 | E16: =E15+C16-D16 -> 382
A17: 45967 | B17: CASH DEPOSITED | C17: 130000 | E17: =E16+C17-D17 -> 130382
A18: 45967 | B18: IDEA GROVE WIO A/C | D18: 130014 | E18: =E17+C18-D18 -> 368
A19: 17/6/2025 | B19: CASH DEPOSITED | C19: =49500+40500+34500+500 -> 125000 | E19: =E18+C19-D19 -> 125368
A20: 17/6/2025 | B20: IDEA GROVE WIO A/C | D20: 124104 | E20: =E19+C20-D20 -> 1264
A21: 23/6/2025 | B21: USD RECD | C21: 44058 | E21: =E20+C21-D21 -> 45322
A22: 23/6/2025 | B22: CAPSLOCK | D22: 44124 | E22: =E21+C22-D22 -> 1198
A23: 24-6-2025 | B23: USD RECD | C23: 6975 | E23: =E22+C23-D23 -> 8173
A24: 24-6-2025 | B24: CASH DEPOSITED | C24: =49500+40500+34500+500 -> 125000 | E24: =E23+C24-D24 -> 133173
A25: 24-6-2025 | B25: IDEA GROVE WIO A/C | D25: 130451 | E25: =E24+C25-D25 -> 2722
A26: 28-6-2025 | B26: USD RECD | C26: 748986 | E26: =E25+C26-D26 -> 751708
A27: 28-6-2025 | B27: TT TRANSFER TO INFINITY WIO A/C | D27: 230145 | E27: =E26+C27-D27 -> 521563
A28: 28-6-2025 | B28: CAPSLOCK | D28: 451201 | E28: =E27+C28-D28 -> 70362
A29: 45664 | B29: USD RECD | C29: 589642 | E29: =E28+C29-D29 -> 660004
A30: 45664 | B30: CANRIFY ADIB | D30: 270142 | E30: =E29+C30-D30 -> 389862
A31: 45695 | B31: TT TRANSFER TO INFINITY WIO A/C | D31: 388142 | E31: =E30+C31-D31 -> 1720
A32: 45907 | B32: ROYAL EN EM ENBD | C32: 12555 | E32: =E31+C32-D32 -> 14275
A33: 45907 | B33: pinnacle int fab | C33: 86412 | E33: =E32+C33-D33 -> 100687
A34: 45907 | B34: pankaj ji wio | D34: 17500 | E34: =E33+C34-D34 -> 83187
E35: =E34+C35-D35 -> 83187
E36: =E35+C36-D36 -> 83187
E37: =E36+C37-D37 -> 83187
E38: =E37+C38-D38 -> 83187
E39: =E38+C39-D39 -> 83187
E40: =E39+C40-D40 -> 83187
E41: =E40+C41-D41 -> 83187
E42: =E41+C42-D42 -> 83187
E43: =E42+C43-D43 -> 83187
E44: =E43+C44-D44 -> 83187
E45: =E44+C45-D45 -> 83187
E46: =E45+C46-D46 -> 83187
... E100: =E99+C100-D100 -> 83187

Sheet AGINRA EIB AED 
A1: AGINRA
A2: WIO AED ACC .NO -
A3: DATE | B3: PARTICULAR | C3: DEPOSIT | D3: WITHDRAWAL | E3: BALANCE
A4: 30-04-2025 | B4: FUND RECD FROM AGNIRA INT | E4: 5000
A5: 02.06.2025 | B5: BANK CHARGES | D5: =425+21.25 -> 446.25 | E5: =E4+C5-D5 -> 4553.75
A6: 02.07.2025 | B6: BANK CHARGES | D6: =425+21.25 -> 446.25 | E6: =E5+C6-D6 -> 4107.5
A7: 01.08.2025 | B7: BANK CHARGES | D7: =425+21.25 -> 446.25 | E7: =E6+C7-D7 -> 3661.25
A8: 25.09.2025 | B8: FUND RECD FROM IDEA GROVE EIB | C8: 125254 | E8: =E7+C8-D8 -> 128915.25
A9: 25.09.2025 | B9: TT TRF TO AMINEX ADIB | D9: 122967 | E9: =E8+C9-D9 -> 5948.25
A10: 02.10.2025 | B10: FUND RECD FROM IDEA GROVE EIB | C10: 251673 | E10: =E9+C10-D10 -> 257621.25
A11: 02.10.2025 | B11: FUND RECD FROM PINNACLE INT SIB AED | C11: 101348 | E11: =E10+C11-D11 -> 358969.25
A12: 02.10.2025 | B12: TT TRF TO AMINEX ADIB | D12: 354839 | E12: =E11+C12-D12 -> 4130.25
A13: 02.10.2025 | B13: BANK CHARGES | D13: 11.55 | E13: =E12+C13-D13 -> 4118.7
A14: 03.10.2025 | B14: FUND RECD FROM IDEA GROVE EIB | C14: 549634 | E14: =E13+C14-D14 -> 553752.7
A15: 03.10.2025 | B15: TT TRF TO CAPS LOCK FAB AED | D15: 551237 | E15: =E14+C15-D15 -> 2515.7
A16: 03.10.2025 | B16: BANK CHARGES | D16: 11.55 | E16: =E15+C16-D16 -> 2504.15
A17: 04.10.2025 | B17: FUND RECD FROM PINNACLE INT ADIB AED | C17: 223101 | E17: =E16+C17-D17 -> 225605.15
A18: 04.10.2025 | B18: FUND RECD FROM BULLFROG ADIB AED | C18: 119201 | E18: =E17+C18-D18 -> 344806.15
A19: 04.10.2025 | B19: FUND RECD FROM IDEA GROVE EIB | C19: 243684 | E19: =E18+C19-D19 -> 588490.15
A20: 04.10.2025 | B20: TT TRF TO CAPS LOCK FAB AED | D20: 582641 | E20: =E19+C20-D20 -> 5849.15
A21: 04.10.2025 | B21: BANK CHARGES | D21: 11.55 | E21: =E20+C21-D21 -> 5837.6
A22: 30.09.2025 | B22: BANK CHARGES | D22: 425 | E22: =E21+C22-D22 -> 5412.6
A23: 30.09.2025 | B23: BANK CHARGES | D23: 21.25 | E23: =E22+C23-D23 -> 5391.35
A24: 01.10.2025 | B24: BANK CHARGES | D24: 425 | E24: =E23+C24-D24 -> 4966.35
A25: 01.10.2025 | B25: BANK CHARGES | D25: 21.25 | E25: =E24+C25-D25 -> 4945.1
A26: 01.10.2025 | B26: BANK CHARGES | D26: 11.55 | E26: =E25+C26-D26 -> 4933.55
A27: 09.10.2025 | B27: FUND RECD FROM IDEA GROVE EIB | C27: 453120 | E27: =E26+C27-D27 -> 458053.55
A28: 09.10.2025 | B28: TT TRF TO AMINEX ADIB | D28: 6830 | E28: =E27+C28-D28 -> 451223.55
A29: 09.10.2025 | B29: BANK CHARGES | D29: 11.55 | E29: =E28+C29-D29 -> 451212
A30: 10.10.2025 | B30: TT TRF TO CAPS LOCK FAB AED | D30: 443060 | E30: =E29+C30-D30 -> 8152
A31: 10.10.2025 | B31: BANK CHARGES | D31: 11.55 | E31: =E30+C31-D31 -> 8140.45
A32: 11.10.2025 | B32: FUND RECD FROM IDEA GROVE EIB | C32: 513620 | E32: =E31+C32-D32 -> 521760.45
A33: 11.10.2025 | B33: TT TRF TO AMINEX ADIB | D33: 515340 | E33: =E32+C33-D33 -> 6420.45
A34: 11.10.2025 | B34: BANK CHARGES | D34: 11.55 | E34: =E33+C34-D34 -> 6408.9
A35: 18.10.2025 | B35: FUND RECD FROM PINNACLE INT ADIB AED | C35: 515340 | E35: =E34+C35-D35 -> 521748.9
A36: 18.10.2025 | B36: TT TRF TO CAPS LOCK FAB AED | D36: 517467 | E36: =E35+C36-D36 -> 4281.9
A37: 18.10.2025 | B37: BANK CHARGES | D37: 11.55 | E37: =E36+C37-D37 -> 4270.35
A38: 18.10.2025 | B38: FUND RECD FROM BULLFROG ADIB AED | C38: 432658 | E38: =E37+C38-D38 -> 436928.35
A39: 18.10.2025 | B39: TT TRF TO CAPS LOCK FAB AED | D39: 430256 | E39: =E38+C39-D39 -> 6672.35
A40: 18.10.2025 | B40: BANK CHARGES | D40: 11.55 | E40: =E39+C40-D40 -> 6660.8
A41: 08.11.2025 | B41: FUND RECD FROM ENFLOW MSQ AED | C41: 148963 | E41: =E40+C41-D41 -> 155623.8
A42: 08.11.2025 | B42: TT TRF TO CAPS LOCK FAB AED | D42: 147231 | E42: =E41+C42-D42 -> 8392.8
A43: 08.11.2025 | B43: BANK CHARGES | D43: 11.55 | E43: =E42+C43-D43 -> 8381.25 | F43: =+E43-7935 -> 446.25
A44: 17.11.2025 | B44: FUND RECD FROM IDEA GROVE EIB | C44: 726934 | E44: =E43+C44-D44 -> 735315.25
A45: 17.11.2025 | B45: TT TRF TO CAPS LOCK FAB AED | D45: 729682 | E45: =E44+C45-D45 -> 5633.25
A46: 17.11.2025 | B46: BANK CHARGES | D46: 11.55 | E46: =E45+C46-D46 -> 5621.7
A47: 21.11.2025 | B47: FUND RECD FROM IDEA GROVE EIB | C47: 331947 | E47: =E46+C47-D47 -> 337568.7
A48: 21.11.2025 | B48: TT TRF TO AMINEX ADIB | D48: 330151 | E48: =E47+C48-D48 -> 7417.7
A49: 21.11.2025 | B49: BANK CHARGES | D49: 11.55 | E49: =E48+C49-D49 -> 7406.15
A50: 21.11.2025 | B50: BANK CHARGES | D50: 425 | E50: =E49+C50-D50 -> 6981.15
A51: 21.11.2025 | B51: BANK CHARGES | D51: 21.25 | E51: =E50+C51-D51 -> 6959.9
A52: 25.11.2025 | B52: FUND RECD FROM IDEA GROVE EIB | C52: 703021 | E52: =E51+C52-D52 -> 709980.9
A53: 25.11.2025 | B53: TT TRF TO AMINEX ADIB | D53: 705217 | E53: =E52+C53-D53 -> 4763.9
A54: 25.11.2025 | B54: BANK CHARGES | D54: 11.55 | E54: =E53+C54-D54 -> 4752.35
A55: 26.11.2025 | B55: FUND RECD FROM PINNACLE INT ADIB AED | C55: 101583 | E55: =E54+C55-D55 -> 106335.35
A56: 26.11.2025 | B56: FUND RECD FROM IDEA GROVE EIB | C56: 803482 | E56: =E55+C56-D56 -> 909817.35
A57: 26.11.2025 | B57: TT TRF TO INFINITY WIO AED | D57: 903426 | E57: =E56+C57-D57 -> 6391.35
A58: 26.11.2025 | B58: BANK CHARGES | D58: 11.55 | E58: =E57+C58-D58 -> 6379.8
A59: 09.12.2025 | B59: FUND RECD FROM IDEA GROVE EIB | C59: 800127 | E59: =E58+C59-D59 -> 806506.8
A60: 09.12.2025 | B60: TT TRF TO INFINITY WIO AED | D60: 801438 | E60: =E59+C60-D60 -> 5068.8
A61: 09.12.2025 | B61: BANK CHARGES | D61: 11.55 | E61: =E60+C61-D61 -> 5057.25
A62: 09.12.2025 | B62: BANK CHARGES | D62: 421 | E62: =E61+C62-D62 -> 4636.25
A63: 09.12.2025 | B63: BANK CHARGES | D63: 21.25 | E63: =E62+C63-D63 -> 4615
A64: 09.12.2025 | B64: BANK CHARGES | D64: 4 | E64: =E63+C64-D64 -> 4611
A65: 13.12.2025 | B65: FUND RECD FROM IDEA GROVE EIB | C65: 763843 | E65: =E64+C65-D65 -> 768454
A66: 13.12.2025 | B66: TT TRF TO CAPS LOCK FAB AED | D66: 183923 | E66: =E65+C66-D66 -> 584531
A67: 13.12.2025 | B67: BANK CHARGES | D67: 1.05 | E67: =E66+C67-D67 -> 584529.95
A68: 13.12.2025 | B68: TT TRF TO INFINITY WIO AED | D68: 581320 | E68: =E67+C68-D68 -> 3209.95
A69: 13.12.2025 | B69: BANK CHARGES | D69: 11.55 | E69: =E68+C69-D69 -> 3198.4
A70: 18.12.2025 | B70: FUND RECD FROM IDEA GROVE EIB | C70: 249968 | E70: =E69+C70-D70 -> 253166.4
A71: 18.12.2025 | B71: FUND RECD FROM ROYAL ENBD | C71: 8569 | E71: =E70+C71-D71 -> 261735.4
A72: 18.12.2025 | B72: TT TRF TO AMINEX ADIB | D72: 259023 | E72: =E71+C72-D72 -> 2712.4
A73: 18.12.2025 | B73: BANK CHARGES | D73: 11.55 | E73: =E72+C73-D73 -> 2700.85
A74: 02.01.2026 | B74: BANK CHARGES | D74: 10.5 | E74: =E73+C74-D74 -> 2690.35
A75: 05.01.2026 | B75: BANK CHARGES | D75: 425 | E75: =E74+C75-D75 -> 2265.35
A76: 05.01.2026 | B76: BANK CHARGES | D76: 21.25 | E76: =E75+C76-D76 -> 2244.1
A77: 13.01.2026 | B77: FUND RECD FROM IDEA GROVE EIB | C77: 600102 | E77: =E76+C77-D77 -> 602346.1
A78: 13.01.2026 | B78: TT TRF TO INFINITY WIO AED | D78: 600150 | E78: =E77+C78-D78 -> 2196.1
A79: 13.01.2026 | B79: BANK CHARGES | D79: 11.55 | E79: =E78+C79-D79 -> 2184.55
A80: 16.01.2026 | B80: FUND RECD FROM IDEA GROVE EIB | C80: 510067 | E80: =E79+C80-D80 -> 512251.55
A81: 16.01.2026 | B81: TT TRF TO INFINITY WIO AED | D81: 510797 | E81: =E80+C81-D81 -> 1454.55
A82: 16.01.2026 | B82: BANK CHARGES | D82: 11.55 | E82: =E81+C82-D82 -> 1443
A83: 03.02.2026 | B83: BANK CHARGES | D83: 425 | E83: =E82+C83-D83 -> 1018
A84: 03.02.2026 | B84: BANK CHARGES | D84: 9.7 | E84: =E83+C84-D84 -> 1008.3
A85: 07.02.2026 | B85: FUND RECD FROM IDEA GROVE EIB | C85: 855743 | E85: =E84+C85-D85 -> 856751.3
A86: 07.02.2026 | B86: TT TRF TO INFINITY WIO AED | D86: 854906 | E86: =E85+C86-D86 -> 1845.3
A87: 07.02.2026 | B87: BANK CHARGES | D87: 11.55 | E87: =E86+C87-D87 -> 1833.75
A88: 09.02.2026 | B88: FUND RECD FROM IDEA GROVE EIB | C88: 811204 | E88: =E87+C88-D88 -> 813037.75
A89: 09.02.2026 | B89: TT TRF TO AMINEX SIB AED | D89: 812034 | E89: =E88+C89-D89 -> 1003.75
A90: 09.02.2026 | B90: BANK CHARGES | D90: 11.55 | E90: =E89+C90-D90 -> 992.2
A91: 09.02.2026 | B91: FUND RECD FROM IDEA GROVE EIB | C91: 708234 | E91: =E90+C91-D91 -> 709226.2
A92: 09.02.2026 | B92: TT TRF TO AMINEX SIB AED | D92: 707589 | E92: =E91+C92-D92 -> 1637.2
A93: 09.02.2026 | B93: BANK CHARGES | D93: 11.55 | E93: =E92+C93-D93 -> 1625.65
A94: 13.04.2026 | B94: BANK CHARGES | D94: 425 | E94: =E93+C94-D94 -> 1200.65
A95: 13.04.2026 | B95: BANK CHARGES | D95: 21.25 | E95: =E94+C95-D95 -> 1179.4
A96: 13.04.2026 | B96: BANK CHARGES | D96: 425 | E96: =E95+C96-D96 -> 754.4
A97: 13.04.2026 | B97: BANK CHARGES | D97: 21.25 | E97: =E96+C97-D97 -> 733.15
E98: =E97+C98-D98 -> 733.15
E99: =E98+C99-D99 -> 733.15
E100: =E99+C100-D100 -> 733.15
...

Sheet PINNACLE MSQ EURO
A1: PINNACLE GROUPS FZ LLC
A2: MSQ BANK EURO ACC .NO -
A3: DATE | B3: PARTICULAR | C3: DEPOSIT | D3: WITHDRAWAL | E3: BALANCE
E4: 0
E5: =E4+C5-D5 -> 0
E6: =E5+C6-D6 -> 0
E7: =E6+C7-D7 -> 0
E8: =E7+C8-D8 -> 0
E9: =E8+C9-D9 -> 0
E10: =E9+C10-D10 -> 0
E11: =E10+C11-D11 -> 0
E12: =E11+C12-D12 -> 0
E13: =E12+C13-D13 -> 0
E14: =E13+C14-D14 -> 0
E15: =E14+C15-D15 -> 0
E16: =E15+C16-D16 -> 0
... E100: =E99+C100-D100 -> 0

Sheet PINNACLE NBF AED
A1: PINNACLE GROUPS FZ LLC
A2: BANK NBF ACC .NO -
A3: DATE | B3: PARTICULAR | C3: DEPOSIT | D3: WITHDRAWAL | E3: BALANCE
E4: 1449 | H4: 787.5
A5: 44938 | B5: BANK CHARGES | D5: 367.5 | E5: =E4+C5-D5 -> 1081.5
A6: 02.01.2024 | B6: BANK CHARGES | D6: 367.5 | E6: =E5+C6-D6 -> 714
A7: 45327 | B7: BANK CHARGES | D7: 367.5 | E7: =E6+C7-D7 -> 346.5
B8: TT REC FROM PINNACLE WIO | C8: 79986 | E8: =E7+C8-D8 -> 80332.5
D9: 1.05 | E9: =E8+C9-D9 -> 80331.45
A10: 45335 | B10: trf to electronic way | D10: 630 | E10: =E9+C10-D10 -> 79701.45
A11: 45337 | B11: trf to pinnacle wio | D11: 44600 | E11: =E10+C11-D11 -> 35101.45
A12: 45337 | B12: TRF TO COMIDA NBF | D12: 17531 | E12: =E11+C12-D12 -> 17570.45
A13: 45337 | B13: ETISALAT PMNT | D13: 2237.45 | E13: =E12+C13-D13 -> 15333
A14: 45337 | B14: ETISALAT PMNT NISHANT MARROO | D14: 105 | E14: =E13+C14-D14 -> 15228
A15: 45338 | B15: DEWA PMNT | D15: 811.31 | E15: =E14+C15-D15 -> 14416.69
A16: 45338 | B16: charge | D16: 1 | E16: =E15+C16-D16 -> 14415.69
A17: 45342 | B17: RECD ROYAL NBF | C17: 101378 | E17: =E16+C17-D17 -> 115793.69
A18: 45342 | B18: TRF TO PG WIO AEDC | D18: 103300 | E18: =E17+C18-D18 -> 12493.69
A19: 45342 | B19: CHARGES | D19: 15.75 | E19: =E18+C19-D19 -> 12477.94
A20: 45345 | B20: charge | D20: 1 | E20: =E19+C20-D20 -> 12476.94
A21: 45345 | B21: TRF SEANDEEPK KEDIA MASHREQ BANK | D21: 9235 | E21: =E20+C21-D21 -> 3241.94
A22: 45345 | B22: CHARGES | D22: 15.75 | E22: =E21+C22-D22 -> 3226.19
A23: 45348 | B23: recd pinnacle gr wio | C23: 14450 | E23: =E22+C23-D23 -> 17676.19
A24: 45348 | B24: trf to wisor wio aed | D24: 3390 | E24: =E23+C24-D24 -> 14286.19
A25: 45351 | B25: charges | D25: 367.5 | E25: =E24+C25-D25 -> 13918.69
A26: 45351 | B26: charges | D26: 16.75 | E26: =E25+C26-D26 -> 13901.94
A27: 45367 | B27: RECD FROM ROYAL NBF AED | C27: 487995 | E27: =E26+C27-D27 -> 501896.94
A28: 45367 | B28: TRF TO ADITYA TRIVEDI WIO | D28: 500185 | E28: =E27+C28-D28 -> 1711.94
A29: 45371 | B29: DEWA PMNT | D29: 765 | E29: =E28+C29-D29 -> 946.94
A30: 45372 | B30: recd from hedges FAB | C30: 495310 | E30: =E29+C30-D30 -> 496256.94
A31: 45372 | B31: recd from rhine enbd | C31: 285654 | E31: =E30+C31-D31 -> 781910.94
A32: 45372 | B32: RECD FROM HEDGES AL MASHRAF | C32: 497125 | E32: =E31+C32-D32 -> 1279035.9
A33: 45372 | B33: RECD FROM HEDGES ADIB | C33: 498122 | E33: =E32+C33-D33 -> 1777157.9
A34: 45372 | B34: RECD FROM ROYAL NBF AED | C34: 257425 | E34: =E33+C34-D34 -> 2034582.9
A35: 45372 | B35: RECD FROM ROYAL NBF AED | C35: 531850 | E35: =E34+C35-D35 -> 2566432.9
A36: 45373 | B36: TRF GRENEW FZE (COMMERCIAL INVESTMENT) | D36: 1800260 | E36: =E35+C36-D36 -> 766172.94
A37: 45373 | B37: TRF GRENEW FZE (COMMERCIAL INVESTMENT) | D37: 765150 | E37: =E36+C37-D37 -> 1022.94
A38: 45373 | B38: charges | D38: 15.75 | E38: =E37+C38-D38 -> 1007.19
A39: 45382 | B39: CHARGES | D39: 367.5 | E39: =E38+C39-D39 -> 639.69
A40: 45382 | B40: IBAN LETTER CHARGE | D40: 105 | E40: =E39+C40-D40 -> 534.69 | H40: =1128285.4+3500 -> 1131785.4
A41: 45384 | B41: HOLD AMOUNT RECD | C41: 619 | E41: =E40+C41-D41 -> 1153.69
A42: 45384 | B42: RETURN SAOURSA TECH | C42: 43600 | E42: =E41+C42-D42 -> 44753.69
A43: 45384 | B43: CHARGES | D43: 2.1 | E43: =E42+C43-D43 -> 44751.59
A44: 45386 | B44: trf to NIYAT SIB | D44: 2050 | E44: =E43+C44-D44 -> 42701.59
A45: 45386 | B45: TRF TO NIYAT NBF AED | D45: 42350 | E45: =E44+C45-D45 -> 351.59
A46: 45386 | B46: CHARGES | D46: 2.1 | E46: =E45+C46-D46 -> 349.49
A47: 45413 | B47: CHARGES | D47: 349.48 | E47: =E46+C47-D47 -> 0.0099999999
A48: 45416 | B48: ROYAL NBF | C48: 1510 | E48: =E47+C48-D48 -> 1510.01
A49: 45416 | B49: CHARGES | D49: =17.19+0.86 -> 18.05 | E49: =E48+C49-D49 -> 1491.96
A50: 45423 | B50: PAID TO EMARAT PREPAID | D50: 500 | E50: =E49+C50-D50 -> 991.96
A51: 45444 | B51: CHARGES | D51: 367.5 | E51: =E50+C51-D51 -> 624.46
A52: 45457 | B52: RECD FROM ROYAL NBF AED | C52: 210264 | E52: =E51+C52-D52 -> 210888.46
A53: 45457 | B53: TRF TO ADITYA TRIVEDI WIO | D53: 210150 | E53: =E52+C53-D53 -> 738.46
A54: 45474 | B54: CHARGES | D54: 367.5 | E54: =E53+C54-D54 -> 370.96
A55: 45484 | B55: ATM card Charges | D55: 157.5 | E55: =E54+C55-D55 -> 213.46
A56: 45484 | B56: CHARGES | D56: 213.45 | E56: =E55+C56-D56 -> 0.0099999999
A57: 45546 | B57: RECD FRON ROYAL ENBD | C57: 1342 | E57: =E56+C57-D57 -> 1342.01
A58: 45566 | B58: CHARGES | D58: 889.05 | E58: =E57+C58-D58 -> 452.96
A59: 45302 | B59: Monhtly Bank Charges | D59: =350+17.5 -> 367.5 | E59: =E58+C59-D59 -> 85.46
A60: 45619 | B60: cheque recd | C60: 15750 | E60: =E59+C60-D60 -> 15835.46
A61: 45987 | B61: TRF TO SAHUL | D61: 4625 | E61: =E60+C61-D61 -> 11210.46
A62: 45987 | B62: trf to kedia ji mashreq | D62: 10000 | E62: =E61+C62-D62 -> 1210.46
A63: 45626 | B63: charges | D63: 367.5 | E63: =E62+C63-D63 -> 842.96
A64: 45657 | B64: charges | D64: 367.5 | E64: =E63+C64-D64 -> 475.46
A65: 45689 | B65: CHARGES | D65: 367.5 | E65: =E64+C65-D65 -> 107.96
A66: 45717 | B66: CHARGES | D66: 107.91 | E66: =E65+C66-D66 -> 0.05
A67: 45772 | B67: TT REC FROM COMIDA NBF A/C | C67: 841 | E67: =E66+C67-D67 -> 841.05
A68: 45772 | B68: USD TO AED | D68: 250 | E68: =E67+C68-D68 -> 591.05
A69: 45778 | B69: aed | C69: 28626 | E69: =E68+C69-D69 -> 29217.05
A70: 45778 | B70: CHARGES | D70: 591.05 | E70: =E69+C70-D70 -> 28626
A71: 45780 | B71: CHARGES | D71: 403.54 | E71: =E70+C71-D71 -> 28222.46
A72: 45782 | B72: INFINITY ADIB A/C | D72: 27104 | E72: =E71+C72-D72 -> 1118.46
A73: 14/05/2025 | B73: INEXCO INTERNATIONAL DMCC | C73: 800610 | E73: =E72+C73-D73 -> 801728.46
A74: 14/05/2025 | B74: INVEST TRADE PT LTED | D74: 800541 | E74: =E73+C74-D74 -> 1187.46
A75: 15-5-2025 | B75: INEXCO INTERNATIONAL DMCC | C75: 500245 | E75: =E74+C75-D75 -> 501432.46
A76: 15-5-2025 | B76: CASH DEPOSITED | C76: 200000 | E76: =E75+C76-D76 -> 701432.46 | G76: 28222.46
A77: 15-5-2025 | B77: HEDGES NBF | C77: 199998 | E77: =E76+C77-D77 -> 901430.46 | G77: =E76-G76 -> 673210
A78: 15-5-2025 | B78: INVEST TRADE PT LTED | D78: 899950 | E78: =E77+C78-D78 -> 1480.46
A79: 16-5-2025 | B79: TT RECEIVED FROM PINNACLE INT NBF A/C | C79: 248998 | E79: =E78+C79-D79 -> 250478.46
A80: 16-5-2025 | B80: COMIDA NBF A/C | C80: 34996 | E80: =E79+C80-D80 -> 285474.46
A81: 16-5-2025 | B81: ROYAL NBF | C81: 49980 | E81: =E80+C81-D81 -> 335454.46
A82: 16-5-2025 | B82: ROYAL NBF | C82: 200412 | E82: =E81+C82-D82 -> 535866.46
A83: 16-5-2025 | B83: COMIDA NBF A/C | C83: 200945 | E83: =E82+C83-D83 -> 736811.46
A84: 16-5-2025 | B84: INVEST TRADE PT LTED | D84: 402412 | E84: =E83+C84-D84 -> 334399.46
A85: 16-5-2025 | B85: AMINEX ADIB A/C | D85: 84415 | E85: =E84+C85-D85 -> 249984.46
A86: 16-5-2025 | B86: INFINITY WIO A/C | D86: 248995 | E86: =E85+C86-D86 -> 989.46
A87: 20-5-2025 | B87: ROYAL ENBD A/C | C87: 13555 | E87: =E86+C87-D87 -> 14544.46
A88: 21-5-2025 | B88: ROYAL ENBD A/C | C88: 6412 | E88: =E87+C88-D88 -> 20956.46
A89: 21-5-2025 | B89: PINNACLE INT SIB A/C | D89: 5000 | E89: =E88+C89-D89 -> 15956.46
A90: 23-5-2025 | B90: CHEQUE WITHDRAW | D90: 12757.5 | E90: =E89+C90-D90 -> 3198.96
A91: 23-5-2025 | B91: ROYAL ENBD A/C | C91: 9985 | E91: =E90+C91-D91 -> 13183.96
A92: 23-5-2025 | B92: CASH DEPOSITED | C92: 170000 | E92: =E91+C92-D92 -> 183183.96
A93: 23-5-2025 | B93: TT TRANSFER TO MJS STAR NBF A/C | D93: 10941 | E93: =E92+C93-D93 -> 172242.96
A94: 24-5-2025 | B94: LOAN | D94: 155000 | E94: =E93+C94-D94 -> 17242.96
A95: 24-5-2025 | B95: LOAN | D95: 7750 | E95: =E94+C95-D95 -> 9492.96
A96: 24-5-2025 | B96: LOAN | D96: 300 | E96: =E95+C96-D96 -> 9192.96
A97: 24-5-2025 | B97: LOAN | D97: 6000 | E97: =E96+C97-D97 -> 3192.96
A98: 27-5-2025 | B98: ROYAL ENBD A/C | C98: 255142 | E98: =E97+C98-D98 -> 258334.96
A99: 27-5-2025 | B99: pinnacle sib | D99: 242500 | E99: =E98+C99-D99 -> 15834.96
A100: 27-5-2025 | B100: carnify adib | D100: 15100 | E100: =E99+C100-D100 -> 734.96
...

Sheet BLACKPEPPER GN SIB
A1: BLACKPEPPER GEN SIB
C4: 5000 | E4: =C4 -> 5000
E5: =E4+C5-D5 -> 5000
E6: =E5+C6-D6 -> 5000
E7: =E6+C7-D7 -> 5000
E8: =E7+C8-D8 -> 5000
E9: =E8+C9-D9 -> 5000
E10: =E9+C10-D10 -> 5000
E11: =E10+C11-D11 -> 5000
E12: =E11+C12-D12 -> 5000
E13: =E12+C13-D13 -> 5000
E14: =E13+C14-D14 -> 5000
E15: =E14+C15-D15 -> 5000
E16: =E15+C16-D16 -> 5000
... E210: =E209+C210-D210 -> 5000

Sheet ENFLOW SIB
A1: ENFLOW SIB
A4: 45769 | B4: TT RECEIVED FROM ENFLOW MSQ A/C | C4: 5000 | E4: =C4 -> 5000
A5: 45778 | B5: charges | D5: 400 | E5: =E4+C5-D5 -> 4600
A6: 45778 | B6: charges | D6: 25.25 | E6: =E5+C6-D6 -> 4574.75
E7: =E6+C7-D7 -> 4574.75
E8: =E7+C8-D8 -> 4574.75
E9: =E8+C9-D9 -> 4574.75
E10: =E9+C10-D10 -> 4574.75
E11: =E10+C11-D11 -> 4574.75
E12: =E11+C12-D12 -> 4574.75
E13: =E12+C13-D13 -> 4574.75
E14: =E13+C14-D14 -> 4574.75
E15: =E14+C15-D15 -> 4574.75
E16: =E15+C16-D16 -> 4574.75
E17: =E16+C17-D17 -> 4574.75
E18: =E17+C18-D18 -> 4574.75
... E180: =E179+C180-D180 -> 4574.75

Sheet ENFLOW MSQ
A1: ENFLOW MSQ
A4: 45769 | B4: OPENING BALANCE | C4: 481.35 | E4: =C4 -> 481.35
A5: 45769 | B5: TT RECEIVED FROM ROYAL EN EM ENBD A/C | C5: 9899 | E5: =E4+C5-D5 -> 10380.35
A6: 45769 | B6: TT TRANSFER TO ENFLOW SIB AC | D6: 5000 | E6: =E5+C6-D6 -> 5380.35
A7: 45778 | B7: CHARGES | D7: 550 | E7: =E6+C7-D7 -> 4830.35
A8: 45778 | B8: CHARGES | D8: 27.5 | E8: =E7+C8-D8 -> 4802.85
A9: 45778 | B9: CHARGES | D9: 35 | E9: =E8+C9-D9 -> 4767.85
A10: 45778 | B10: CHARGES | D10: 1.75 | E10: =E9+C10-D10 -> 4766.1
A11: 21-5-2025 | B11: ETISALAT BILL | D11: 1149.75 | E11: =E10+C11-D11 -> 3616.35
A12: 24-5-2025 | B12: CASH DEPOSITED | C12: 50000 | E12: =E11+C12-D12 -> 53616.35
A13: 24-5-2025 | B13: CARNIFY ADIB | D13: 51124.11 | E13: =E12+C13-D13 -> 2492.24
A14: 13-06-2025 | B14: ETISALAT BILL | D14: 417.18 | E14: =E13+C14-D14 -> 2075.06
A15: 17-6-2025 | B15: RECD FROM ARAVALI | C15: 797667.5 | E15: =E14+C15-D15 -> 799742.56
A16: 17-6-2025 | B16: IDEA GROVE WIO | D16: 321415.11 | E16: =E15+C16-D16 -> 478327.45
A17: 18-6-2025 | B17: TT TRANSFER TO BLACKPEPPER GENERAL NBF | D17: 477601 | E17: =E16+C17-D17 -> 726.45
A18: 20-6-2025 | B18: RECD FROM ARAVALI | C18: 957201 | E18: =E17+C18-D18 -> 957927.45
A19: 20-6-2025 | B19: IDEA GROVE WIO | D19: 725410.21 | E19: =E18+C19-D19 -> 232517.24
A20: 20-6-2025 | B20: IDEA GROVE WIO | D20: 201375 | E20: =E19+C20-D20 -> 31142.24
A21: 24-6-2025 | B21: IDEA GROVE WIO | D21: 29998.88 | E21: =E20+C21-D21 -> 1143.36
A22: 25-6-2025 | B22: PINNACLE INT FAB | C22: 4321 | E22: =E21+C22-D22 -> 5464.36
A23: 26-6-2025 | B23: RECD FROM ARAVALI | C23: 1435801 | E23: =E22+C23-D23 -> 1441265.4
A24: 26-6-2025 | B24: IDEA GROVE WIO | D24: 741241.11 | E24: =E23+C24-D24 -> 700024.25
A25: 26-6-2025 | B25: IDEA GROVE WIO | D25: 690016.31 | E25: =E24+C25-D25 -> 10007.94
A26: 26-6-2025 | B26: VAT PAYMENT | D26: 5456.68 | E26: =E25+C26-D26 -> 4551.26
A27: 28-6-2025 | B27: HEDGES NBF | C27: 69457 | E27: =E26+C27-D27 -> 74008.26
A28: 45664 | B28: AGNICO MSQ | C28: 199994.12 | E28: =E27+C28-D28 -> 274002.38
A29: 45664 | B29: BINARY 00003 | D29: 3727.5 | E29: =E28+C29-D29 -> 270274.88
A30: 45664 | B30: CHARGES | D30: 1521.08 | E30: =E29+C30-D30 -> 268753.8
A31: 45754 | B31: TT RECEIVED FROM ARAVALI FENCE | C31: 1027720 | E31: =E30+C31-D31 -> 1296473.8
A32: 45754 | B32: TT TRANSFER TO AGNIRA WIO A/C | D32: 741111.24 | E32: =E31+C32-D32 -> 555362.56
A33: 45754 | B33: TT TRANSFER TO BLACKPEPPER GENERAL NBF | D33: 500241.11 | E33: =E32+C33-D33 -> 55121.45
A34: 45907 | B34: TT TRANSFER TO IDEA GROVE WIO A/C | D34: 50124 | E34: =E33+C34-D34 -> 4997.45
E35: =E34+C35-D35 -> 4997.45
E36: =E35+C36-D36 -> 4997.45
E37: =E36+C37-D37 -> 4997.45
E38: =E37+C38-D38 -> 4997.45
E39: =E38+C39-D39 -> 4997.45
E40: =E39+C40-D40 -> 4997.45
E41: =E40+C41-D41 -> 4997.45
E42: =E41+C42-D42 -> 4997.45
E43: =E42+C43-D43 -> 4997.45
E44: =E43+C44-D44 -> 4997.45
E45: =E44+C45-D45 -> 4997.45
E46: =E45+C46-D46 -> 4997.45
... E177: =E176+C177-D177 -> 4997.45

Sheet QUANTUM ADIB AED
A1: QUANTUM QUEST GENERAL
A2: BANK ADIB ACC .NO -
A3: DATE | B3: PARTICULAR | C3: DEPOSIT | D3: WITHDRAWAL | E3: BALANCE
E4: 0
A5: 45734 | B5: recd from HEDGES ADIB | C5: 5412 | E5: =E4+C5-D5 -> 5412 | J5: 74.32
E6: =E5+C6-D6 -> 5412
E7: =E6+C7-D7 -> 5412
E8: =E7+C8-D8 -> 5412 | H8: 157.5
E9: =E8+C9-D9 -> 5412
E10: =E9+C10-D10 -> 5412
E11: =E10+C11-D11 -> 5412
E12: =E11+C12-D12 -> 5412
E13: =E12+C13-D13 -> 5412
E14: =E13+C14-D14 -> 5412
E15: =E14+C15-D15 -> 5412
E16: =E15+C16-D16 -> 5412
E17: =E16+C17-D17 -> 5412
E18: =E17+C18-D18 -> 5412
E19: =E18+C19-D19 -> 5412
E20: =E19+C20-D20 -> 5412
... E100: =E99+C100-D100 -> 5412

Sheet PINNACLE NBF USD
A1: PINNACLE GROUPS FZ LLC
A2: BANK NBF ACC .NO -
A3: DATE | B3: PARTICULAR | C3: DEPOSIT | D3: WITHDRAWAL | E3: BALANCE
E4: 0
A5: 45409 | B5: recd from royal nbf | C5: 7450 | E5: =E4+C5-D5 -> 7450 | J5: 74.32
A6: 45409 | B6: CHARGES | D6: 97.2 | E6: =E5+C6-D6 -> 7352.8
A7: 45412 | B7: TRF TO COMIDA ADIB USD | D7: 7310 | E7: =E6+C7-D7 -> 42.8
A8: 45413 | B8: CHARGES | D8: 42.79 | E8: =E7+C8-D8 -> 0.01 | H8: 157.5
A9: 45414 | B9: RECD FROM ROYAL NBF USD | C9: 150 | E9: =E8+C9-D9 -> 150.01
A10: 45414 | B10: CHARGES | D10: =36.84+1.84+15 -> 53.68 | E10: =E9+C10-D10 -> 96.33
A11: 45422 | B11: refund | C11: 7310 | E11: =E10+C11-D11 -> 7406.33
A12: 45439 | B12: TRF TO BLUE FIRE NBF | D12: 7315 | E12: =E11+C12-D12 -> 91.33
D13: 74.32 | E13: =E12+C13-D13 -> 17.01
D14: 2.86 | E14: =E13+C14-D14 -> 14.15
D15: 14.14 | E15: =E14+C15-D15 -> 0.01
A16: 45772 | B16: AED | C16: 68 | E16: =E15+C16-D16 -> 68.01
A17: 45776 | B17: CHARGES | D17: 68 | E17: =E16+C17-D17 -> 0.01
A18: 45776 | B18: RECD FROM QUICK TOUCH | C18: 489986.5 | E18: =E17+C18-D18 -> 489986.51
A19: 45776 | B19: CHARGES | D19: =5.45+0.27 -> 5.72 | E19: =E18+C19-D19 -> 489980.79
A20: 45776 | B20: TT TRANSFER TO CENTURY CITI USD 480,124 | D20: 480124 | E20: =E19+C20-D20 -> 9856.79
A21: 45777 | B21: TT TRANSFER OPTICORE USD A/C ADIB A/C | D21: 1225 | E21: =E20+C21-D21 -> 8631.79
A22: 45777 | B22: CHARGES | D22: 665.32 | E22: =E21+C22-D22 -> 7966.47
A23: 45778 | B23: usd to aed | D23: 7800 | E23: =E22+C23-D23 -> 166.47
E24: =E23+C24-D24 -> 166.47
E25: =E24+C25-D25 -> 166.47
E26: =E25+C26-D26 -> 166.47
E27: =E26+C27-D27 -> 166.47
E28: =E27+C28-D28 -> 166.47
E29: =E28+C29-D29 -> 166.47
E30: =E29+C30-D30 -> 166.47
E31: =E30+C31-D31 -> 166.47
E32: =E31+C32-D32 -> 166.47
E33: =E32+C33-D33 -> 166.47
E34: =E33+C34-D34 -> 166.47
E35: =E34+C35-D35 -> 166.47
... E100: =E99+C100-D100 -> 166.47

Sheet CARNIFY EIB AED
A1: CARNIFY INTERNATIONAL A/C
A2: EIB AED ACC .NO -
A3: DATE | B3: PARTICULAR | C3: DEPOSIT | D3: WITHDRAWAL | E3: BALANCE
A4: 26-07-2025 | B4: FUND RECD FROM GLOBAL NEXUS TRADING | C4: 499890 | E4: =C4 -> 499890
A5: 26-07-2025 | B5: FUND RECD FROM GLOBAL NEXUS TRADING | C5: 499790 | E5: =E4+C5-D5 -> 999680
A6: 26-07-2025 | B6: TT TRF AMINEX GENERAL TRADING LLC | D6: 541251 | E6: =E5+C6-D6 -> 458429
A7: 26-07-2025 | B7: BANK CHARGES | D7: 11.55 | E7: =E6+C7-D7 -> 458417.45
A8: 26-07-2025 | B8: TT TRF TO BLACK PEPPER GT AED | D8: 421400 | E8: =E7+C8-D8 -> 37017.45
A9: 26-07-2025 | B9: BANK CHARGES | D9: 11.55 | E9: =E8+C9-D9 -> 37005.9
A10: 26-07-2025 | B10: FUND RECD FROM INEXCO INT DMCC AED | C10: 1000340 | E10: =E9+C10-D10 -> 1037345.9
A11: 26-07-2025 | B11: TT TRF TO BULLFROG TRADING AED | D11: 445124 | E11: =E10+C11-D11 -> 592221.9
A12: 26-07-2025 | B12: BANK CHARGES | D12: 11.55 | E12: =E11+C12-D12 -> 592210.35
A13: 30-07-2025 | B13: TT TRF TO BLACK PEPPER GT AED | D13: 590124 | E13: =E12+C13-D13 -> 2086.35
A14: 30-07-2025 | B14: FUND RECD FROM GLOBAL NEXUS TRADING | C14: 499990 | E14: =E13+C14-D14 -> 502076.35
A15: 30-07-2025 | B15: FUND RECD FROM GLOBAL NEXUS TRADING | C15: 499980 | E15: =E14+C15-D15 -> 1002056.3
A16: 30-07-2025 | B16: FUND RECD FROM GLOBAL NEXUS TRADING | C16: 1000030 | E16: =E15+C16-D16 -> 2002086.4
A17: 31-07-2025 | B17: TT TRF TO BLACK PEPPER GT AED | D17: 612454 | E17: =E16+C17-D17 -> 1389632.4
A18: 31-07-2025 | B18: BANK CHARGES | D18: 11.55 | E18: =E17+C18-D18 -> 1389620.8
A19: 31-07-2025 | B19: TT TRF TO AMINEX GENERAL TRADING AED | D19: 455820 | E19: =E18+C19-D19 -> 933800.8
A20: 31-07-2025 | B20: BANK CHARGES | D20: 11.55 | E20: =E19+C20-D20 -> 933789.25
A21: 31-07-2025 | B21: TT TRF TO AMINEX GENERAL TRADING AED | D21: 425515 | E21: =E20+C21-D21 -> 508274.25
A22: 31-07-2025 | B22: BANK CHARGES | D22: 11.55 | E22: =E21+C22-D22 -> 508262.7
A23: 31-07-2025 | B23: TT TRF TO BLACK PEPPER GT AED | D23: 249850 | E23: =E22+C23-D23 -> 258412.7
A24: 31-07-2025 | B24: BANK CHARGES | D24: 11.55 | E24: =E23+C24-D24 -> 258401.15
A25: 31-07-2025 | B25: TT TRF TO BLACK PEPPER GT AED | D25: 253970 | E25: =E24+C25-D25 -> 4431.15
A26: 31-07-2025 | B26: BANK CHARGES | D26: 11.55 | E26: =E25+C26-D26 -> 4419.6
A27: 45665 | B27: FUND RECD FROM GLOBAL NEXUS TRADING | C27: 987890 | E27: =E26+C27-D27 -> 992309.6
A28: 45665 | B28: FUND RECD FROM GLOBAL NEXUS TRADING | C28: 1012110 | E28: =E27+C28-D28 -> 2004419.6
A29: 45665 | B29: BANK CHARGES | D29: 11.55 | E29: =E28+C29-D29 -> 2004408.1
A30: 45665 | B30: TT TRF TO BLACK PEPPER GT AED | D30: 498990 | E30: =E29+C30-D30 -> 1505418.1
A31: 45665 | B31: TT TRF TO BLACK PEPPER GT AED | D31: 499890 | E31: =E30+C31-D31 -> 1005528.1
A32: 45665 | B32: BANK CHARGES | D32: 11.55 | E32: =E31+C32-D32 -> 1005516.5
A33: 45665 | B33: TT TRF TO AMINEX GENERAL TRADING AED | D33: 750580 | E33: =E32+C33-D33 -> 254936.5
A34: 45665 | B34: BANK CHARGES | D34: 11.55 | E34: =E33+C34-D34 -> 254924.95
A35: 45665 | B35: TT TRF TO BLACK PEPPER GT AED | D35: 251065 | E35: =E34+C35-D35 -> 3859.95
A36: 45665 | B36: BANK CHARGES | D36: 11.55 | E36: =E35+C36-D36 -> 3848.4
A37: 45816 | B37: FUND RECD FROM ADITYA TRIVEDI WIO | C37: 125000 | E37: =E36+C37-D37 -> 128848.4
A38: 45816 | B38: TT TRF TO AMINEX ADIB AED | D38: 126518 | E38: =E37+C38-D38 -> 2330.4
A39: 45816 | B39: BANK CHARGES | D39: 11.55 | E39: =E38+C39-D39 -> 2318.85
A40: 13.08.2025 | B40: TT TRF TO CARNIFY ENBD AED | D40: 1000 | E40: =E39+C40-D40 -> 1318.85
A41: 13.08.2025 | B41: CASH DEPOSIT | C41: 121000 | E41: =E40+C41-D41 -> 122318.85
A42: 13.08.2025 | B42: TT TRF TO ADITYA TRIVEDI RUYA BANK | D42: 20521 | E42: =E41+C42-D42 -> 101797.85
A43: 13.08.2025 | B43: TT TRF TO CARNIFY ENBD AED | D43: 99000 | E43: =E42+C43-D43 -> 2797.85
A44: 02.09.2025 | B44: BANK CHARGES | D44: =425+21.25 -> 446.25 | E44: =E43+C44-D44 -> 2351.6
A45: 16.09.2025 | B45: CASH DEPOSIT | C45: 250000 | E45: =E44+C45-D45 -> 252351.6
A46: 16.09.2025 | B46: TT TRF TO BLACK PEPPER GT AED | D46: 251630 | E46: =E45+C46-D46 -> 721.6
A47: 16.09.2025 | B47: BANK CHARGES | D47: 11.55 | E47: =E46+C47-D47 -> 710.05
A48: 25.09.2025 | B48: CASH DEPOSIT | C48: 240000 | E48: =E47+C48-D48 -> 240710.05
A49: 25.09.2025 | B49: TT TRF TO BLACK PEPPER GT ADIB AED | D49: 238620 | E49: =E48+C49-D49 -> 2090.05
A50: 25.09.2025 | B50: BANK CHARGES | D50: 11.55 | E50: =E49+C50-D50 -> 2078.5
A51: 29.09.2025 | B51: CASH DEPOSIT | C51: 100000 | E51: =E50+C51-D51 -> 102078.5
A52: 29.09.2025 | B52: CASH DEPOSIT | C52: 99000 | E52: =E51+C52-D52 -> 201078.5
A53: 29.09.2025 | B53: CASH DEPOSIT | C53: 131500 | E53: =E52+C53-D53 -> 332578.5
A54: 29.09.2025 | B54: TT TRF TO BLACK PEPPER GT ADIB AED | D54: 331560 | E54: =E53+C54-D54 -> 1018.5
A55: 29.09.2025 | B55: BANK CHARGES | D55: 11.55 | E55: =E54+C55-D55 -> 1006.95
A56: 30.09.2025 | B56: CASH DEPOSIT | C56: 199000 | E56: =E55+C56-D56 -> 200006.95
A57: 30.09.2025 | B57: TT TRF TO BLACK PEPPER GT NBF AED | D57: 198964 | E57: =E56+C57-D57 -> 1042.95
A58: 30.09.2025 | B58: BANK CHARGES | D58: 11.55 | E58: =E57+C58-D58 -> 1031.4
A59: 17.10.2025 | B59: CASH DEPOSIT | C59: 200000 | E59: =E58+C59-D59 -> 201031.4
A60: 17.10.2025 | B60: TT TRF TO BLACK PEPPER GT NBF AED | D60: 198675 | E60: =E59+C60-D60 -> 2356.4
A61: 17.10.2025 | B61: BANK CHARGES | D61: 11.55 | E61: =E60+C61-D61 -> 2344.85
A62: 28.10.2025 | B62: CASH DEPOSIT | C62: 90000 | E62: =E61+C62-D62 -> 92344.85
A63: 28.10.2025 | B63: CASH DEPOSIT | C63: 135000 | E63: =E62+C63-D63 -> 227344.85
A64: 28.10.2025 | B64: TT TRF TO BLACK PEPPER GT NBF AED | D64: 225361 | E64: =E63+C64-D64 -> 1983.85
A65: 28.10.2025 | B65: BANK CHARGES | D65: 11.55 | E65: =E64+C65-D65 -> 1972.3
A66: 02.10.2025 | B66: BANK CHARGES | D66: 425 | E66: =E65+C66-D66 -> 1547.3
A67: 02.10.2025 | B67: BANK CHARGES | D67: 21.25 | E67: =E66+C67-D67 -> 1526.05
A68: 04.11.2025 | B68: BANK CHARGES | D68: 425 | E68: =E67+C68-D68 -> 1101.05
A69: 04.11.2025 | B69: BANK CHARGES | D69: 21.25 | E69: =E68+C69-D69 -> 1079.8
A70: 06.11.2025 | B70: FUND RECD FROM ADITYA TRIVEDI | C70: 80000 | E70: =E69+C70-D70 -> 81079.8
A71: 06.11.2025 | B71: TT TRF TO BLACK PEPPER GT NBF AED | D71: 79968 | E71: =E70+C71-D71 -> 1111.8
A72: 06.11.2025 | B72: BANK CHARGES | D72: 11.55 | E72: =E71+C72-D72 -> 1100.25
A73: 11.11.2025 | B73: FUND RECD FROM PINNACLE INT FAB | C73: 6894 | E73: =E72+C73-D73 -> 7994.25
A74: 11.11.2025 | B74: FTA TAX PAYMENT | D74: 6688.5 | E74: =E73+C74-D74 -> 1305.75
A75: 17.12.2025 | B75: CASH DEPOSIT | C75: 300000 | E75: =E74+C75-D75 -> 301305.75
A76: 17.12.2025 | B76: FUND RECD FROM ROYAL ENBD | C76: 340537 | E76: =E75+C76-D76 -> 641842.75 | G76: 71722.64
A77: 17.12.2025 | B77: TT TRF TO CLARK SMIHT (USD 173347.78) | D77: 640000 | E77: =E76+C77-D77 -> 1842.75 | G77: 173347.78
A78: 17.12.2025 | B78: FUND RECD FROM ROYAL ENBD | C78: 999968 | E78: =E77+C78-D78 -> 1001810.8 | G78: 270855.9
A79: 17.12.2025 | B79: TT TRF TO CLARK SMIHT (USD 270855.90) | D79: 1000000 | E79: =E78+C79-D79 -> 1810.75 | G79: 486998.92 | I79: 1400000
A80: 17.12.2025 | B80: BANK CHARGES | D80: 425 | E80: =E79+C80-D80 -> 1385.75 | G80: 397074.76
A81: 17.12.2025 | B81: BANK CHARGES | D81: 21.25 | E81: =E80+C81-D81 -> 1364.5 | G81: =SUM(G76:G80) -> 1400000 | I81: =+I79-G81 -> 0 | J81: =+I81*3.69 -> 0
A82: 17.12.2025 | B82: BANK CHARGES | D82: 10.5 | E82: =E81+C82-D82 -> 1354
A83: 17.12.2025 | B83: FUND RECD FROM ROYAL ENBD | C83: 950348 | E83: =E82+C83-D83 -> 951702
A84: 17.12.2025 | B84: FUND RECD FROM ROYAL ENBD | C84: 1034058 | E84: =E83+C84-D84 -> 1985760
A85: 17.12.2025 | B85: TT TRF TO CLARK SMIHT (USD 486998.92) | D85: 1798000 | E85: =E84+C85-D85 -> 187760
A86: 17.12.2025 | B86: FUND RECD FROM CARNIFY ENBD AED | C86: 1280169 | E86: =E85+C86-D86 -> 1467929
A87: 17.12.2025 | B87: TT TRF TO CLARK SMIHT (USD 397074.76) | D87: 1466000 | E87: =E86+C87-D87 -> 1929
A88: 17.12.2025 | B88: CASH DEPOSIT | C88: 200000 | E88: =E87+C88-D88 -> 201929
A89: 17.12.2025 | B89: FUND RECD FROM ROYAL ENBD | C89: 64002 | E89: =E88+C89-D89 -> 265931
A90: 17.12.2025 | B90: TT TRF TO CLARK SMIHT (USD 71722.64) | D90: 264799.99 | E90: =E89+C90-D90 -> 1131.01
A91: 19.12.2025 | B91: FUND RECD FROM ADITYA TRIVEDI | C91: 49000 | E91: =E90+C91-D91 -> 50131.01
A92: 19.12.2025 | B92: FUND RECD FROM ADITYA TRIVEDI | C92: 37621 | E92: =E91+C92-D92 -> 87752.01
A93: 19.12.2025 | B93: FUND RECD FROM ADITYA TRIVEDI | C93: 49000 | E93: =E92+C93-D93 -> 136752.01
A94: 19.12.2025 | B94: TT TRF TO BLACK PEPPER GT NBF AED | D94: 136021 | E94: =E93+C94-D94 -> 731.01
A95: 19.12.2025 | B95: BANK CHARGES | D95: 11.55 | E95: =E94+C95-D95 -> 719.46
A96: 13.01.2026 | B96: CASH DEPOSIT | C96: 70000 | E96: =E95+C96-D96 -> 70719.46
A97: 13.01.2026 | B97: TT TRF TO ADITYA TRIVEDI WIO BANK | D97: 70000 | E97: =E96+C97-D97 -> 719.46
A98: 14.01.2026 | B98: FUND RECD FROM ROYAL ENBD | C98: 496993 | E98: =E97+C98-D98 -> 497712.46
A99: 14.01.2026 | B99: TT TRF TO ADITYA TRIVEDI RUYA BANK | D99: 198000 | E99: =E98+C99-D99 -> 299712.46
A100: 14.01.2026 | B100: TT TRF TO ADITYA TRIVEDI WIO BANK | D100: 150000 | E100: =E99+C100-D100 -> 149712.46
...

Sheet PINNACLE WIO AED
A1: PINNACLE GROUPS FZ LLC
A2: BANK WIO AED ACC .NO -
A3: DATE | B3: PARTICULAR | C3: DEPOSIT | D3: WITHDRAWAL | E3: BALANCE
B4: OPENING BLC | E4: 557.58
A5: 22-11-2023 | B5: CASH DEPOSIT | C5: 99500 | E5: =E4+C5-D5 -> 100057.58
A6: 22-11-2023 | B6: ADITYA TRAVEDI | D6: 79400 | E6: =E5+C6-D6 -> 20657.58 | H6: 367000
A7: 23-11-2023 | B7: CASH DEPOSIT | C7: 590000 | E7: =E6+C7-D7 -> 610657.58
A8: 23-11-2023 | B8: TRF PINNACLE INT WIO AED | D8: 200000 | E8: =E7+C8-D8 -> 410657.58
A9: 23-11-2023 | B9: TRF WISOR WIO AED | D9: 402850 | E9: =E8+C9-D9 -> 7807.58
A10: 25-11-2023 | B10: CASH DEPOSIT | C10: 299500 | E10: =E9+C10-D10 -> 307307.58
A11: 25-11-2023 | B11: RECD RHINE WIO AED | C11: 199860 | E11: =E10+C11-D11 -> 507167.58
A12: 25-11-2023 | B12: TRF NATURE GLOBAL HOLDING FZ LLC | D12: 500000 | E12: =E11+C12-D12 -> 7167.58
A13: 27-11-2023 | B13: CHARGES | D13: 99 | E13: =E12+C13-D13 -> 7068.58
A14: 28-11-2023 | B14: RECD COMIDA WIO AED | C14: 304122 | E14: =E13+C14-D14 -> 311190.58
A15: 28-11-2023 | B15: TRF NATURE GLOBAL HOLDING FZ LLC | D15: 310000 | E15: =E14+C15-D15 -> 1190.58
A16: 44938 | B16: RECD ROYAL WIO AED | C16: 378578 | E16: =E15+C16-D16 -> 379768.58
A17: 44938 | B17: TRF ADTIYA | D17: 350000 | E17: =E16+C17-D17 -> 29768.58
A18: 44938 | B18: TRF PINNACLE INT WIO AED | D18: 29000 | E18: =E17+C18-D18 -> 768.58
A19: 45119 | B19: CASH DEPOSIT | C19: 118000 | E19: =E18+C19-D19 -> 118768.58
A20: 45119 | B20: TRF ADTIYA | D20: 118000 | E20: =E19+C20-D20 -> 768.58
A21: 45272 | B21: CASH DEPOSIT | C21: 558000 | E21: =E20+C21-D21 -> 558768.58
A22: 45272 | B22: COMIDA WIO AED | D22: 558265 | E22: =E21+C22-D22 -> 503.58
A23: 45272 | B23: CASH DEPOSIT | C23: 55000 | E23: =E22+C23-D23 -> 55503.58
A24: 45272 | B24: TRF ADTIYA | D24: 55000 | E24: =E23+C24-D24 -> 503.58
A25: 15-12-2023 | B25: CASH DEPOSIT | C25: 200000 | E25: =E24+C25-D25 -> 200503.58
A26: 15-12-2023 | B26: CASH DEPOSIT | C26: 492000 | E26: =E25+C26-D26 -> 692503.58
A27: 15-12-2023 | B27: COMIDA WIO AED | D27: 692024 | E27: =E26+C27-D27 -> 479.58
A28: 18-12-2023 | B28: CASH DEPOSIT | C28: 610400 | E28: =E27+C28-D28 -> 610879.58
A29: 18-12-2023 | B29: TRF HEDGES WIO AED | D29: 561025 | E29: =E28+C29-D29 -> 49854.58
A30: 18-12-2023 | B30: TRF HEDGES WIO AED | D30: 49420 | E30: =E29+C30-D30 -> 434.58
A31: 18-12-2023 | B31: CASH DEPOSIT | C31: 1900 | E31: =E30+C31-D31 -> 2334.58
A32: 45279 | B32: Etisalt Pinnacle groups | D32: 1807.9 | E32: =E31+C32-D32 -> 526.68
A33: 45280 | B33: CASH DEPOSIT | C33: 314600 | E33: =E32+C33-D33 -> 315126.68
A34: 45280 | B34: TRF HEDGES WIO AED | D34: 314440 | E34: =E33+C34-D34 -> 686.68
A35: 45281 | B35: RECD HEDGES WIO AED | C35: 29995 | E35: =E34+C35-D35 -> 30681.68
A36: 45281 | B36: TRF ADTIYA | D36: 30000 | E36: =E35+C36-D36 -> 681.68 | H36: 313.95
A37: 45281 | B37: RECD HEDGES WIO AED | C37: 1778921 | E37: =E36+C37-D37 -> 1779602.7
A38: 45281 | B38: CONCVERT AED TO USD WIO | D38: 1776600.7 | E38: =E37+C38-D38 -> 3001.96
A39: 45282 | B39: MOB RECHARGE | C39: 50 | E39: =E38+C39-D39 -> 3051.96
A40: 45286 | B40: RECD USD TO AED | C40: 29996.16 | E40: =E39+C40-D40 -> 33048.12
A41: 45286 | B41: CHARGES | D41: 99 | E41: =E40+C41-D41 -> 32949.12
A42: 45286 | B42: TRF ADITYA | D42: 30000 | E42: =E41+C42-D42 -> 2949.12
A43: 45286 | B43: TRF ADITYA | D43: 100 | E43: =E42+C43-D43 -> 2849.12
A44: 45286 | B44: PINNACLE DU LANDLINE | D44: 420.88 | E44: =E43+C44-D44 -> 2428.24
A45: 45287 | B45: RECD HEDGES AL MASRAF AED | C45: 281250 | E45: =E44+C45-D45 -> 283678.24
A46: 45287 | B46: TRF MARYAM WIO | D46: 23700 | E46: =E45+C46-D46 -> 259978.24
A47: 45287 | B47: TRF COMIDA WIO AED | D47: 258064 | E47: =E46+C47-D47 -> 1914.24
A48: 45297 | B48: recd from DEWA | C48: 1148.07 | E48: =E47+C48-D48 -> 3062.31
A49: 45304 | B49: TRF VAT PMNT | D49: 1094.22 | E49: =E48+C49-D49 -> 1968.09
A50: 45311 | B50: RECD HEDGES WIO AED | C50: 1717122 | E50: =E49+C50-D50 -> 1719090.1
A51: 45311 | B51: TRF TO NIYAT GOODS SIB USD 467465 | D51: 1716998.9 | E51: =E50+C51-D51 -> 2091.14
A52: 45311 | B52: CHARGES | D52: 115.5 | E52: =E51+C52-D52 -> 1975.64
A53: 45313 | B53: RECD FRM RHINE WIO AED | C53: 102995 | E53: =E52+C53-D53 -> 104970.64
A54: 45313 | B54: RECD RHINE WIO AED | C54: 490314 | E54: =E53+C54-D54 -> 595284.64
A55: 45313 | B55: RECD HEDGES WIO AED | C55: 717432 | E55: =E54+C55-D55 -> 1312716.6
A56: 45313 | B56: NIYAT SIB | D56: 1312002.9 | E56: =E55+C56-D56 -> 713.69
A57: 45313 | B57: CHARGES | D57: 115.5 | E57: =E56+C57-D57 -> 598.19
A58: 45313 | B58: RECD RHINE WIO AED | C58: 30122 | E58: =E57+C58-D58 -> 30720.19
A59: 45313 | B59: TRF TO NIYAT SIB AED | D59: 29989 | E59: =E58+C59-D59 -> 731.19
A60: 45318 | B60: charges | D60: 99 | E60: =E59+C60-D60 -> 632.19
A61: 45322 | B61: RECD HEDGES WIO AED | C61: 2448 | E61: =E60+C61-D61 -> 3080.19
A62: 45322 | B62: TRF COMIDA WIO AED | D62: 2698 | E62: =E61+C62-D62 -> 382.19
A63: 45327 | B63: RECD HEDGES WIO AED | C63: 367358 | E63: =E62+C63-D63 -> 367740.19
A64: 45327 | B64: TRF TO ADITYA TRIVEDI WIO | D64: 367150 | E64: =E63+C64-D64 -> 590.19
A65: 45328 | B65: RECD HEDGES WIO AED | C65: 50437 | E65: =E64+C65-D65 -> 51027.19
A66: 45328 | B66: TRF TO ADITYA TRIVEDI WIO | D66: 50738 | E66: =E65+C66-D66 -> 289.19
A67: 45329 | B67: RECD HEDGES FAB | C67: 149417 | E67: =E66+C67-D67 -> 149706.19
A68: 45329 | B68: TRF TO ADITYA TRIVEDI WIO | D68: 149310 | E68: =E67+C68-D68 -> 396.19
B69: recd Aditya | C69: 80000 | E69: =E68+C69-D69 -> 80396.19
D70: 79986 | E70: =E69+C70-D70 -> 410.19
A71: 45337 | B71: recd from pinnacle nbf | C71: 44600 | E71: =E70+C71-D71 -> 45010.19
A72: 45337 | B72: trf to saorsa technocrat INR 1,000,000 | D72: 44456.5 | E72: =E71+C72-D72 -> 553.69
A73: 45337 | B73: RECD FROM ASHISH JI | C73: 50000 | E73: =E72+C73-D73 -> 50553.69
A74: 45337 | B74: TRF TO PINNACLE GR MSQ | D74: 50100 | E74: =E73+C74-D74 -> 453.69
A75: 45338 | B75: RECD PINNACLE MSQ | C75: 20200 | E75: =E74+C75-D75 -> 20653.69
A76: 45338 | B76: RECD PINNACLE MSQ | C76: 26530 | E76: =E75+C76-D76 -> 47183.69
A77: 45338 | B77: RECD PINNACLE ADIB | C77: 65100 | E77: =E76+C77-D77 -> 112283.69
A78: 45338 | B78: RECD HEDGES WIO AED | C78: 277103 | E78: =E77+C78-D78 -> 389386.69
A79: 45338 | B79: TRF TO ADITYA TRIVEDI WIO | D79: 367000 | E79: =E78+C79-D79 -> 22386.69
A80: 45338 | B80: TRF SHAMS AL SABAH MKTG CBD | D80: 20180 | E80: =E79+C80-D80 -> 2206.69
A81: 45342 | B81: RECD PG NBF | C81: 103300 | E81: =E80+C81-D81 -> 105506.69
A82: 45342 | B82: RECD PG ADIB | C82: 87200 | E82: =E81+C82-D82 -> 192706.69
A83: 45342 | B83: RECD WSJ TRADING | C83: 175132 | E83: =E82+C83-D83 -> 367838.69
A84: 45342 | B84: TRF TO ADITYA TRIVEDI WIO | D84: 367000 | E84: =E83+C84-D84 -> 838.69
A85: 45348 | B85: CHARGES | D85: 99 | E85: =E84+C85-D85 -> 739.69
A86: 45348 | B86: RECD FROM PRIME TRADE FINANCE | C86: 15000 | E86: =E85+C86-D86 -> 15739.69
A87: 45348 | B87: TRF TO PINNACLE HOLDING WIO | D87: 1010 | E87: =E86+C87-D87 -> 14729.69
A88: 45348 | B88: TRF TO PINNACLE GR NBF | D88: 14450 | E88: =E87+C88-D88 -> 279.69
A89: 45350 | B89: recd from pinnacle group adib | C89: 249500 | E89: =E88+C89-D89 -> 249779.69
A90: 45350 | B90: recd from pinnacle group adib | C90: 530050 | E90: =E89+C90-D90 -> 779829.69
A91: 45350 | B91: TRF TO MARYAM JAVED SCB | D91: 200550 | E91: =E90+C91-D91 -> 579279.69
A92: 45350 | B92: TRF TO CENTURY EXP | D92: 579178.11 | E92: =E91+C92-D92 -> 101.58
A93: 45350 | B93: CHARGES | D93: 52.5 | E93: =E92+C93-D93 -> 49.08
A94: 45350 | B94: RECD PINNACLE GR ADIB | C94: 782700 | E94: =E93+C94-D94 -> 782749.08
A95: 45350 | B95: TRF TO CENTURY EXP USD 213000 | D95: 782295.01 | E95: =E94+C95-D95 -> 454.07
A96: 45350 | B96: CHARGES | D96: 52.5 | E96: =E95+C96-D96 -> 401.57
A97: 45353 | B97: recd fro pg ADIB | C97: 499995 | E97: =E96+C97-D97 -> 500396.57
A98: 45353 | B98: recd fro pg ADIB | C98: 499980 | E98: =E97+C98-D98 -> 1000376.6
A99: 45353 | B99: trf to century exports | D99: 930316.91 | E99: =E98+C99-D99 -> 70059.66
A100: 45353 | B100: trf to lrg steel | D100: 69622.82 | E100: =E99+C100-D100 -> 436.84
...

Sheet PINNACLE WIO USD
A1: PINNACLE GROUPS FZ LLC
A2: BANK WIO USD ACC .NO -
A3: DATE | B3: PARTICULAR | C3: DEPOSIT | D3: WITHDRAWAL | E3: BALANCE
E4: 0
A5: 45281 | B5: CONVERTED FROM AED WIO | C5: 483692 | E5: =E4+C5-D5 -> 483692
A6: 45281 | B6: SENT TO WHITE INK INDIA BOB 1185 | D6: 196055.45 | E6: =E5+C6-D6 -> 287636.55
A7: 45282 | B7: SENT TO WHITE INK INDIA BOB 1185 | D7: 204150 | E7: =E6+C7-D7 -> 83486.55
A8: 45282 | B8: CHARGES | D8: 14.7 | E8: =E7+C8-D8 -> 83471.85
A9: 45286 | B9: USD TO AED | D9: 8170 | E9: =E8+C9-D9 -> 75301.85
A10: 45286 | B10: TRFD COMIDA WIO USD | D10: 75250 | E10: =E9+C10-D10 -> 51.85
A11: 45286 | B11: CHARGES | D11: 30.45 | E11: =E10+C11-D11 -> 21.4
D12: 21.4 | E12: =E11+C12-D12 -> -8.7290175e-12
E13: =E12+C13-D13 -> -8.7290175e-12
E14: =E13+C14-D14 -> -8.7290175e-12
E15: =E14+C15-D15 -> -8.7290175e-12
E16: =E15+C16-D16 -> -8.7290175e-12
E17: =E16+C17-D17 -> -8.7290175e-12
E18: =E17+C18-D18 -> -8.7290175e-12
E19: =E18+C19-D19 -> -8.7290175e-12
E20: =E19+C20-D20 -> -8.7290175e-12
E21: =E20+C21-D21 -> -8.7290175e-12
E22: =E21+C22-D22 -> -8.7290175e-12
E23: =E22+C23-D23 -> -8.7290175e-12
E24: =E23+C24-D24 -> -8.7290175e-12
... E100: =E99+C100-D100 -> -8.7290175e-12

Sheet PINNACLE ADIB AED  
A1: PINNACLE GROUPS FZ LLC
A2: BANK ADIB AED ACC .NO -
A3: DATE | B3: PARTICULAR | C3: DEPOSIT | D3: WITHDRAWAL | E3: BALANCE
E4: 0
A5: 05.01.2024 | B5: RECD HEDGES FAB AED | C5: 141279 | E5: =E4+C5-D5 -> 141279
A6: 45297 | B6: charges | D6: 210 | E6: =E5+C6-D6 -> 141069 | H6: 88990.75
A7: 44935 | B7: TRF TO KOTHARI GEN TR | D7: 140122 | E7: =E6+C7-D7 -> 947
A8: 45313 | B8: RECD HEDGES FAB AED | C8: 500894 | E8: =E7+C8-D8 -> 501841
A9: 45313 | B9: RECD RHINE MULTY ADIB | C9: 457324 | E9: =E8+C9-D9 -> 959165
A10: 45313 | B10: TRF TO NIYAT SIB AED | D10: 457236 | E10: =E9+C10-D10 -> 501929
A11: 45313 | B11: TRF TO NIYAT SIB AED | D11: 378526 | E11: =E10+C11-D11 -> 123403
A12: 45313 | B12: TRF TO NIYAT SIB AED | D12: 122324 | E12: =E11+C12-D12 -> 1079
A13: 45313 | B13: charges | D13: 15.75 | E13: =E12+C13-D13 -> 1063.25
A14: 45313 | B14: charges | D14: 15.75 | E14: =E13+C14-D14 -> 1047.5
A15: 45313 | B15: charges | D15: 15.75 | E15: =E14+C15-D15 -> 1031.75
A16: 45318 | B16: FROM ROYAL ADIB AED | C16: 70235 | E16: =E15+C16-D16 -> 71266.75
A17: 45318 | B17: TRF TO ADITYA WIO | D17: 70000 | E17: =E16+C17-D17 -> 1266.75
A18: 45318 | B18: RECD ROYAL ADIB | C18: 10112 | E18: =E17+C18-D18 -> 11378.75
A19: 45318 | B19: TRF VERSATILE - ALOK | D19: 10000 | E19: =E18+C19-D19 -> 1378.75
A20: 45318 | B20: charges | D20: 84 | E20: =E19+C20-D20 -> 1294.75
B21: stationary | D21: 593.13 | E21: =E20+C21-D21 -> 701.62
C22: 22937 | E22: =E21+C22-D22 -> 23638.62
B23: TRF TO ADITYA WIO | D23: 23000 | E23: =E22+C23-D23 -> 638.62
A24: 45338 | B24: RECD RHINE ADIB | C24: 64995 | E24: =E23+C24-D24 -> 65633.62
A25: 45338 | B25: TRF TO PINNACLE WIO | D25: 65100 | E25: =E24+C25-D25 -> 533.62
A26: 45339 | B26: CHARGES | D26: 15.75 | E26: =E25+C26-D26 -> 517.87
A27: 45342 | B27: RECD PINN INT ADIB | C27: 89650 | E27: =E26+C27-D27 -> 90167.87
A28: 45342 | B28: trf to PG WIO | D28: 87200 | E28: =E27+C28-D28 -> 2967.87
A29: 45342 | B29: charges | D29: 15.75 | E29: =E28+C29-D29 -> 2952.12
A30: 45348 | B30: TRADE LIC EXP CHARGES | D30: 367.5 | E30: =E29+C30-D30 -> 2584.62
A31: 45350 | B31: MONTHLY CHARGES | D31: 52.5 | E31: =E30+C31-D31 -> 2532.12
A32: 45350 | B32: RECD PINNACLE INT ADIB | C32: 249200 | E32: =E31+C32-D32 -> 251732.12
A33: 45350 | B33: trf to pinncale grp wio | D33: 249500 | E33: =E32+C33-D33 -> 2232.12
A34: 45350 | B34: RECD FROM RHINE ENBD | C34: 528012 | E34: =E33+C34-D34 -> 530244.12
A35: 45350 | B35: RECD ROYAL FAB | C35: 783952 | E35: =E34+C35-D35 -> 1314196.1
A36: 45350 | B36: trf to PG WIO | D36: 530050 | E36: =E35+C36-D36 -> 784146.12
A37: 45350 | B37: charges | D37: 15.75 | E37: =E36+C37-D37 -> 784130.37
A38: 45350 | B38: trf to PG WIO | D38: 782700 | E38: =E37+C38-D38 -> 1430.37
A39: 45350 | B39: charges | D39: 15.75 | E39: =E38+C39-D39 -> 1414.62
A40: 45350 | B40: charges | D40: 15.75 | E40: =E39+C40-D40 -> 1398.87
A41: 45353 | B41: RECD RHINE ADIB | C41: 499995 | E41: =E40+C41-D41 -> 501393.87
A42: 45353 | B42: RECD RHINE ADIB | C42: 499998 | E42: =E41+C42-D42 -> 1001391.9
A43: 45353 | B43: trf to PG WIO | D43: 499980 | E43: =E42+C43-D43 -> 501411.87
A44: 45353 | B44: trf to PG WIO | D44: 499995 | E44: =E43+C44-D44 -> 1416.87
A45: 45353 | B45: charges | D45: 15.75 | E45: =E44+C45-D45 -> 1401.12
A46: 45353 | B46: charges | D46: 15.75 | E46: =E45+C46-D46 -> 1385.37
A47: 45353 | B47: charges | D47: 15.75 | E47: =E46+C47-D47 -> 1369.62
A48: 45355 | B48: RECD FROM RHINE ADIB AED | C48: 485655 | E48: =E47+C48-D48 -> 487024.62
A49: 45355 | B49: RECD FROM RHINE ADIB AED | C49: 404235 | E49: =E48+C49-D49 -> 891259.62
A50: 45355 | B50: TRF TO PINNACLE WIO | D50: 480960 | E50: =E49+C50-D50 -> 410299.62
A51: 45355 | B51: charges | D51: 15.75 | E51: =E50+C51-D51 -> 410283.87
A52: 45355 | B52: TRF TO PINNACLE WIO | D52: 409215 | E52: =E51+C52-D52 -> 1068.87
A53: 45355 | B53: charges | D53: 15.75 | E53: =E52+C53-D53 -> 1053.12
A54: 45369 | B54: recd from hedges adib | C54: 418450 | E54: =E53+C54-D54 -> 419503.12
A55: 45369 | B55: TRF TO ADITYA WIO | D55: 418065 | E55: =E54+C55-D55 -> 1438.12
A56: 45369 | B56: charges | D56: 15.75 | E56: =E55+C56-D56 -> 1422.37
A57: 45372 | B57: RECD FROM RHINE SIB AED | C57: 481125 | E57: =E56+C57-D57 -> 482547.37
A58: 45372 | B58: RECD FROM ROYAL AL MASHRAF AED | C58: 499677 | E58: =E57+C58-D58 -> 982224.37
A59: 45373 | B59: TRF TO GRENEW FZE BOB | D59: 981540 | E59: =E58+C59-D59 -> 684.37
A60: 45373 | B60: charges | D60: 15.75 | E60: =E59+C60-D60 -> 668.62
A61: 45373 | B61: charges | D61: 52.75 | E61: =E60+C61-D61 -> 615.87
A62: 45386 | B62: AMAZON PRIME SUBSCRIPTION | D62: 16 | E62: =E61+C62-D62 -> 599.87
A63: 45409 | B63: charges | D63: 131.25 | E63: =E62+C63-D63 -> 468.62
A64: 45411 | B64: recd from verveston fzco | C64: 478733 | E64: =E63+C64-D64 -> 479201.62
A65: 45411 | B65: TRF TO KOTHARI GEN TR MSQ | D65: 289984.25 | E65: =E64+C65-D65 -> 189217.37 | H65: 305125
A66: 45411 | B66: CHARGES | D66: 15.75 | E66: =E65+C66-D66 -> 189201.62
A67: 45412 | B67: RECD FROM ROYAL AL MASHRAF AED | C67: 501575 | E67: =E66+C67-D67 -> 690776.62
A68: 45412 | B68: RECD FROM ROYAL EN EM NBF | C68: 499855 | E68: =E67+C68-D68 -> 1190631.6
A69: 45412 | B69: recd from hedges NBF | C69: 240135 | E69: =E68+C69-D69 -> 1430766.6
A70: 45412 | B70: TRF TO ADITYA WIO | D70: 665810 | E70: =E69+C70-D70 -> 764956.62
A71: 45412 | B71: TRF TO ADITYA WIO | D71: 734190 | E71: =E70+C71-D71 -> 30766.62
A72: 45412 | B72: TRF TO PINNACLE GR MSQ | D72: 14550 | E72: =E71+C72-D72 -> 16216.62
A73: 45412 | B73: charges | D73: 15.75 | E73: =E72+C73-D73 -> 16200.87
A74: 45412 | B74: charges | D74: 15.75 | E74: =E73+C74-D74 -> 16185.12
A75: 45412 | B75: charges | D75: 15.75 | E75: =E74+C75-D75 -> 16169.37
A76: 45416 | B76: recd from hedges ADIB | C76: 492520 | E76: =E75+C76-D76 -> 508689.37
A77: 45416 | B77: trf to niyat mashreq | D77: 492853 | E77: =E76+C77-D77 -> 15836.37
A78: 45416 | B78: charges | D78: 15.75 | E78: =E77+C78-D78 -> 15820.62
A79: 45418 | B79: RECD FROM RHINE ADIB AED | C79: 43258 | E79: =E78+C79-D79 -> 59078.62
A80: 45418 | B80: TRF TO COMIDA ADIB | D80: 50185 | E80: =E79+C80-D80 -> 8893.62
A81: 45422 | B81: trf to electronic way trading llc MSQ | D81: 630 | E81: =E80+C81-D81 -> 8263.62
A82: 45422 | B82: charges | D82: 15.75 | E82: =E81+C82-D82 -> 8247.87
A83: 45422 | B83: charges | D83: 16 | E83: =E82+C83-D83 -> 8231.87
A84: 45434 | B84: RECD FROM RHINE SIB AED | C84: 7695 | E84: =E83+C84-D84 -> 15926.87
A85: 45434 | B85: TRF TO ENS ENVIRONMENTAL CONSULTANCY | D85: 10500 | E85: =E84+C85-D85 -> 5426.87
A86: 45434 | B86: charges | D86: 15.75 | E86: =E85+C86-D86 -> 5411.12
D87: 131.25 | E87: =E86+C87-D87 -> 5279.87
D88: 16 | E88: =E87+C88-D88 -> 5263.87
A89: 45457 | B89: trf to comida ADIB | D89: 3521 | E89: =E88+C89-D89 -> 1742.87
A90: 45457 | B90: recd from royal ENBD | C90: 790154 | E90: =E89+C90-D90 -> 791896.87
A91: 45457 | B91: TRF TO ADITYA WIO | D91: 789850 | E91: =E90+C91-D91 -> 2046.87
A92: 45457 | B92: charges | D92: 15.75 | E92: =E91+C92-D92 -> 2031.12
A93: 45463 | B93: pmnt to hamriya free zone | D93: 110 | E93: =E92+C93-D93 -> 1921.12
A94: 45465 | B94: dewa pmnt | D94: 511 | E94: =E93+C94-D94 -> 1410.12
A95: 45468 | B95: recd from royal enbd | C95: 122184 | E95: =E94+C95-D95 -> 123594.12
A96: 45468 | B96: recd from royal enbd | C96: 68105 | E96: =E95+C96-D96 -> 191699.12
A97: 45470 | B97: clearing cheque no. 500001 | D97: 190116 | E97: =E96+C97-D97 -> 1583.12
A98: 45471 | B98: charges | D98: 131.25 | E98: =E97+C98-D98 -> 1451.87
A99: 45472 | B99: etisalat | D99: 231 | E99: =E98+C99-D99 -> 1220.87
A100: 45472 | B100: etisalat | D100: 231 | E100: =E99+C100-D100 -> 989.87
...

Sheet PINNACLE ADIB USD 
A1: PINNACLE GROUPS FZ LLC
A2: BANK ADIB USD ACC .NO -
A3: DATE | B3: PARTICULAR | C3: DEPOSIT | D3: WITHDRAWAL | E3: BALANCE
E4: 0
A5: 45546 | B5: recd from quick touch technologies | C5: 499963.46 | E5: =E4+'[1]PINNACLE ADIB USD '!C5-'[1]PINNACLE ADIB USD '!D5 -> 499963.46
A6: 45546 | B6: TRF TO COMIDA ADIB USD | D6: 172955 | E6: =E5+'[1]PINNACLE ADIB USD '!C6-'[1]PINNACLE ADIB USD '!D6 -> 327008.46
A7: 45546 | B7: TRF TO BLUEFIRE ADIB | D7: 26516 | E7: =E6+'[1]PINNACLE ADIB USD '!C7-'[1]PINNACLE ADIB USD '!D7 -> 300492.46
A8: 45546 | B8: TRF TO CENTURY CITI | D8: 290150 | E8: =E7+'[1]PINNACLE ADIB USD '!C8-'[1]PINNACLE ADIB USD '!D8 -> 10342.46
A9: 45547 | B9: TRF TO PINN INT ADIB | D9: 9900 | E9: =E8+'[1]PINNACLE ADIB USD '!C9-'[1]PINNACLE ADIB USD '!D9 -> 442.46
A10: 45547 | B10: CHARGES | D10: =160.55+52.5+52.5+52.5+52.5+21 -> 391.55 | E10: =E9+'[1]PINNACLE ADIB USD '!C10-'[1]PINNACLE ADIB USD '!D10 -> 50.91
A11: 45549 | B11: recd from quick touch technologies | C11: 999963.56 | E11: =E10+'[1]PINNACLE ADIB USD '!C11-'[1]PINNACLE ADIB USD '!D11 -> 1000014.5
A12: 45549 | B12: TRF TO COMIDA ADIB USD | D12: 500834 | E12: =E11+'[1]PINNACLE ADIB USD '!C12-'[1]PINNACLE ADIB USD '!D12 -> 499180.47
A13: 45551 | B13: TRF TO CENTURY IOB | D13: 400150 | E13: =E12+'[1]PINNACLE ADIB USD '!C13-'[1]PINNACLE ADIB USD '!D13 -> 99030.47
A14: 45551 | B14: TRF TO COMIDA ADIB USD | D14: 98950 | E14: =E13+'[1]PINNACLE ADIB USD '!C14-'[1]PINNACLE ADIB USD '!D14 -> 80.47
A15: 45556 | B15: recd from quick touch technologies | C15: 749963.56 | E15: =E14+'[1]PINNACLE ADIB USD '!C15-'[1]PINNACLE ADIB USD '!D15 -> 750044.03
A16: 45556 | B16: RECD FROM BLACK PEPPER GT ADIB | C16: 58193 | E16: =E15+'[1]PINNACLE ADIB USD '!C16-'[1]PINNACLE ADIB USD '!D16 -> 808237.03
A17: 45558 | B17: trf to century IOB | D17: 500150 | E17: =E16+'[1]PINNACLE ADIB USD '!C17-'[1]PINNACLE ADIB USD '!D17 -> 308087.03
A18: 45558 | B18: TRF TO DIVINE IOB | D18: 249850 | E18: =E17+'[1]PINNACLE ADIB USD '!C18-'[1]PINNACLE ADIB USD '!D18 -> 58237.03
A19: 45561 | B19: recd from quick touch technologies | C19: 1999963.6 | E19: =E18+'[1]PINNACLE ADIB USD '!C19-'[1]PINNACLE ADIB USD '!D19 -> 2058200.6
A20: 45561 | B20: TRF TO COMIDA ADIB USD | D20: 1039452 | E20: =E19+'[1]PINNACLE ADIB USD '!C20-'[1]PINNACLE ADIB USD '!D20 -> 1018748.6
A21: 45562 | B21: trf to century iob | D21: 750160 | E21: =E20+'[1]PINNACLE ADIB USD '!C21-'[1]PINNACLE ADIB USD '!D21 -> 268588.59
A22: 45562 | B22: trf to pinn comp | D22: 152500 | E22: =E21+'[1]PINNACLE ADIB USD '!C22-'[1]PINNACLE ADIB USD '!D22 -> 116088.59
A23: 45565 | B23: CHARGES | D23: 160.65 | E23: =E22+'[1]PINNACLE ADIB USD '!C23-'[1]PINNACLE ADIB USD '!D23 -> 115927.94
A24: 45565 | B24: TRF TO COMIDA ADIB USD | D24: 35145 | E24: =E23+'[1]PINNACLE ADIB USD '!C24-'[1]PINNACLE ADIB USD '!D24 -> 80782.94
A25: 45568 | B25: trf to ploutos cimb | D25: 61666 | E25: =E24+'[1]PINNACLE ADIB USD '!C25-'[1]PINNACLE ADIB USD '!D25 -> 19116.94
A26: 45568 | B26: TRF TO COMIDA ADIB USD | D26: 19018 | E26: =E25+'[1]PINNACLE ADIB USD '!C26-'[1]PINNACLE ADIB USD '!D26 -> 98.94
A27: 45574 | B27: recd from quick touch technologies | C27: 999963.56 | E27: =E26+'[1]PINNACLE ADIB USD '!C27-'[1]PINNACLE ADIB USD '!D27 -> 1000062.5
A28: 45574 | B28: TRF TO COMIDA ADIB USD | D28: 799984 | E28: =E27+'[1]PINNACLE ADIB USD '!C28-'[1]PINNACLE ADIB USD '!D28 -> 200078.5
A29: 45575 | B29: recd from quick touch technologies | C29: 499963.56 | E29: =E28+'[1]PINNACLE ADIB USD '!C29-'[1]PINNACLE ADIB USD '!D29 -> 700042.06
A30: 45575 | B30: TRF TO COMIDA ADIB USD | D30: 199421 | E30: =E29+'[1]PINNACLE ADIB USD '!C30-'[1]PINNACLE ADIB USD '!D30 -> 500621.06
A31: 45575 | B31: TRF TO COMIDA ADIB USD | D31: 8474 | E31: =E30+'[1]PINNACLE ADIB USD '!C31-'[1]PINNACLE ADIB USD '!D31 -> 492147.06
A32: 45575 | B32: recd from quick touch technologies | C32: 999963.56 | E32: =E31+'[1]PINNACLE ADIB USD '!C32-'[1]PINNACLE ADIB USD '!D32 -> 1492110.6
A33: 45576 | B33: TRF TO DIVINE IOB | D33: 750130 | E33: =E32+'[1]PINNACLE ADIB USD '!C33-'[1]PINNACLE ADIB USD '!D33 -> 741980.62
A34: 45577 | B34: trf to pinnacle int adib | D34: 350500 | E34: =E33+'[1]PINNACLE ADIB USD '!C34-'[1]PINNACLE ADIB USD '!D34 -> 391480.62
A35: 45580 | B35: TRF TO COMIDA ADIB USD | D35: 391150 | E35: =E34+'[1]PINNACLE ADIB USD '!C35-'[1]PINNACLE ADIB USD '!D35 -> 330.62
A36: 45302 | B36: Monthly Charges | D36: 160.65 | E36: =E35+'[1]PINNACLE ADIB USD '!C36-'[1]PINNACLE ADIB USD '!D36 -> 169.97
A37: 45614 | B37: recd from quick touch technologies | C37: 699963.56 | E37: =E36+'[1]PINNACLE ADIB USD '!C37-'[1]PINNACLE ADIB USD '!D37 -> 700133.53
A38: 45615 | B38: TRF TO PREMIUM ADIB | D38: 47554 | E38: =E37+'[1]PINNACLE ADIB USD '!C38-'[1]PINNACLE ADIB USD '!D38 -> 652579.53
A39: 45615 | B39: TRF TO COMIDA ADIB USD | D39: 375136 | E39: =E38+'[1]PINNACLE ADIB USD '!C39-'[1]PINNACLE ADIB USD '!D39 -> 277443.53
A40: 45615 | B40: TRF TO CARNIFY ADIB USD | D40: 270984 | E40: =E39+'[1]PINNACLE ADIB USD '!C40-'[1]PINNACLE ADIB USD '!D40 -> 6459.53
A41: 45621 | B41: TRF TO PREMIUM ADIB | D41: 6358 | E41: =E40+'[1]PINNACLE ADIB USD '!C41-'[1]PINNACLE ADIB USD '!D41 -> 101.53
A42: 45622 | B42: RECEIVED FROM QUICK TOUCH | C42: 999963.56 | E42: =E41+'[1]PINNACLE ADIB USD '!C42-'[1]PINNACLE ADIB USD '!D42 -> 1000065.1
A43: 45622 | B43: TRANSFER TO PINNACLE INTERNATIONAL | D43: 400000 | E43: =E42+'[1]PINNACLE ADIB USD '!C43-'[1]PINNACLE ADIB USD '!D43 -> 600065.09
A44: 45622 | B44: TRANSFER TO COMIDA GOODS | D44: 600000 | E44: =E43+'[1]PINNACLE ADIB USD '!C44-'[1]PINNACLE ADIB USD '!D44 -> 65.09
A45: 45705 | B45: recd from Eagle Trans Shipping | C45: 18574.81 | E45: =E44+'[1]PINNACLE ADIB USD '!C45-'[1]PINNACLE ADIB USD '!D45 -> 18639.9
A46: 45707 | B46: bank charges | D46: 160.65 | E46: =E45+'[1]PINNACLE ADIB USD '!C46-'[1]PINNACLE ADIB USD '!D46 -> 18479.25
A47: 45707 | B47: bank charges | D47: 160.65 | E47: =E46+'[1]PINNACLE ADIB USD '!C47-'[1]PINNACLE ADIB USD '!D47 -> 18318.6
A48: 45707 | B48: bank charges | D48: 110.25 | E48: =E47+'[1]PINNACLE ADIB USD '!C48-'[1]PINNACLE ADIB USD '!D48 -> 18208.35
A49: 45707 | B49: TRF TO PREMIUM ADIB | D49: 18113 | E49: =E48+'[1]PINNACLE ADIB USD '!C49-'[1]PINNACLE ADIB USD '!D49 -> 95.35
A50: 45778 | B50: recd from quick touch technologies | C50: 499963.56 | E50: =E49+'[1]PINNACLE ADIB USD '!C50-'[1]PINNACLE ADIB USD '!D50 -> 500058.91
A51: 45778 | B51: INFINITY ADIB A/C | D51: 201339 | E51: =E50+'[1]PINNACLE ADIB USD '!C51-'[1]PINNACLE ADIB USD '!D51 -> 298719.91
A52: 45778 | B52: TT TO CENTURY CITI USD 298,511 | D52: 298511 | E52: =E51+'[1]PINNACLE ADIB USD '!C52-'[1]PINNACLE ADIB USD '!D52 -> 208.91
A53: 45780 | B53: QUICKTOUCH | C53: 999963.56 | E53: =E52+'[1]PINNACLE ADIB USD '!C53-'[1]PINNACLE ADIB USD '!D53 -> 1000172.5
A54: 45780 | B54: bank charges | D54: 105 | E54: =E53+'[1]PINNACLE ADIB USD '!C54-'[1]PINNACLE ADIB USD '!D54 -> 1000067.5
A55: 45782 | B55: TT TO CENTURY CITI USD 699,782 | D55: 699782 | E55: =E54+'[1]PINNACLE ADIB USD '!C55-'[1]PINNACLE ADIB USD '!D55 -> 300285.47
A56: 45782 | B56: TT TRANSFER TO PLOUSTOS TRADELINK USD198,315 | D56: 198315 | E56: =E55+'[1]PINNACLE ADIB USD '!C56-'[1]PINNACLE ADIB USD '!D56 -> 101970.47
A57: 45782 | B57: TT TRANSFER TO INFINITY ADIB A/C USD 101,234 | D57: 101234 | E57: =E56+'[1]PINNACLE ADIB USD '!C57-'[1]PINNACLE ADIB USD '!D57 -> 736.47
A58: 45782 | B58: bank charges | D58: 300.17 | E58: =E57+'[1]PINNACLE ADIB USD '!C58-'[1]PINNACLE ADIB USD '!D58 -> 436.3
A59: 28-5-2025 | B59: bank charges | D59: 110.25 | E59: =E58+'[1]PINNACLE ADIB USD '!C59-'[1]PINNACLE ADIB USD '!D59 -> 326.05
A60: 45817 | B60: recd from quick touch technologies | C60: 499963.56 | E60: =E59+'[1]PINNACLE ADIB USD '!C60-'[1]PINNACLE ADIB USD '!D60 -> 500289.61
A61: 45817 | B61: TT TRANSFER TO CARNIFY ADIB | D61: 228594 | E61: =E60+'[1]PINNACLE ADIB USD '!C61-'[1]PINNACLE ADIB USD '!D61 -> 271695.61
A62: 45817 | B62: TT TRANSFER TO INFINITY ADIB A/C | D62: 271306 | E62: =E61+'[1]PINNACLE ADIB USD '!C62-'[1]PINNACLE ADIB USD '!D62 -> 389.61
A63: 45836 | B63: bank charges | D63: 110.25 | E63: =E62+'[1]PINNACLE ADIB USD '!C63-'[1]PINNACLE ADIB USD '!D63 -> 279.36
E64: =E63+C64-D64 -> 279.36
E65: =E64+C65-D65 -> 279.36
E66: =E65+C66-D66 -> 279.36
E67: =E66+C67-D67 -> 279.36
E68: =E67+C68-D68 -> 279.36
E69: =E68+C69-D69 -> 279.36
E70: =E69+C70-D70 -> 279.36
E71: =E70+C71-D71 -> 279.36
E72: =E71+C72-D72 -> 279.36
E73: =E72+C73-D73 -> 279.36
E74: =E73+C74-D74 -> 279.36
E75: =E74+C75-D75 -> 279.36
... E100: =E99+C100-D100 -> 279.36

Sheet  TRADERS EIB AED
A1: TRADERS VENTURES FORFAITING LLC
A2: EIB AED ACC .NO -
A3: DATE | B3: PARTICULAR | C3: DEPOSIT | D3: WITHDRAWAL | E3: BALANCE
E4: 0
A5: 45429 | B5: RECD FROM RAYMOND WIO ACCOUNT | C5: 10000 | E5: =E4+C5-D5 -> 10000
A6: 45429 | B6: etisalat payment | D6: 375.42 | E6: =E5+C6-D6 -> 9624.58
A7: 45444 | B7: CHARGES | D7: 200 | E7: =E6+C7-D7 -> 9424.58
A8: 45444 | B8: CHARGES | D8: 10 | E8: =E7+C8-D8 -> 9414.58
A9: 45455 | B9: RECD FOR WISOR ENBD AED | C9: 111155 | E9: =E8+C9-D9 -> 120569.58
A10: 45455 | B10: TRF TO DSK LEGAL USD 30120 | D10: 110992.2 | E10: =E9+C10-D10 -> 9577.38
A11: 45455 | B11: CARD PMNT FOR DOCUSIGN EURO 396 | D11: 1914.08 | E11: =E10+C11-D11 -> 7663.3
A12: 45457 | B12: CHARGES | D12: 76.25 | E12: =E11+C12-D12 -> 7587.05
A13: 45457 | B13: etisalat payment | D13: 383.25 | E13: =E12+C13-D13 -> 7203.8
A14: 45472 | B14: etisalat payment | D14: 231 | E14: =E13+C14-D14 -> 6972.8
E15: =E14+C15-D15 -> 6972.8
E16: =E15+C16-D16 -> 6972.8
E17: =E16+C17-D17 -> 6972.8
E18: =E17+C18-D18 -> 6972.8
E19: =E18+C19-D19 -> 6972.8
E20: =E19+C20-D20 -> 6972.8
E21: =E20+C21-D21 -> 6972.8
E22: =E21+C22-D22 -> 6972.8
E23: =E22+C23-D23 -> 6972.8
E24: =E23+C24-D24 -> 6972.8
E25: =E24+C25-D25 -> 6972.8
E26: =E25+C26-D26 -> 6972.8
... E100: =E99+C100-D100 -> 6972.8

Sheet TRADERS EIB USD
A1: TRADERS VENTURES FORFAITING LLC
A2: EIB USD ACC .NO -
A3: DATE | B3: PARTICULAR | C3: DEPOSIT | D3: WITHDRAWAL | E3: BALANCE
E4: 0
E5: =E4+C5-D5 -> 0
E6: =E5+C6-D6 -> 0
E7: =E6+C7-D7 -> 0
E8: =E7+C8-D8 -> 0
E9: =E8+C9-D9 -> 0
E10: =E9+C10-D10 -> 0
E11: =E10+C11-D11 -> 0
E12: =E11+C12-D12 -> 0
E13: =E12+C13-D13 -> 0
E14: =E13+C14-D14 -> 0
E15: =E14+C15-D15 -> 0
E16: =E15+C16-D16 -> 0
... E100: =E99+C100-D100 -> 0

Sheet PREMIUM SIB AED 
A1: PREMIUM EXIM GENERAL TRADING LLC
A2: SIB BANK AED ACC .NO -
A3: DATE | B3: PARTICULAR | C3: DEPOSIT | D3: WITHDRAWAL | E3: BALANCE
E4: 68.81
D5: 5.25 | E5: =E4+C5-D5 -> 63.56
A6: 18-11-2023 | B6: BANK CHARGES | D6: 157.5 | E6: =E5+C6-D6 -> -93.94
A7: 14-12-2023 | B7: RECD NATIO RAW | C7: 921243.75 | E7: =E6+C7-D7 -> 921149.81
A8: 14-12-2023 | B8: TRF NIYAT SIB AED | D8: 15000 | E8: =E7+C8-D8 -> 906149.81
A9: 14-12-2023 | B9: TRF NIYAT SIB AED | D9: 906023 | E9: =E8+C9-D9 -> 126.81
A10: 45293 | B10: BANK CHARGES | D10: 162.75 | E10: =E9+C10-D10 -> -35.94
A11: 05.01.2024 | B11: RECD HEDGES FAB AED | C11: 151734 | E11: =E10+C11-D11 -> 151698.06
A12: 45299 | B12: TRF TO COMIDA WIO | D12: 151060 | E12: =E11+C12-D12 -> 638.06
A13: 45299 | B13: charges | D13: 1.05 | E13: =E12+C13-D13 -> 637.01
A14: 45307 | B14: ETISALAT PAYMENT | D14: 454.97 | E14: =E13+C14-D14 -> 182.04
A15: 45322 | B15: charges | D15: 5.25 | E15: =E14+C15-D15 -> 176.79
D16: 157.46 | E16: =E15+C16-D16 -> 19.33
A17: 45338 | B17: RECD RHINE ADIB | C17: 2531 | E17: =E16+C17-D17 -> 2550.33
A18: 45338 | B18: etisalat PAYMENT | D18: 416.85 | E18: =E17+C18-D18 -> 2133.48
A19: 45338 | B19: ETISALAT PAYMENT | D19: 220.4 | E19: =E18+C19-D19 -> 1913.08
A20: 45338 | B20: dewa | D20: 1054.94 | E20: =E19+C20-D20 -> 858.14
A21: 45351 | B21: charges | D21: 164.34 | E21: =E20+C21-D21 -> 693.8
A22: 45351 | B22: charges | D22: 157.5 | E22: =E21+C22-D22 -> 536.3
A23: 45360 | B23: RECD FROM ALHAMBRA TRADING FZCO | C23: 487813.75 | E23: =E22+C23-D23 -> 488350.05
A24: 45360 | B24: RENT PAYMENT NAKHEEL RESIDENTIAL PROPERTIES LLC | D24: 24397.75 | E24: =E23+C24-D24 -> 463952.3
A25: 45360 | B25: TRF TO M J S STAR WIO AED | D25: 458966 | E25: =E24+C25-D25 -> 4986.3
A26: 45369 | B26: LANDLINE HOME PMNT | D26: 418.95 | E26: =E25+C26-D26 -> 4567.35
A27: 45369 | B27: LANDLINE OFFICE PMNT | D27: 219.45 | E27: =E26+C27-D27 -> 4347.9
A28: 45369 | B28: SIGMA 401 HOME PMNT | D28: 342.75 | E28: =E27+C28-D28 -> 4005.15
A29: 45381 | B29: charges | D29: 320.25 | E29: =E28+C29-D29 -> 3684.9
A30: 45397 | B30: LANDLINE HOME PMNT | D30: 418.95 | E30: =E29+C30-D30 -> 3265.95
A31: 45397 | B31: LANDLINE HOME PMNT | D31: 235.52 | E31: =E30+C31-D31 -> 3030.43
A32: 45400 | B32: BILL PAYMENT | D32: 270.89 | E32: =E31+C32-D32 -> 2759.54
A33: 45400 | B33: BILL PAYMENT | D33: 331.22 | E33: =E32+C33-D33 -> 2428.32
A34: 45404 | B34: BILL PAYMENT | D34: 80.88 | E34: =E33+C34-D34 -> 2347.44
A35: 45409 | B35: VAT PAYMENT | D35: 953.96 | E35: =E34+C35-D35 -> 1393.48
... A39: 45426 | B39: BILL PAYMENT | D39: 221.34 | E39: =E38+C39-D39 -> 224.01
A40: 45429 | B40: TT RECD FROM RHINE SIB A/C | C40: 3500 | E40: =E39+C40-D40 -> 3724.01
B41: dewa | D41: 259.86 | E41: =E40+C41-D41 -> 3464.15
B42: dewa | D42: 719 | E42: =E41+C42-D42 -> 2745.15
D43: 5.25 | E43: =E42+C43-D43 -> 2739.9
D44: 315 | E44: =E43+C44-D44 -> 2424.9
A45: 45446 | B45: TT RECD FROM pinnacle int | C45: 94140 | E45: =E44+C45-D45 -> 96564.9
A46: 45446 | B46: tt transfer to niyat sib | D46: 95167 | E46: =E45+C46-D46 -> 1397.9
A47: 45455 | B47: card pmnts to ICP ervices | D47: 153.747 | E47: =E46+C47-D47 -> 1244.153
A48: 45457 | B48: ETISALAT PAYMENT | D48: 219.77 | E48: =E47+C48-D48 -> 1024.383
A49: 45457 | B49: ETISALAT PAYMENT | D49: 208.93 | E49: =E48+C49-D49 -> 815.453
A50: 45457 | B50: ETISALAT PAYMENT | D50: 396.78 | E50: =E49+C50-D50 -> 418.673
A51: 45461 | B51: recd from pinnacle group mashreq aed | C51: 13684 | E51: =E50+C51-D51 -> 14102.673
A52: 45463 | B52: clearing cheque no 000011 | D52: 13250 | E52: =E51+C52-D52 -> 852.673
A53: 45463 | D53: 627.22 | E53: =E52+C53-D53 -> 225.453
A54: 45474 | B54: bank charges | D54: 225.45 | E54: =E53+C54-D54 -> 0.0030000001
A55: 45493 | B55: recd from rhine sib | C55: 985 | E55: =E54+C55-D55 -> 985.003
A56: 45493 | B56: recd from rhine ENBD | C56: 986 | E56: =E55+C56-D56 -> 1971.003
A57: 45493 | B57: dewa pmnt | D57: 240 | E57: =E56+C57-D57 -> 1731.003
A58: 45493 | B58: dewa pmnt | D58: 350 | E58: =E57+C58-D58 -> 1381.003
A59: 45493 | B59: dewa pmnt | D59: 590 | E59: =E58+C59-D59 -> 791.003
A60: 45493 | B60: dewa pmnt | D60: 210 | E60: =E59+C60-D60 -> 581.003
A61: 45493 | B61: dewa pmnt | D61: 420 | E61: =E60+C61-D61 -> 161.003
A62: 45497 | B62: AHR recovery charges | D62: 116.69 | E62: =E61+C62-D62 -> 44.313
B63: bank charges | D63: 162.75 | E63: =E62+C63-D63 -> -118.437
B64: bank charges | D64: 157.5 | E64: =E63+C64-D64 -> -275.937
B65: bank charges | D65: 320.25 | E65: =E64+C65-D65 -> -596.187
A66: 45554 | B66: RECD FROM | C66: 2049 | E66: =E65+C66-D66 -> 1452.813
A67: 45554 | B67: RECD FROM ROYAL ENBD | C67: 14129 | E67: =E66+C67-D67 -> 15581.813
A68: 45555 | B68: cheque 000002 | D68: 13250 | E68: =E67+C68-D68 -> 2331.813
A69: 45558 | B69: RECD FROM ROYAL ENBD | C69: 110845 | E69: =E68+C69-D69 -> 113176.81
A70: 45558 | B70: TRF TO GLOBAL IMPEX ICICI USD 30000 | D70: 110465.4 | E70: =E69+C70-D70 -> 2711.413
D71: 320.25 | E71: =E70+C71-D71 -> 2391.163
C72: 108550 | E72: =E71+C72-D72 -> 110941.16
D73: 108221 | E73: =E72+C73-D73 -> 2720.163
D74: 1.05 | E74: =E73+C74-D74 -> 2719.113
A75: 45588 | B75: DEWA PMNT | D75: 341 | E75: =E74+C75-D75 -> 2378.113
A76: 45588 | B76: DEWA PMNT | D76: 679.46 | E76: =E75+C76-D76 -> 1698.653
A77: 45588 | B77: ETISALAT PMNT | D77: 208.93 | E77: =E76+C77-D77 -> 1489.723
A78: 45593 | B78: vat | D78: 1018.2 | E78: =E77+C78-D78 -> 471.523
A79: 45576 | B79: Monthly Bank Charges | D79: =5+150+150+15.25 -> 320.25 | E79: =E78+C79-D79 -> 151.273
A80: 45573 | B80: RECD FROM CARNIFY ENBD | C80: 16864 | E80: =E79+C80-D80 -> 17015.273
A81: 45608 | B81: CLEARing cheque no 000015 | D81: 16800 | E81: =E80+C81-D81 -> 215.273
A82: 45627 | B82: charges | D82: 320.25 | E82: =E81+C82-D82 -> -104.977
A83: 45645 | B83: RECD FROM HEDGES ADIB | C83: 13619 | E83: =E82+C83-D83 -> 13514.023
A84: 45646 | B84: cheque cleared | D84: 13250 | E84: =E83+C84-D84 -> 264.023
D85: 320.25 | E85: =E84+C85-D85 -> -56.227
A86: 45740 | B86: charges | D86: 168 | E86: =E85+C86-D86 -> -224.227
E87: =E86+C87-D87 -> -224.227
E88: =E87+C88-D88 -> -224.227
E89: =E88+C89-D89 -> -224.227
E90: =E89+C90-D90 -> -224.227
E91: =E90+C91-D91 -> -224.227
E92: =E91+C92-D92 -> -224.227
E93: =E92+C93-D93 -> -224.227
E94: =E93+C94-D94 -> -224.227
E95: =E94+C95-D95 -> -224.227
E96: =E95+C96-D96 -> -224.227
E97: =E96+C97-D97 -> -224.227
E98: =E97+C98-D98 -> -224.227
... E100: =E99+C100-D100 -> -224.227

Sheet PREMIUM SIB USD
A1: PREMIUM EXIM GENERAL TRADING LLC
A2: SIB BANK USD ACC .NO -
A3: DATE | B3: PARTICULAR | C3: DEPOSIT | D3: WITHDRAWAL | E3: BALANCE
E4: 286.18
D5: 1.43 | E5: =E4+C5-D5 -> 284.75
A6: 01.12.2023 | B6: BANK CHARGES | D6: 157.5 | E6: =E5+C6-D6 -> 127.25
A7: 45293 | B7: BANK CHARGES | D7: 157.5 | E7: =E6+C7-D7 -> -30.25
A8: 45303 | B8: charges | D8: 1.43 | E8: =E7+C8-D8 -> -31.68
D9: 158.93 | E9: =E8+C9-D9 -> -190.61
D10: 1.43 | E10: =E9+C10-D10 -> -192.04
D11: 157.5 | E11: =E10+C11-D11 -> -349.54
A12: 45412 | B12: charges | D12: 160.36 | E12: =E11+C12-D12 -> -509.9
A13: 45412 | B13: charges | D13: 157.5 | E13: =E12+C13-D13 -> -667.4
B14: bank charges | D14: 318 | E14: =E13+C14-D14 -> -985.4
B15: charges | D15: 318.02 | E15: =E14+C15-D15 -> -1303.42
B16: charges | D16: 158.63 | E16: =E15+C16-D16 -> -1462.05
B17: charges | D17: 794.65 | E17: =E16+C17-D17 -> -2256.7
E18: =E17+C18-D18 -> -2256.7
E19: =E18+C19-D19 -> -2256.7
E20: =E19+C20-D20 -> -2256.7
E21: =E20+C21-D21 -> -2256.7
E22: =E21+C22-D22 -> -2256.7
E23: =E22+C23-D23 -> -2256.7
E24: =E23+C24-D24 -> -2256.7
E25: =E24+C25-D25 -> -2256.7
E26: =E25+C26-D26 -> -2256.7
E27: =E26+C27-D27 -> -2256.7
E28: =E27+C28-D28 -> -2256.7
E29: =E28+C29-D29 -> -2256.7
... E100: =E99+C100-D100 -> -2256.7

Sheet AL GARHOUD WIO AED 
A1: AL GARHOUD GENERAL TRADING LLC
A2: WIO BANK AED ACC .NO -
A3: DATE | B3: PARTICULAR | C3: DEPOSIT | D3: WITHDRAWAL | E3: BALANCE
E4: 270.65
A5: 24-11-2023 | B5: RECD COMIDA WIO AED | C5: 8650 | E5: =E4+C5-D5 -> 8920.65
A6: 28-11-2023 | B6: CHEQUE 000003 | D6: 8500 | E6: =E5+C6-D6 -> 420.65
A7: 28-11-2023 | B7: RECD MARKET 24 FZ LLC | C7: 110000 | E7: =E6+C7-D7 -> 110420.65
A8: 28-11-2023 | B8: ROYAL WIO AED | C8: 35985 | E8: =E7+C8-D8 -> 146405.65
A9: 28-11-2023 | B9: B V AND R COMMODITIES CORP | D9: 146102.02 | E9: =E8+C9-D9 -> 303.63
A10: 28-11-2023 | B10: CHARGES | D10: 52.5 | E10: =E9+C10-D10 -> 251.13
A11: 45181 | B11: BANK CHARGES | D11: 99 | E11: =E10+C11-D11 -> 152.13
A12: 16-12-2023 | B12: CASH DEPOSTI | C12: 6200 | E12: =E11+C12-D12 -> 6352.13
A13: 18-12-2023 | B13: CASH DEPOSTI | C13: 5400 | E13: =E12+C13-D13 -> 11752.13
A14: 18-12-2023 | B14: ETISALAT PAYMENT | D14: 4284 | E14: =E13+C14-D14 -> 7468.13
A15: 45279 | B15: ETISALAT AL GARHOUD HOME 202 | D15: 313.95 | E15: =E14+C15-D15 -> 7154.18
A16: 45279 | B16: DEWA AL GARHOUD HOME 202 | D16: 286.16 | E16: =E15+C16-D16 -> 6868.02
A17: 45279 | B17: CHEQUE 000008 | D17: 6176 | E17: =E16+C17-D17 -> 692.02
A18: 45286 | B18: CASH DEPOSTI | C18: 2000 | E18: =E17+C18-D18 -> 2692.02
A19: 45286 | B19: VAT PAYMENT | D19: 2044.43 | E19: =E18+C19-D19 -> 647.59
A20: 45297 | B20: CASH DEPOSTI | C20: 7200 | E20: =E19+C20-D20 -> 7847.59
A21: 45297 | B21: CASH DEPOSTI | C21: 7500 | E21: =E20+C21-D21 -> 15347.59
A22: 45297 | D22: 14807.5 | E22: =E21+C22-D22 -> 540.09
A23: 45302 | B23: CHARGES | D23: 99 | E23: =E22+C23-D23 -> 441.09
A24: 45302 | B24: RECD FROM RHINE WIO | C24: 167525 | E24: =E23+C24-D24 -> 167966.09
A25: 45302 | B25: TRF METELLOY LINKERS | D25: 82869.31 | E25: =E24+C25-D25 -> 85096.78
A26: 45302 | B26: CHARGES | D26: 52.5 | E26: =E25+C26-D26 -> 85044.28
A27: 45302 | B27: TRF METELLOY LINKERS | D27: 84544.53 | E27: =E26+C27-D27 -> 499.75
A28: 45302 | B28: CHARGES | D28: 52.5 | E28: =E27+C28-D28 -> 447.25
A29: 45309 | B29: PAYMENT ETISALAT | D29: 313.95 | E29: =E28+C29-D29 -> 133.3
A30: 45314 | B30: RECD RHINE WIO | C30: 32855 | E30: =E29+C30-D30 -> 32988.3
A31: 45314 | B31: TRF TO HEDGES WIO | D31: 32851 | E31: =E30+C31-D31 -> 137.3
A32: 45321 | B32: RECD RHINE ADIB | C32: 184128 | E32: =E31+C32-D32 -> 184265.3
A33: 45321 | B33: TRANSFERRED TO USD | D33: 184000 | E33: =E32+C33-D33 -> 265.3
A34: 45338 | B34: RECD RHINE WIO | C34: 2028 | E34: =E33+C34-D34 -> 2293.3
A35: 45327 | B35: CREDIT TRANSACTION | D35: 210 | E35: =E34+C35-D35 -> 2083.3
A36: 45338 | B36: CHARGES | D36: 99 | E36: =E35+C36-D36 -> 1984.3
A37: 45341 | B37: ETISALAT PAYMENT | D37: 313.95 | E37: =E36+C37-D37 -> 1670.35
A38: 45345 | B38: TRF TO COMIDA WIO AED | D38: 1670 | E38: =E37+C38-D38 -> 0.35
E39: =E38+C39-D39 -> 0.35
E40: =E39+C40-D40 -> 0.35
E41: =E40+C41-D41 -> 0.35
E42: =E41+C42-D42 -> 0.35
E43: =E42+C43-D43 -> 0.35
E44: =E43+C44-D44 -> 0.35
E45: =E44+C45-D45 -> 0.35
E46: =E45+C46-D46 -> 0.35
E47: =E46+C47-D47 -> 0.35
E48: =E47+C48-D48 -> 0.35
E49: =E48+C49-D49 -> 0.35
E50: =E49+C50-D50 -> 0.35
... E100: =E99+C100-D100 -> 0.35

Sheet AL GARHOUD WIO USD
A1: AL GARHOUD GENERAL TRADING LLC
A2: WIO BANK USD ACC .NO -
A3: DATE | B3: PARTICULAR | C3: DEPOSIT | D3: WITHDRAWAL | E3: BALANCE
E4: 0.54
A5: 45272 | B5: RECD IMPACTONE GROUP AG | C5: 30000 | E5: =E4+C5-D5 -> 30000.54
A6: 13-12-2023 | B6: TRF SINO RISE INDUSTRY CO LTD | D6: 30000 | E6: =E5+C6-D6 -> 0.54
A7: 45311 | B7: RECD FROM SILICON UDYOG | C7: 314.73 | E7: =E6+C7-D7 -> 315.27
A8: 45321 | B8: RECD FROM AED ACCOUNT | C8: 50095.29 | E8: =E7+C8-D8 -> 50410.56
A9: 45321 | B9: TRF TO HEDGES AL MASRAF | D9: 50380 | E9: =E8+C9-D9 -> 30.56
A10: 45321 | B10: CHARGES | D10: 30.45 | E10: =E9+C10-D10 -> 0.11
E11: =E10+C11-D11 -> 0.11
E12: =E11+C12-D12 -> 0.11
E13: =E12+C13-D13 -> 0.11
E14: =E13+C14-D14 -> 0.11
E15: =E14+C15-D15 -> 0.11
E16: =E15+C16-D16 -> 0.11
E17: =E16+C17-D17 -> 0.11
E18: =E17+C18-D18 -> 0.11
E19: =E18+C19-D19 -> 0.11
E20: =E19+C20-D20 -> 0.11
E21: =E20+C21-D21 -> 0.11
E22: =E21+C22-D22 -> 0.11
... E126: =E125+C126-D126 -> 0.11
E128: 0
E129: =E128+C129-D129 -> 0
E130: =E129+C130-D130 -> 0
E131: =E130+C131-D131 -> 0
E132: =E131+C132-D132 -> 0
E133: =E132+C133-D133 -> 0
E134: =E133+C134-D134 -> 0
E135: =E134+C135-D135 -> 0
E136: =E135+C136-D136 -> 0
E137: =E136+C137-D137 -> 0
E138: =E137+C138-D138 -> 0
E139: =E138+C139-D139 -> 0
E140: =E139+C140-D140 -> 0
... E202: =E201+C202-D202 -> 0

Sheet NIYAT SIB AED 
A1: NIYAT GOODS WHOLESALERS LLC
A2: SIB BANK AED ACC .NO -
A3: DATE | B3: PARTICULAR | C3: DEPOSIT | D3: WITHDRAWAL | E3: BALANCE
E4: 13.83
A5: 30-11-2023 | B5: BANK CHARGES | D5: 5.25 | E5: =E4+C5-D5 -> 8.58
A6: 30-11-2023 | B6: RECD | C6: 50000 | E6: =E5+C6-D6 -> 50008.58
A7: 30-11-2023 | B7: TRF ROYAL WIO AED | D7: 49865 | E7: =E6+C7-D7 -> 143.58
A8: 44938 | B8: BANK CHARGES | D8: 158 | E8: =E7+C8-D8 -> -14.42
A9: 45089 | B9: RECD BLUE FIRE WIO AED | C9: 7380 | E9: =E8+C9-D9 -> 7365.58
A10: 45089 | B10: OWN ACC AED TO USD | D10: 6996.14 | E10: =E9+C10-D10 -> 369.44
A11: 14-12-2023 | B11: RECD PREMIUM SIB AED | C11: 15000 | E11: =E10+C11-D11 -> 15369.44
A12: 14-12-2023 | B12: RECD PREMIUM SIB AED | C12: 906023 | E12: =E11+C12-D12 -> 921392.44
A13: 14-12-2023 | B13: TRF COMIDA WIO AED | D13: 908145 | E13: =E12+C13-D13 -> 13247.44
A14: 14-12-2023 | B14: CHARGES | D14: 1.05 | E14: =E13+C14-D14 -> 13246.39
A15: 18-12-2023 | B15: NIYAT 310 DEWA | D15: 637.6 | E15: =E14+C15-D15 -> 12608.79
A16: 18-12-2023 | B16: NIYAT 310 ETISALAT | D16: 543.9 | E16: =E15+C16-D16 -> 12064.89
A17: 45286 | B17: FTA VAT PAYMENT | D17: 2369.04 | E17: =E16+C17-D17 -> 9695.85
A18: 45287 | B18: TRF PREMIER COM | D18: 5250 | E18: =E17+C18-D18 -> 4445.85
A19: 45287 | B19: CHARGES | D19: 0.5 | E19: =E18+C19-D19 -> 4445.35
A20: 45288 | B20: CHARGES | D20: 17 | E20: =E19+C20-D20 -> 4428.35
